Workbook

Sheet Title
D9: Information Technology Service Agreement System Interface Specification (FIX) for Market Data Distribution System
H17: 2019

Sheet History
A2: Release/Revision history
A4: No | B4: Version | C4: Date | D4: Release/Revision Description | E4: Author
A5: 1 | B5: 0.9 | C5: 2017.06.02 | D5: Initial Writing | E5: Dongeun Kim
A6: 2 | B6: 0.91 | C6: 2017.06.05 | D6: Revision of New Messages being Defined for Vietnam BR | E6: Dongeun Kim
A7: 3 | B7: 0.92 | C7: 2017.07.19 | D7: Revision of Message Structures | E7: Dongeun Kim
A8: 4 | B8: 0.97 | C8: 2017.10.20 | D8: Definition of Tags as Requirements and Revision of Messages | E8: Dongeun Kim
A9: 5 | B9: 0.99 | C9: 2017.11.01 | D9: Add the purposes in Inteface List tab Modify the names of messages referring to the names of usecases | E9: Dongeun Kim
A10: 6 | B10: 0.992 | C10: 2017.11.17 | D10: Split the 'Comment' column to 'Field Meaning' and 'Possible Value' Fill and modify the meaning/possible value of all the words in Tag(Glossary) | E10: Dongeun Kim
A11: 7 | B11: 0.993 | C11: 2017.11.23 | D11: Check the message to MSS in the interface list. | E11: Dongeun Kim
A12: 8 | B12: 0.994 | C12: 2017.12.06 | D12: Update the purposes into detail in Interface List tab Update 'Required' fileds in each interface definition tab | E12: Dongeun Kim
A13: 9 | B13: 0.995 | C13: 2017.12.15 | D13: 1. Modify the definition of tag NoMDEntries(268) and MarketMakerContractCode(30574) 2. Add a new message 'Random End' and add 'Random End Triggering Condition Code' in the definition of Security Definition with related tags 3. Delete 'UnderlyingSecurityID' in the definition of Security Definition, and delete 'BoardEvtID' and 'BoardEvtStartTime' in the definition of Security Status 4. Add 'English Symbol' and 'VWAP' to Tag(Glossary) and Security Definition 5. Update values of user-defined tags from 8000/10000 to 20000/30000 6. Update the Online/Batch type value of Index and Disclosure in Interface List 7. Synchronize the definition of tags with the specification document from trading channel | E13: Dongeun Kim
A14: 10 | B14: 0.996 | C14: 2018.01.12 | D14: 1. Update the entire Field Meanings of the sheet Tag(Glossary) based on other output documents 2. Add SymbolCloseInfoPxType(20027) to the definition of Security Definition 3. Modify the Field Meaning and length of TotalPage(30606) and CurrentPage(30607), and add those fields to 'Index Constituents Information' message | E14: Dongeun Kim
A15: 11 | B15: 0.997 | C15: 2018.01.19 | D15: 1. Modify the field name and meaning ClassID(20009) to ProductID(20009) 2. Delete the tag SecurityGroup(1151) and modify the tags in definition to ProductID(20009) 3. Delete checks of the messages to MSS in interface list 4. Move the message 'RandomEnd(MW)' to trans type of market data in interface list 5. Delete the message 'Dynamic Price Limit(MG)' which is not included in VN 6. Delete the message 'Issuer Information(MJ)' and 'Member(Dealer) Information(MK)' as change of business requirement 7. Add the message 'Price Limit Expansion(MX)' and 'Quantity Allocation(MY)' in interface list 8. Modify field meaning and length of DisparateRatio(30602) to merge with DisparateSign(30601), and delete DisparateSign(30601) 9. Modify the name and fields of the message 'Reference Price Determination(M7)' to 'Security Information Notification(M7)' 10. Add ListedShares(20020) to the definition of Security Definition 11. Modify field meaning and possible value of all the tags to synchronize their definition of the document VN_CHN_DS_System Interface Specification(FIX) | E15: Dongeun Kim
A16: 12 | B16: 0.9971 | C16: 2018.02.09 | D16: 1. Modify the field meaning of ForeignerOrderLimitQty(30558) in Tag(Glossary) 2. Remove the possible values of Tag(Glossary) that are not used in VN system. 3. Remove ForeignerLimitRatio(30598) from the message 'Foreigner Order Limit(MF)' 4. Modify the tag name of 30606, 30607 for more general meaning. 5. Delete the message Open Interest(type=MA) due to the modification of business in VSD. | E16: Dongeun Kim
A17: 13 | B17: 0.9974 | C17: 2018.02.20 | D17: 1. Add the tag SecurityID(48); change all the definition using Symbol(55) to SecurityID(48). 2. Remove the tag EnglishSymbol(30624); change the tag EnglishSymbol(30624) in the definition of 'Security Definition' to Symbol(55), and modify the definition of Symbol(55) 3. Delete the field HaltReason(327) from the definition of Security Status 4. Modify the possible value of the tag SecurityStatus(965) and ForeignInvestorTypeCode(30581) 5. Add a new tag TscProductGroupID(30628) to be substituted the tag SecurityType(167) 6. Modify the field meaning of the tag ForeignerOrderLimitQty(30558) 7. Modify the field meaning of the tag Yield(236) in Tag(Glossary) 8. Add a new tag DynamicVIBasePrice(20047) and DynamicVIDispartiyRatio(20048) in 'Volatility Interruption' 9. Delete the tag MarketMakerContractCode(30574) in 'Market Maker Information' 10. Add the tag SecurityID(48) and SecurityIDSource(22) in 'Market Maker Information' 11. Modify the field meaning of the tag TotalMsgNo(30606) and CurrentMsgNo(30607) 12. Modify the field meaning of the tag SellTotOrderQty(30521), BuyTotOrderQty(30522), SellValidOrderCnt(30523), BuyValidOrderCnt(30524) 13. Change wording in every field meaning: issue → security 14. Update definition of ‘number” format length 15. Delete 'Security Board(M6)' message; its purpose (to list securities) is covered by 'Security Definition(d)' | E17: Dongeun Kim
A18: 14 | B18: 0.998 | C18: 2018.02.27 | D18: 1. Merge the definition of the messages Price + Price(Bond), Deem Trade Price + Deem Trade Price(Bond) 2. Rollback the modification 1. and 2. in the version 0.9973; SecurityID(48) => Symbol(55), Symbol(55) => EnglishSymbol(30624) 3. Delete SecurityIDSource(22) in the Tag(Glossary) and all the definitions | E18: Dongeun Kim
A19: 15 | B19: 0.9981 | C19: 2018.03.02 | D19: 1. Change the field name of EnglishSymbol(30624) to TickerCode(30624) 2. Add new tags SymbolShortCode(30628), SymbolName(30629), SymbolEnglishName(30630) 3. Add SymbolShortCode(30628), SymbolName(30629), SymbolEnglishName(30630) and remove SecurityDesc(107) in the definition of 'SecurityDefinition' 4. Modify the field meaning of Symbol(55) | E19: Dongeun Kim
A20: 16 | B20: 0.9982 | C20: 2018.03.09 | D20: 1. Modify the possible value of TransactTime(60) from YYYYMMDD HH:MM:SS.sss to HHmmSSsss 2. Modify the length of PriceFluctuationRatio(30603) from 9 to 10 3. Delete repeating groups in the definition of 'Trading Result of Foreign Investors(MT)', and delete the tag FornInvestTypeCode(20054); the output is sum of trading results for foreign investors 4. Modify the SecurityDesc(107) to SymbolName(30629) in the definition of 'Disclosure(MU)' 5. Modify the length of ContractMultiplier(231) from 20 to 22(12.8) 6. Modify the length of CouponRate(223) from 14(9.4) to 14(7.5) 7. Modify the length of tags related to trading price from 14(9.4) to 15(9.4) 8. Modify the length of TotalMsgNo(30606) and CurrentMsgNo(30607) from 11 to 15 9. Add SecurityGroupID(30604) in the definition of 'Security Definition(d)' 10. Add new tag ContractSize(30631) to modify the item UnitOfMeasureQty(1147) in 'Security Definition(d)' 11. Delete the tags not used in MDDS 12. Modify the format of all the tags whose formats are 'Number' to 'Price', 'Int' or 'Float' 13. Delete the message 'Quantity Allocation(MY)'; it is not the information distributed by MDDS, which means it is not essencial to receive market data 14. Modify the history of omitted content History No.13 | E20: Dongeun Kim
A21: 17 | B21: 0.9983 | C21: 2018.03.19 | D21: 1. Modify the definitions of tags to synchronize the output of other parts 2. Delete the tags not used in MDDS 3. Add new tags IdxName(30632) and IdxEnglishName(30633), and add the tags to 'Index Constituents Information(ML)' in the definition 4. Rollback the deletion of tag OpenInterestQty(30540) for error correction 5. Modify the length of TransactTime(60) from 21 to 9; MDDS uses this field without date information 6. Modify the tag Symbol(55) to MarketMakerContractUnit(30574) in the definition of message 'Market Maker Information(MH)'; Rollback the modification 9. and 10. in the version 0.9974 7. Modify the possible values of MsgType(35) in the sheet 'Header' 8. Delete BordID(20054) in the definition of 'Investor per Industry(M2)', 'Investor per Symbol(M3)', 'Top N Members per Symbol(M4)', 'Top N Symbols(MP, MQ, MR, MS)'; those statistics merges not per {Symbol, Board} but per {Symbol}. 9. Rollback the deletion of the message 'Open Interest(MA)' as EOD distribution 10. Rollback the deletion of repeating groups in the definition of 'Trading Result of Foreign Investors(MT)' which is history No.3 in the version 0.9982 | E21: Dongeun Kim
... A46: 41 | B46: 0.9A16 | C46: 2023.09.05 | D46: 1. Delete TransactTime(60) from the definition of 'Open Interest(MA)' 2. Modify Req'd field of SellTotOrderQty, BuyTotOrderQty, SellValidOrderCnt, BuyValidOrderCnt, NumberOfOrders in 'Price Recovery(W)' 3. Modify the description of possible values for MDEntryType(269) 4. Add the message '(Block Trade) Price Recovery (W)' and '(Block Trade) Price Recovery (Bond) (W)' in interface list | E46: Hyungshik Ju

Sheet Guildline
B2: Guideline
B4: No. | C4: Sort | D4: Item | E4: Guideline
B5: 1 | C5: Interface List | D5: TransType | E5: Write the Sending Message Type.
B6: 2 | C6: Interface List | D6: Interface ID | E6: Assign ID to verify the interface. - Rules for assigning Interface ID : VN_Business Code(3 Digits) of Sending System_IF_Message Format_Serial Number - Message Format : FIX, FL(Fixed Length) etc. Ex) If sender is Trading system : VN_TRS_IF_FIX_0001
B7: 3 | C7: Interface List | D7: Interface Name | E7: Write the FIX Message title. Go to the Interface Definition when clicking title.
B8: 4 | C8: Interface List | D8: MsgType | E8: Write the type of the message.
B9: 5 | C9: Interface List | D9: Realtime/Batch | E9: R: Realtime B: Batch
B10: 6 | C10: Interface List | D10: Timing | E10: Timing code of message communication - DO: Day Opening (Before or At Market Opening) - ONO: Online (From Day Opening until Market Closing) - ONT: Online (Trading Hours) - ONB: Online (From Market Opening until Daily Batch) - ALL: All Day - MC: Market Closing - DB: Daily Batch - DC: Day Closing (EOD, End of Day)
B11: 7 | C11: Interface List | D11: Transmission Protocol | E11: Write Sending Protocols. - TCP/IP, UDP, etc.
B12: 8 | C12: Interface List | D12: Interface System - FROM | E12: Post '○' on the 'From' system of the Interface.
B13: 9 | C13: Interface List | D13: Interface System - TO | E13: Post '■' on the 'Final Destination(To)' system of the Interface. ※ If Passing Through System is available, then post '□'.
B14: 10 | C14: Interface List | D14: Purpose | E14: Write Remarks and purpose of the message
C16: Inferface Definition | E16: Write Interface Definition Sheet after the Interface List Sheet with the following steps as below. - Tag : Write information of entire Tag that have been used in Interface Definition. - Header : (Common Information) Write Header information of the message. - Add sheet per Interface Receiving System.
B17: 1 | C17: Inferface Definition | D17: Interface ID | E17: Same with the guideline for the interface list above.
B18: 2 | C18: Inferface Definition | D18: Interface Name | E18: Same with the guideline for the interface list above.
B19: 3 | C19: Inferface Definition | D19: Tag | E19: Write Tag number.
B20: 4 | C20: Inferface Definition | D20: Field Name | E20: Write the Field Name.
B21: 5 | C21: Inferface Definition | D21: Req'd | E21: Post 'Y', if it is the required field.
B22: 6 | C22: Inferface Definition | D22: Format | E22: Write the data format of the field.
B23: 7 | C23: Inferface Definition | D23: Length | E23: Write the length of the field.
B24: 8 | C24: Inferface Definition | D24: Comments | E24: Write the definition including the purpose of the field.

Sheet Interface List
B2: Interface List - MDS
B4: No | C4: TransType | D4: Interface ID | E4: Interface Name | F4: MsgType | G4: Realtime /Batch | H4: Timing | I4: Transmission Protocol | J4: Interface System | AJ4: Purpose | AK4: Remark
J5: From | W5: TO
J6: CHN | K6: BND | L6: ME | M6: TRS | N6: M I S | O6: MDS | P6: I N X | Q6: R D S | R6: C S S | S6: DRS | T6: M S S | U6: MEM | V6: BANK | W6: CHN | X6: BND | Y6: ME | Z6: TRS | AA6: M I S | AB6: MDS | AC6: I N X | AD6: R D S | AE6: C S S | AF6: DRS | AG6: M S S | AH6: MEM | AI6: BANK
B7: 1 | C7: Tag | D7: - | E7: FIX Tag | H7: -
B8: 2 | C8: Header | D8: - | E8: FIX Header | H8: -
B9: 3 | C9: Trailer | D9: - | E9: FIX Trailer | H9: -
B10: 4 | C10: ReferenceData | D10: IFMDFIX0001 | E10: Security Definition | F10: d | G10: B | H10: DO | I10: UDP | O10: ○ | AH10: ■ | AJ10: Distribute reference data to receive market data for a security
B11: 5 | D11: IFMDFIX0002 | E11: Security Status | F11: f | G11: R | H11: ONT | I11: UDP | O11: ○ | AH11: ■ | AJ11: Distribute market control to change the status of a security
B12: 7 | D12: IFMDFIX0003 | E12: Security Information Notification | F12: M7 | G12: R | H12: ONT | I12: UDP | O12: ○ | AH12: ■ | AJ12: Distribute determination/notification of reference price, valuation price, or list of shares among market control
B13: 8 | D13: IFMDFIX0004 | E13: Symbol Closing Information | F13: M8 | G13: B | H13: MC | I13: UDP | O13: ○ | AH13: ■ | AJ13: Distribute symbol closing information among market control
B14: 9 | D14: IFMDFIX0005 | E14: Volatility Interruption | F14: MD | G14: R | H14: ONT | I14: UDP | O14: ○ | AH14: ■ | AJ14: Distribute volatility interruption message among market control
B15: 10 | D15: IFMDFIX0006 | E15: Market Maker Information | F15: MH | G15: B | H15: DO | I15: UDP | O15: ○ | AH15: ■ | AJ15: Distribute market maker information where the unit of contracts is symbol for stock/bond market and is product for derivatives
B16: 11 | D16: IFMDFIX0007 | E16: Symbol Event | F16: MI | G16: B | H16: DO | I16: UDP | O16: ○ | AH16: ■ | AJ16: Distribute symbol event for each symbol and the reason of the event for Stock market
B17: 14 | D17: IFMDFIX0008 | E17: Index Constituents Information | F17: ML | G17: B | H17: DO | I17: UDP | O17: ○ | AH17: ■ | AJ17: Distribute the list of constituent securities for each index
B18: 17 | C18: MarketData | D18: IFMDFIX0009 | E18: Price | F18: X | G18: R | H18: ONT | I18: UDP | O18: ○ | AH18: ■ | AJ18: Distribute the repeated structures of best orders in levels for best order messages, and distribute repeated structures of the execution/opening/highest/lowest price for trade messages
B19: 18 | D19: IFMDFIX0010 | E19: Price Recovery | F19: W | G19: R | H19: ONT | I19: UDP | O19: ○ | AH19: ■ | AJ19: Distribute price recovery periodically (automatically)
B20: 19 | D20: IFMDFIX0011 | E20: Price Recovery(Bond) | F20: W | G20: R | H20: ONT | I20: UDP | O20: ○ | AH20: ■ | AJ20: Distribute price recovery with yield periodically (automatically)
B21: 20 | D21: IFMDFIX0012 | E21: (Block Trade) Price Recovery | F21: W | G21: R | H21: ONT | I21: UDP | O21: ○ | AH21: ■ | AJ21: Distribute price recovery periodically (automatically)
B22: 21 | D22: IFMDFIX0013 | E22: (Block Trade) Price Recovery(Bond) | F22: W | G22: R | H22: ONT | I22: UDP | O22: ○ | AH22: ■ | AJ22: Distribute price recovery with yield periodically (automatically)
B23: 22 | D23: IFMDFIX0014 | E23: Index | F23: M1 | G23: R | H23: ONT | I23: UDP | O23: ○ | AH23: ■ | AJ23: Distribute index periodically during trading time and EOD(from the end of the maket to termination of process) The indices which are calculated only in EOD are distributed by batch process
B24: 23 | D24: IFMDFIX0015 | E24: Investor per Industry | F24: M2 | G24: R | H24: ONT | I24: UDP | O24: ○ | AH24: ■ | AJ24: Distribute sum of trade by investor in the structures repeated for each industry
B25: 24 | D25: IFMDFIX0016 | E25: Investor per Industry(Bond) | F25: M2 | G25: R | H25: ONT | I25: UDP | O25: ○ | AH25: ■ | AJ25: Distribute sum of trade by investor in the structures repeated for each bond cartegory
B26: 25 | D26: IFMDFIX0017 | E26: Investor per Industry(Derivatives) | F26: M2 | G26: R | H26: ONT | I26: UDP | O26: ○ | AH26: ■ | AJ26: Distribute sum of trade by investor in the structures repeated for each future/option market
B27: 26 | D27: IFMDFIX0018 | E27: Investor per Symbol | F27: M3 | G27: B | H27: MC | I27: UDP | O27: ○ | AH27: ■ | AJ27: Distribute sum of trade by investor in the structures repeated for each symbol
B28: 27 | D28: IFMDFIX0019 | E28: Top N Members per Symbol | F28: M4 | G28: R | H28: ONB | I28: UDP | O28: ○ | AH28: ■ | AJ28: Distribute top N members in the structures repeated for each symbol
B29: 28 | D29: IFMDFIX0020 | E29: Open Interest | F29: MA | G29: B | H29: DB | I29: UDP | O29: ○ | AH29: ■ | AJ29: Distribute open interest received from VSD in EOD
B30: 29 | D30: IFMDFIX0021 | E30: Deem Trade Price | F30: ME | G30: R | H30: ONT | I30: UDP | O30: ○ | AH30: ■ | AJ30: Distribute deem trade price with yield for pre-opening session
... B43: 42 | D43: IFMDFIX0034 | E43: Time Stamp (Polling) | F43: MV | G43: R | H43: ALL | I43: UDP | O43: ○ | AH43: ■ | AJ43: Distribute time stamp to check polling for each physical network line

Sheet Tag(Glossary)
B2: Tag
B4: Tag | C4: Field Name | D4: Req'd | E4: Format | F4: Length | G4: Field Meaning | H4: Possible Value
B5: 8 | C5: BeginString | E5: String | F5: 7 | G5: FIX.4.4
B6: 9 | C6: BodyLength | E6: Int | F6: 6 | G6: Length filed
B7: 10 | C7: CheckSum | E7: String | F7: 3 | G7: Three byte, simple checksum
B8: 15 | C8: Currency | E8: String | F8: 3 | G8: Currency code on ISO 4217 | H8: VND: Vietnamese Dong USD: US Dollar EUR: Euro
B9: 34 | C9: MsgSeqNum | E9: Int | F9: 11 | G9: Session sequence number
B10: 35 | C10: MsgType | E10: String | F10: 3 | G10: Refer to 'Header' sheet of the document 'VN_MDS_DS_SystemInterfaceSpecification(FIX)'
B11: 49 | C11: SenderCompID | E11: String | F11: 16 | G11: Sender(Member CompID)
B12: 52 | C12: SendingTime | E12: UTCTime | F12: 21 | G12: Time of message transmission | H12: YYYYMMDD HH:MM:SS.sss
B13: 55 | C13: Symbol | E13: String | F13: 12 | G13: The unique code of an issue (a.k.a. instrument or symbol). Generally it is ISIN code but in case of Repo market it is defined as the exchange staffs want
B14: 56 | C14: TargetCompID | E14: String | F14: 16 | G14: Target(Counter Member CompID) | H14: * Member side, VOTGW = HOSE FIX gateway VXTGW = HNX FIX gateway
B15: 60 | C15: TransactTime | E15: UTCTime | F15: 9 | G15: Time of execution/order creation | H15: HHmmSSsss : Normal Case
B16: 75 | C16: TradeDate | E16: LocalMktDate | F16: 8 | G16: Indicates local date of trade refereneced in this message in YYYYMMDD format. | H16: YYYYMMDD
B17: 83 | C17: RptSeq | E17: Int | F17: 9 | G17: Data sequential number within repeated record
B18: 106 | C18: Issuer | E18: String | F18: 10 | G18: Issuer's unique ID
B19: 140 | C19: PrevClosePx | E19: Price | F19: 15(9.4) | G19: Prev Close Price
B20: 148 | C20: Headline | E20: String | F20: 250 | G20: TEXT Format
B21: 200 | C21: MaturityMonthYear | E21: String | F21: 6 | G21: Expiration or maturity month (YYYYMM)
B22: 201 | C22: PutOrCall | E22: String | F22: 1 | G22: Rights type code of derivatives | H22: P = Put C = Call
B23: 202 | C23: StrikePrice | E23: Price | F23: 18(9.8) | G23: Exercise (strike) price of options or Subscription Warrant
B24: 207 | C24: SecurityExchange | E24: String | F24: 2 | G24: The unique ID assigned by Exchange | H24: HO: HoSE HX: HNX
B25: 223 | C25: CouponRate | E25: Float | F25: 14(7.5) | G25: Rate of return of a bond. Coupon Rate = Annual Interest Payments / Par Value
B26: 225 | C26: IssueDate | E26: String | F26: 8 | G26: Issued date | H26: YYYYMMDD
B27: 231 | C27: ContractMultiplier | E27: Float | F27: 22(12.8) | G27: Trading multiplier for calculating trading or settlement amount
B28: 236 | C28: Yield | E28: Float | F28: 13(5.6) | G28: Yield to maturity based on Reference Price
B29: 268 | C29: NoMDEntries | E29: Int | F29: 9 | G29: Number(Depth) of market data entries repeated as following
B30: 269 | C30: MDEntryType | E30: String | F30: 1 | G30: Data classification for an entry of market data | H30: Possible values in message X (Price) . 0 = Bid 1 = Offer 2 = Trade 4 = Opening Price 7 = Trading Session High Price 8 = Trading Session Low Price Possible values in message W (Price Recovery) . 0 = Bid 1 = Offer
B31: 270 | C31: MDEntryPx | E31: Price | F31: 15(9.4) | G31: Price for an entry of market data
B32: 271 | C32: MDEntrySize | E32: Int | F32: 12 | G32: Size (or quantity) for an entry of market data
B33: 279 | C33: MDUpdateAction | E33: String | F33: 1 | G33: Type code of update action for an entry of market data | H33: 0 = New
B34: 290 | C34: MDEntryPositionNo | E34: Int | F34: 2 | G34: Position no (or level) for an entry of market data
B35: 330 | C35: BuyVolume | E35: Int | F35: 12 | G35: Trading volume in buy side
B36: 331 | C36: SellVolume | E36: Int | F36: 12 | G36: Trading volume in sell side
B37: 336 | C37: TradingSessionID | E37: String | F37: 2 | G37: Trading Session | H37: 01 = GT Order Load 10 = Opening Call Auction 11 = Opening Call Auction Extension 20 = Call Auction after Halt 21 = Call Auction after Halt Extension 30 = Closing Call Auction 40 = Continuous Auction 50 = VI Call Auction 51 = VI Call Auction Extension 60 = Order Accept Only 80 = Periodic Call Auction 90 = Trading Halt 99 = Board Closing
B38: 346 | C38: NumberOfOrders | E38: Int | F38: 11 | G38: Number of orders
B39: 381 | C39: GrossTradeAmt | E39: Float | F39: 23(18.4) | G39: Gross amount traded
B40: 387 | C40: TotalVolumeTraded | E40: Int | F40: 12 | G40: Total volume traded
B41: 541 | C41: MaturityDate | E41: String | F41: 8 | G41: Expiration or maturity date | H41: YYYYMMDD
B42: 911 | C42: TotNumReports | E42: Int | F42: 16 | G42: Entire number of messages for issue information transmission or for a set of statistics results
B43: 965 | C43: SecurityStatus | E43: String | F43: 1 | G43: Whether trading halt or not | H43: Y = Halt N = Not Halt
B44: 1148 | C44: LowLimitPrice | E44: Price | F44: 15(9.4) | G44: Available low limit price for the tradig day
B45: 1149 | C45: HighLimitPrice | E45: Price | F45: 15(9.4) | G45: Available high limit price for the tradig day
B46: 1193 | C46: SettlMethod | E46: String | F46: 1 | G46: The final settlement method | H46: C: Cash D: Physical Delivery A: Cash + Physical Delivery O: None
B47: 1194 | C47: ExerciseStyle | E47: String | F47: 1 | G47: Rights exercise type code of a derivatives | H47: A: American-style E: European-style B: Bermuda-style Z: Etc.
B48: 20000 | C48: InvestCode | E48: String | F48: 4 | G48: This field indicates which category the owner of a given order or quote belongs to. This field is validated against AccountType field as below: - If AccountType is Customer (1), any value is permitted for this field. - If AccountType is House (3), this field must be 1000. | H48: 1000 = Securities company 2000 = Insurance company 3000 = Asset management company and Investment company 3200 = Fund 4000 = Bank 5000 = General finance company 6000 = Pension Fund 7000 = Goverment representation 7030 = International organization 7100 = Misc corporation 8000 = Indivisual
B49: 20003 | C49: ProductGrpID | E49: String | F49: 3 | G49: Indicates Product Group ID which is defined in the trading system. Product Group is a group of Products that share the trading schedule. | H49: STO : Stock Market Product Group BDO : Bond Market Product Group RPO : Repo Market Prodcut Group STX : Listed Stock Market Product Group UPX : UPCOM Product Group BDX : Government Bond Product Group FIO : Index Future Product Group FBX : Bond Future Product Group HCX : Corporate Bond Product Group
B50: 20004 | C50: BoardID | E50: String | F50: 2 | G50: Unique identifier to a Board where a given instrument is traded | H50: G1 : Main G2 : Pre open G3 : Post closing G4 : Odd lot G7 : Buy-in G8 : Sell-out T1 : Negotiation (regular) T4 : Negotiation (regular for Odd lot) T2 : Negotiation (pre) T3 : Negotiation (post) T6 : Negotiation (post for Odd lot) R1 : Negotiation (Repo) AL : All Boards
B51: 20005 | C51: BoardEvtID | E51: String | F51: 3 | G51: Indicates Board event ID which is defined in the trading system. Trading schedule is essentially a sequence (list) of Board events, and each event is identified by three-character code or ID. | H51: AA1: Opening CA Open AB1: Cont.A Open AB2: Board Trading Close AC2: Closing CA Execution AD1: Order Reception Start AD2: CA Excecution AE1: Market Halt Release AE8: Market Halt AF1: CA Open after CB AF6: CB Notice AF7: CB Notice Clear AF8: Suspension by CB AQ3: Interface Connection Cut-off AT6: PLE Notice AW8: Lunch Break AW9: Open after Lunch Break AX1: Board Start BB1: Cont.A Open for Non-PCA Instr. BC1: Closing CA Open BE9: Cont.A Open after Market Halt BF9: Cont.A Open after CB CC1: Closing PCA Open CD1: PCA Open CD3: PCA Execution DB2: Trading Close for LTD Instr. DC2: Closing CA Execution for LTD Instr. EI1: Trading Halt Release by Instr./Product EI8: Instr./Product Halt EI9: Cont.A Open after Instr./Product Halt GT1: GT Order Load
B52: 20008 | C52: SessOpenCloseCode | E52: String | F52: 2 | G52: Indicates whether a given Board or Session is started or ended. | H52: BS : Board Start BE : Board End SS : Session Start SE : Session End SH : Session Halt SR : Session Restart
B53: 20009 | C53: ProductID | E53: String | F53: 11 | G53: Product is a layer or unit to define or manage rules of trading, clearing and settlement, instrument creating, calculating statistics, etc. Product ID is assigned to Product ID created by combination of exchange, market, security group, underlying asset and currency | H53: List of Products (ID and description) will be defined later.
B54: 20013 | C54: ReferencePrice | E54: Price | F54: 15(9.4) | G54: Reference price of a given instrument. Price limit is determined based on this price.
B55: 20014 | C55: EvaluationPrice | E55: Price | F55: 15(9.4) | G55: Valuation price for a 'Re-Valuation' instrument. For such instrument, price limit is set based on this price until the first execution. Once the first execution is occurred, price limit is set again base on the price of the first execution.
B56: 20015 | C56: HgstOrderPrice | E56: Price | F56: 15 (9.4) | G56: Upper price limit for a 'Re-Valuation' instrument during the opening call auction (or until the first execution).
B57: 20016 | C57: LwstOrderPrice | E57: Price | F57: 15 (9.4) | G57: Lower price limit for a 'Re-Valuation' instrument during the opening call auction (or until the first execution).
B58: 20018 | C58: ExClassType | E58: String | F58: 2 | G58: Corporate action type that may affect reference price. | H58: 00: N/A 01: Stock Dividend/Bonus (D/B) 02: Cash Dividend 04: Right Offering (RO) 03: Stock D/B + Cash D 05: RO + Stock D/B 06: RO + Cash D 07: RO + Stock D/B + Cash D 08: Convertible Bond 16: Treasury Stock Div. P1: Stock Split P2: Stock Merge XX: Etc.
B59: 20020 | C59: ListedShares | E59: Int | F59: 16 | G59: Number of listed stocks
B60: 20023 | C60: MemberNo | E60: String | F60: 5 | G60: ID to identify or distinguish market participants or members with 5-digit numeric characters
B61: 20026 | C61: SymbolCloseInfoPx | E61: Price | F61: 15(9.4) | G61: The last execution price of that day. If there is no execution it is replaced with the reference price, and if no reference price is given then it will be 0 (zero)
B62: 20027 | C62: SymbolCloseInfoPxType | E62: String | F62: 1 | G62: Type of closing price | H62: 1: Actual Trade 2: Biased Quotation 3: No Trade 4: Biased Quotation of an Re-Valuation Instr.
B63: 20030 | C63: VITypeCode | E63: String | F63: 1 | G63: Indicates whether VI is activated or released. | H63: 1 = Activated 2 = Released
B64: 20031 | C64: VIKindCode | E64: String | F64: 1 | G64: Indicates which kind of VI is activated or released. | H64: 1 = Static VI 2 = Dynamic VI 3 = Static VI + Dynamic VI
B65: 20032 | C65: StaticVIBasePrice | E65: Price | F65: 15 (9.4) | G65: Indicates static VI reference price. Price range for static VI is determined based on this price, and static VI is activated when an order is about to be executed outside the VI price range.
B66: 20033 | C66: VIPrice | E66: Price | F66: 15 (9.4) | G66: VI Triggering Price
B67: 20034 | C67: StaticVIDispartiyRatio | E67: Price | F67: 8(3.3) | G67: Indicates static VI activation ratio expressed in percent. static VI price range is defined as range from static VI reference price plus/minus this ratio. For example, if static VI reference price is 1000 and this ratio is 2.5, then static VI price range.
B68: 20047 | C68: DynamicVIBasePrice | E68: Price | F68: 15 (9.4) | G68: Indicates dynamic VI reference price. Price range for dynamic VI is determined based on this price, and dynamic VI is activated when an order is about to be executed outside the VI price range.
B69: 20048 | C69: DynamicVIDispartiyRatio | E69: Price | F69: 8(3.3) | G69: Indicates dynamic VI activation ratio expressed in percent. Dynamic VI price range is defined as range from Dynamic VI reference price plus/minus this ratio. For example, if Dynamic VI reference price is 1000 and this ratio is 2, then Dynamic VI price range is from 980 to 1020.
B70: 20054 | C70: FornInvestTypeCode | E70: String | F70: 2 | G70: Indicates whether a given order or quote is owned by foreigner. | H70: 00 Domestic(default) 10 Foreginer
B71: 30001 | C71: MarketID | E71: String | F71: 3 | G71: ID for identifying the market | H71: <Hochiminh Exchange> - STO: HoSE Stock Market - BDO: HoSE Bond Market - RPO: HoSE Repo Market <Hanoi Exchange> - STX: HNX Listed Stock Market - BDX: HNX Government Bond Market - DVX: HNX Derivative Market - UPX: HNX UpCoM Stock Market - HCX: HNX Corporate Bond Market
B72: 30167 | C72: IndexsTypeCode | E72: String | F72: 8 | G72: Industry Index Code for example 001: Composite index 002: VNALLshare index 100: VN30 index
B73: 30168 | C73: SellTradeAmount | E73: Float | F73: 23(18.4) | G73: Trading value in ask side
B74: 30169 | C74: BuyTradedAmount | E74: Float | F74: 23(18.4) | G74: Trading value in bid side
B75: 30213 | C75: SellMemberNo | E75: String | F75: 5 | G75: Member ID in sell side
B76: 30214 | C76: BuyMemberNo | E76: String | F76: 5 | G76: Member ID in buy side
B77: 30215 | C77: SellRankSeq | E77: Int | F77: 6 | G77: Sequence of rank in sell side
B78: 30216 | C78: BuyRankSeq | E78: Int | F78: 6 | G78: Sequence of rank in buy side
B79: 30217 | C79: ValueIndexes | E79: Float | F79: 10(6.2) | G79: Value of the index calculated
B80: 30270 | C80: MDEntryYield | E80: Float | F80: 13(5.6) | G80: Yield of the entry. Bond market only.
B81: 30271 | C81: MDEntryMMSize | E81: Int | F81: 12 | G81: Size of the entry provided from market makers
B82: 30301 | C82: ListingDate | E82: String | F82: 8 | G82: Listing date of a derivative product or an instrument | H82: YYYYMMDD
B83: 30511 | C83: FinalTradeDate | E83: String | F83: 8 | G83: Last trading date | H83: YYYYMMDD
B84: 30512 | C84: FinalSettleDate | E84: String | F84: 8 | G84: Last settlement date | H84: YYYYMMDD
B85: 30521 | C85: SellTotOrderQty | E85: Int | F85: 12 | G85: Total quantity of remaining orders in ask side
B86: 30522 | C86: BuyTotOrderQty | E86: Int | F86: 12 | G86: Total quantity of remaining orders in bid side
B87: 30523 | C87: SellValidOrderCnt | E87: Int | F87: 11 | G87: Valid count of orders in ask side
B88: 30524 | C88: BuyValidOrderCnt | E88: Int | F88: 11 | G88: Valid count of orders in bid side
B89: 30540 | C89: OpenInterestQty | E89: Number | F89: 10 | G89: Open interest quantity
B90: 30541 | C90: SymbolCloseInfoYield | E90: Float | F90: 13(5.6) | G90: Final yield of a bond calculated using the closing price of that day
B91: 30552 | C91: ExpectedTradePx | E91: Price | F91: 15(9.4) | G91: Deemed trading price
B92: 30553 | C92: ExpectedTradeQty | E92: Int | F92: 12
B93: 30554 | C93: ExpectedTradeYield | E93: Float | F93: 13(5.6) | G93: Yield of deemed trading price
B94: 30557 | C94: ForeignerBuyPosblQty | E94: Int | F94: 15 | G94: Maximum number of shares allocated for foreign investors to buy. It is well known as "Total Room"
B95: 30558 | C95: ForeignerOrderLimitQty | E95: Int | F95: 16 | G95: Number of shares available for investors to buy at that time. It is well-known as “Current Room”. Current Room = Total Room – Foreigner Holding Shares
B96: 30561 | C96: OpnPx | E96: Price | F96: 15(9.4) | G96: The first price during that day
B97: 30562 | C97: TrdSessnHighPx | E97: Price | F97: 15(9.4) | G97: Highest price during that day
B98: 30563 | C98: TrdSessnLowPx | E98: Price | F98: 15(9.4) | G98: Lowest price during that day
B99: 30565 | C99: OpnPxYld | E99: Float | F99: 13(5.6) | G99: Yield rate for opening price
B100: 30566 | C100: TrdSessnHighPxYld | E100: Float | F100: 13(5.6) | G100: Yield rate for high price
B101: 30567 | C101: TrdSessnLowPxYld | E101: Float | F101: 13(5.6) | G101: Yield rate for low price
B102: 30568 | C102: ClsPxYld | E102: Float | F102: 13(5.6) | G102: Final yield of a bond calculated using the closing price of that day
...

Sheet Header
B2: Header
B4: Tag | C4: Field Name | D4: Req'd | E4: Format | F4: Length | G4: Comments
B5: 8 | C5: =VLOOKUP($B5,'Tag(Glossary)'!$B:$G,2,0) -> BeginString | D5: Y | E5: =VLOOKUP($B5,'Tag(Glossary)'!$B:$G,4,0) -> String | F5: =VLOOKUP($B5,'Tag(Glossary)'!$B:$G,5,0) -> 7 | G5: =VLOOKUP($B5,'Tag(Glossary)'!$B:$G,6,0) -> FIX.4.4
B6: 9 | C6: =VLOOKUP($B6,'Tag(Glossary)'!$B:$G,2,0) -> BodyLength | D6: Y | E6: =VLOOKUP($B6,'Tag(Glossary)'!$B:$G,4,0) -> Int | F6: =VLOOKUP($B6,'Tag(Glossary)'!$B:$G,5,0) -> 6 | G6: =VLOOKUP($B6,'Tag(Glossary)'!$B:$G,6,0) -> Length filed
B7: 35 | C7: =VLOOKUP($B7,'Tag(Glossary)'!$B:$G,2,0) -> MsgType | D7: Y | E7: =VLOOKUP($B7,'Tag(Glossary)'!$B:$G,4,0) -> String | F7: =VLOOKUP($B7,'Tag(Glossary)'!$B:$G,5,0) -> 3 | G7: =VLOOKUP($B7,'Tag(Glossary)'!$B:$G,6,0) -> Refer to 'Header' sheet of the document 'VN_MDS_DS_SystemInterfaceSpecification(FIX)'
B8: 49 | C8: =VLOOKUP($B8,'Tag(Glossary)'!$B:$G,2,0) -> SenderCompID | D8: Y | E8: =VLOOKUP($B8,'Tag(Glossary)'!$B:$G,4,0) -> String | F8: =VLOOKUP($B8,'Tag(Glossary)'!$B:$G,5,0) -> 16 | G8: =VLOOKUP($B8,'Tag(Glossary)'!$B:$G,6,0) -> Sender(Member CompID)
B9: 56 | C9: =VLOOKUP($B9,'Tag(Glossary)'!$B:$G,2,0) -> TargetCompID | D9: Y | E9: =VLOOKUP($B9,'Tag(Glossary)'!$B:$G,4,0) -> String | F9: =VLOOKUP($B9,'Tag(Glossary)'!$B:$G,5,0) -> 16 | G9: =VLOOKUP($B9,'Tag(Glossary)'!$B:$G,6,0) -> Target(Counter Member CompID)
B10: 34 | C10: =VLOOKUP($B10,'Tag(Glossary)'!$B:$G,2,0) -> MsgSeqNum | D10: Y | E10: =VLOOKUP($B10,'Tag(Glossary)'!$B:$G,4,0) -> Int | F10: =VLOOKUP($B10,'Tag(Glossary)'!$B:$G,5,0) -> 11 | G10: =VLOOKUP($B10,'Tag(Glossary)'!$B:$G,6,0) -> Session sequence number
B11: 52 | C11: =VLOOKUP($B11,'Tag(Glossary)'!$B:$G,2,0) -> SendingTime | D11: Y | E11: =VLOOKUP($B11,'Tag(Glossary)'!$B:$G,4,0) -> UTCTime | F11: =VLOOKUP($B11,'Tag(Glossary)'!$B:$G,5,0) -> 21 | G11: =VLOOKUP($B11,'Tag(Glossary)'!$B:$G,6,0) -> Time of message transmission
B13: * Specification of MsyType(35)
C14: d = Security Definition
C15: f = Secrity Status
C16: X = Price
C17: W = Price Recovery
C18: M1 = Index
C19: M2 = Investor per Industry
C20: M3 = Investor per Symbol
C21: M4 = Top N Members per Symbol
C22: M7 = Security Information Notification
C23: M8 = Symbol Closing Information
C24: MD = Volatility Interruption
C25: MA = Open Interest
... C42: MX = Price Limit Expansion

Sheet Trailer
B2: Trailer
B4: Tag | C4: Field Name | D4: Req'd | E4: Format | F4: Length | G4: Comments
B5: 10 | C5: =VLOOKUP($B5,'Tag(Glossary)'!$B:$G,2,0) -> CheckSum | D5: Y | E5: =VLOOKUP($B5,'Tag(Glossary)'!$B:$G,4,0) -> String | F5: =VLOOKUP($B5,'Tag(Glossary)'!$B:$G,5,0) -> 3 | G5: =VLOOKUP($B5,'Tag(Glossary)'!$B:$G,6,0) -> Three byte, simple checksum

Sheet Security Definition
B2: Security Definition
B4: Interface ID | C4: Interface Name | D4: Tag | E4: Field Name | F4: Req'd | G4: Format | H4: Length | I4: Comments
B5: =INDEX('Interface List'!$D$7:$D$45,MATCH($C5,'Interface List'!$E$7:$E$45,0)) -> IFMDFIX0001 | C5: Security Definition | E5: Standard Header | F5: Y | I5: MsgType = d
B6: =INDEX('Interface List'!$D$7:$D$45,MATCH($C6,'Interface List'!$E$7:$E$45,0)) -> IFMDFIX0001 | C6: Security Definition | D6: 30001 | E6: =VLOOKUP($D6,'Tag(Glossary)'!$B:$G,2,0) -> MarketID | F6: Y | G6: =VLOOKUP($D6,'Tag(Glossary)'!$B:$G,4,0) -> String | H6: =VLOOKUP($D6,'Tag(Glossary)'!$B:$G,5,0) -> 3 | I6: =VLOOKUP($D6,'Tag(Glossary)'!$B:$H,6,0)&IF(ISBLANK(VLOOKUP($D6,'Tag(Glossary)'!$B:$H,7,0)),"",CHAR(10))&VLOOKUP($D6,'Tag(Glossary)'!$B:$H,7,0) -> ID for identifying the market <Hochiminh Exchange> - STO: HoSE Stock Market - BDO: HoSE Bond Market - RPO: HoSE Repo Market <Hanoi Exchange> - STX: HNX Listed Stock Market - BDX: HNX Government Bond Market - DVX: HNX Derivative Market - UPX: HNX UpCoM Stock Market - HCX: HNX Corporate Bond Market
B7: =INDEX('Interface List'!$D$7:$D$45,MATCH($C7,'Interface List'!$E$7:$E$45,0)) -> IFMDFIX0001 | C7: Security Definition | D7: 20004 | E7: =VLOOKUP($D7,'Tag(Glossary)'!$B:$G,2,0) -> BoardID | F7: Y | G7: =VLOOKUP($D7,'Tag(Glossary)'!$B:$G,4,0) -> String | H7: =VLOOKUP($D7,'Tag(Glossary)'!$B:$G,5,0) -> 2 | I7: =VLOOKUP($D7,'Tag(Glossary)'!$B:$H,6,0)&IF(ISBLANK(VLOOKUP($D7,'Tag(Glossary)'!$B:$H,7,0)),"",CHAR(10))&VLOOKUP($D7,'Tag(Glossary)'!$B:$H,7,0) -> Unique identifier to a Board where a given instrument is traded G1 : Main G2 : Pre open G3 : Post closing G4 : Odd lot G7 : Buy-in G8 : Sell-out T1 : Negotiation (regular) T4 : Negotiation (regular for Odd lot) T2 : Negotiation (pre) T3 : Negotiation (post) T6 : Negotiation (post for Odd lot) R1 : Negotiation (Repo) AL : All Boards
B8: =INDEX('Interface List'!$D$7:$D$45,MATCH($C8,'Interface List'!$E$7:$E$45,0)) -> IFMDFIX0001 | C8: Security Definition | D8: 911 | E8: =VLOOKUP($D8,'Tag(Glossary)'!$B:$G,2,0) -> TotNumReports | F8: Y | G8: =VLOOKUP($D8,'Tag(Glossary)'!$B:$G,4,0) -> Int | H8: =VLOOKUP($D8,'Tag(Glossary)'!$B:$G,5,0) -> 16 | I8: =VLOOKUP($D8,'Tag(Glossary)'!$B:$H,6,0)&IF(ISBLANK(VLOOKUP($D8,'Tag(Glossary)'!$B:$H,7,0)),"",CHAR(10))&VLOOKUP($D8,'Tag(Glossary)'!$B:$H,7,0) -> Entire number of messages for issue information transmission or for a set of statistics results
B9: =INDEX('Interface List'!$D$7:$D$45,MATCH($C9,'Interface List'!$E$7:$E$45,0)) -> IFMDFIX0001 | C9: Security Definition | D9: 207 | E9: =VLOOKUP($D9,'Tag(Glossary)'!$B:$G,2,0) -> SecurityExchange | F9: Y | G9: =VLOOKUP($D9,'Tag(Glossary)'!$B:$G,4,0) -> String | H9: =VLOOKUP($D9,'Tag(Glossary)'!$B:$G,5,0) -> 2 | I9: =VLOOKUP($D9,'Tag(Glossary)'!$B:$H,6,0)&IF(ISBLANK(VLOOKUP($D9,'Tag(Glossary)'!$B:$H,7,0)),"",CHAR(10))&VLOOKUP($D9,'Tag(Glossary)'!$B:$H,7,0) -> The unique ID assigned by Exchange HO: HoSE HX: HNX
B10: =INDEX('Interface List'!$D$7:$D$45,MATCH($C10,'Interface List'!$E$7:$E$45,0)) -> IFMDFIX0001 | C10: Security Definition | D10: 55 | E10: =VLOOKUP($D10,'Tag(Glossary)'!$B:$G,2,0) -> Symbol | F10: Y | G10: =VLOOKUP($D10,'Tag(Glossary)'!$B:$G,4,0) -> String | H10: =VLOOKUP($D10,'Tag(Glossary)'!$B:$G,5,0) -> 12 | I10: =VLOOKUP($D10,'Tag(Glossary)'!$B:$H,6,0)&IF(ISBLANK(VLOOKUP($D10,'Tag(Glossary)'!$B:$H,7,0)),"",CHAR(10))&VLOOKUP($D10,'Tag(Glossary)'!$B:$H,7,0) -> The unique code of an issue (a.k.a. instrument or symbol). Generally it is ISIN code but in case of Repo market it is defined as the exchange staffs want
B11: =INDEX('Interface List'!$D$7:$D$45,MATCH($C11,'Interface List'!$E$7:$E$45,0)) -> IFMDFIX0001 | C11: Security Definition | D11: 30624 | E11: =VLOOKUP($D11,'Tag(Glossary)'!$B:$G,2,0) -> TickerCode | F11: Y | G11: =VLOOKUP($D11,'Tag(Glossary)'!$B:$G,4,0) -> String | H11: =VLOOKUP($D11,'Tag(Glossary)'!$B:$G,5,0) -> 20 | I11: =VLOOKUP($D11,'Tag(Glossary)'!$B:$H,6,0)&IF(ISBLANK(VLOOKUP($D11,'Tag(Glossary)'!$B:$H,7,0)),"",CHAR(10))&VLOOKUP($D11,'Tag(Glossary)'!$B:$H,7,0) -> Symbolic characters of an instrument. It might be used as ticker code (a.k.a. trading code, local code, stock code, bond code and so forth)
B12: =INDEX('Interface List'!$D$7:$D$45,MATCH($C12,'Interface List'!$E$7:$E$45,0)) -> IFMDFIX0001 | C12: Security Definition | D12: 30628 | E12: =VLOOKUP($D12,'Tag(Glossary)'!$B:$G,2,0) -> SymbolShortCode | F12: Y | G12: =VLOOKUP($D12,'Tag(Glossary)'!$B:$G,4,0) -> String | H12: =VLOOKUP($D12,'Tag(Glossary)'!$B:$G,5,0) -> 9 | I12: =VLOOKUP($D12,'Tag(Glossary)'!$B:$H,6,0)&IF(ISBLANK(VLOOKUP($D12,'Tag(Glossary)'!$B:$H,7,0)),"",CHAR(10))&VLOOKUP($D12,'Tag(Glossary)'!$B:$H,7,0) -> A short unique code for an instrument which is determined at exchange and used for more convenience than 12-digit instrument code (ISIN code). It may be used as a part of Repo instrument's ISIN code
B13: =INDEX('Interface List'!$D$7:$D$45,MATCH($C13,'Interface List'!$E$7:$E$45,0)) -> IFMDFIX0001 | C13: Security Definition | D13: 30629 | E13: =VLOOKUP($D13,'Tag(Glossary)'!$B:$G,2,0) -> SymbolName | F13: Y | G13: =VLOOKUP($D13,'Tag(Glossary)'!$B:$G,4,0) -> String | H13: =VLOOKUP($D13,'Tag(Glossary)'!$B:$G,5,0) -> 120 | I13: =VLOOKUP($D13,'Tag(Glossary)'!$B:$H,6,0)&IF(ISBLANK(VLOOKUP($D13,'Tag(Glossary)'!$B:$H,7,0)),"",CHAR(10))&VLOOKUP($D13,'Tag(Glossary)'!$B:$H,7,0) -> Instrument name
B14: =INDEX('Interface List'!$D$7:$D$45,MATCH($C14,'Interface List'!$E$7:$E$45,0)) -> IFMDFIX0001 | C14: Security Definition | D14: 30630 | E14: =VLOOKUP($D14,'Tag(Glossary)'!$B:$G,2,0) -> SymbolEnglishName | F14: Y | G14: =VLOOKUP($D14,'Tag(Glossary)'!$B:$G,4,0) -> String | H14: =VLOOKUP($D14,'Tag(Glossary)'!$B:$G,5,0) -> 80 | I14: =VLOOKUP($D14,'Tag(Glossary)'!$B:$H,6,0)&IF(ISBLANK(VLOOKUP($D14,'Tag(Glossary)'!$B:$H,7,0)),"",CHAR(10))&VLOOKUP($D14,'Tag(Glossary)'!$B:$H,7,0) -> Instrument English name
B15: =INDEX('Interface List'!$D$7:$D$45,MATCH($C15,'Interface List'!$E$7:$E$45,0)) -> IFMDFIX0001 | C15: Security Definition | D15: 20009 | E15: =VLOOKUP($D15,'Tag(Glossary)'!$B:$G,2,0) -> ProductID | F15: Y | G15: =VLOOKUP($D15,'Tag(Glossary)'!$B:$G,4,0) -> String | H15: =VLOOKUP($D15,'Tag(Glossary)'!$B:$G,5,0) -> 11 | I15: =VLOOKUP($D15,'Tag(Glossary)'!$B:$H,6,0)&IF(ISBLANK(VLOOKUP($D15,'Tag(Glossary)'!$B:$H,7,0)),"",CHAR(10))&VLOOKUP($D15,'Tag(Glossary)'!$B:$H,7,0) -> Product is a layer or unit to define or manage rules of trading, clearing and settlement, instrument creating, calculating statistics, etc. Product ID is assigned to Product ID created by combination of exchange, market, security group, underlying asset and currency List of Products (ID and description) will be defined later.
B16: =INDEX('Interface List'!$D$7:$D$45,MATCH($C16,'Interface List'!$E$7:$E$45,0)) -> IFMDFIX0001 | C16: Security Definition | D16: 20003 | E16: =VLOOKUP($D16,'Tag(Glossary)'!$B:$G,2,0) -> ProductGrpID | F16: Y | G16: =VLOOKUP($D16,'Tag(Glossary)'!$B:$G,4,0) -> String | H16: =VLOOKUP($D16,'Tag(Glossary)'!$B:$G,5,0) -> 3 | I16: =VLOOKUP($D16,'Tag(Glossary)'!$B:$H,6,0)&IF(ISBLANK(VLOOKUP($D16,'Tag(Glossary)'!$B:$H,7,0)),"",CHAR(10))&VLOOKUP($D16,'Tag(Glossary)'!$B:$H,7,0) -> Indicates Product Group ID which is defined in the trading system. Product Group is a group of Products that share the trading schedule. STO : Stock Market Product Group BDO : Bond Market Product Group RPO : Repo Market Prodcut Group STX : Listed Stock Market Product Group UPX : UPCOM Product Group BDX : Government Bond Product Group FIO : Index Future Product Group FBX : Bond Future Product Group HCX : Corporate Bond Product Group
B17: =INDEX('Interface List'!$D$7:$D$45,MATCH($C17,'Interface List'!$E$7:$E$45,0)) -> IFMDFIX0001 | C17: Security Definition | D17: 30604 | E17: =VLOOKUP($D17,'Tag(Glossary)'!$B:$G,2,0) -> SecurityGroupID | F17: Y | G17: =VLOOKUP($D17,'Tag(Glossary)'!$B:$G,4,0) -> String | H17: =VLOOKUP($D17,'Tag(Glossary)'!$B:$G,5,0) -> 2 | I17: =VLOOKUP($D17,'Tag(Glossary)'!$B:$H,6,0)&IF(ISBLANK(VLOOKUP($D17,'Tag(Glossary)'!$B:$H,7,0)),"",CHAR(10))&VLOOKUP($D17,'Tag(Glossary)'!$B:$H,7,0) -> Security group ID (Stock, Investment Trust, Futures, Option, etc.)
... B52: =INDEX('Interface List'!$D$7:$D$45,MATCH($C52,'Interface List'!$E$7:$E$45,0)) -> IFMDFIX0001 | C52: Security Definition | D52: 30652 | E52: =VLOOKUP($D52,'Tag(Glossary)'!$B:$G,2,0) -> RedumptionDate | F52: N | G52: =VLOOKUP($D52,'Tag(Glossary)'!$B:$G,4,0) -> String | H52: =VLOOKUP($D52,'Tag(Glossary)'!$B:$G,5,0) -> 8 | I52: =VLOOKUP($D52,'Tag(Glossary)'!$B:$H,6,0)&IF(ISBLANK(VLOOKUP($D52,'Tag(Glossary)'!$B:$H,7,0)),"",CHAR(10))&VLOOKUP($D52,'Tag(Glossary)'!$B:$H,7,0) -> Redumption date YYYYMMDD
B53: =INDEX('Interface List'!$D$7:$D$45,MATCH($C53,'Interface List'!$E$7:$E$45,0)) -> IFMDFIX0001 | C53: Security Definition | E53: Standard Trailer | F53: Y

Sheet Security Status
B2: Security Status
B4: Interface ID | C4: Interface Name | D4: Tag | E4: Field Name | F4: Req'd | G4: Format | H4: Length | I4: Comments
B5: =INDEX('Interface List'!$D$7:$D$45,MATCH($C5,'Interface List'!$E$7:$E$45,0)) -> IFMDFIX0002 | C5: Security Status | E5: Standard Header | F5: Y | I5: MsgType = f
B6: =INDEX('Interface List'!$D$7:$D$45,MATCH($C6,'Interface List'!$E$7:$E$45,0)) -> IFMDFIX0002 | C6: Security Status | D6: 30001 | E6: =VLOOKUP($D6,'Tag(Glossary)'!$B:$G,2,0) -> MarketID | F6: Y | G6: =VLOOKUP($D6,'Tag(Glossary)'!$B:$G,4,0) -> String | H6: =VLOOKUP($D6,'Tag(Glossary)'!$B:$G,5,0) -> 3 | I6: =VLOOKUP($D6,'Tag(Glossary)'!$B:$H,6,0)&IF(ISBLANK(VLOOKUP($D6,'Tag(Glossary)'!$B:$H,7,0)),"",CHAR(10))&VLOOKUP($D6,'Tag(Glossary)'!$B:$H,7,0) -> ID for identifying the market <Hochiminh Exchange> - STO: HoSE Stock Market - BDO: HoSE Bond Market - RPO: HoSE Repo Market <Hanoi Exchange> - STX: HNX Listed Stock Market - BDX: HNX Government Bond Market - DVX: HNX Derivative Market - UPX: HNX UpCoM Stock Market - HCX: HNX Corporate Bond Market
B7: =INDEX('Interface List'!$D$7:$D$45,MATCH($C7,'Interface List'!$E$7:$E$45,0)) -> IFMDFIX0002 | C7: Security Status | D7: 30648 | E7: =VLOOKUP($D7,'Tag(Glossary)'!$B:$G,2,0) -> TscProdGrpId | F7: Y | G7: =VLOOKUP($D7,'Tag(Glossary)'!$B:$G,4,0) -> String | H7: =VLOOKUP($D7,'Tag(Glossary)'!$B:$G,5,0) -> 3 | I7: =VLOOKUP($D7,'Tag(Glossary)'!$B:$H,6,0)&IF(ISBLANK(VLOOKUP($D7,'Tag(Glossary)'!$B:$H,7,0)),"",CHAR(10))&VLOOKUP($D7,'Tag(Glossary)'!$B:$H,7,0) -> ID for identifying the set of the same TSC(Trading Schedule Control) target products. A logical unit controlled by the same schedule. ▦▦ IDs ▦▦ STO : HoSE Stock BDO : HoSE Bond RPO : HoSE Repo BDX : Government Bond FIO : HoSE Index Futures FBX : HNX Bond Futures STX : HNX Stock UPX : HNX UpCom HCX : HNX Corporate Bond ALL : All TSC Products Group
B8: =INDEX('Interface List'!$D$7:$D$45,MATCH($C8,'Interface List'!$E$7:$E$45,0)) -> IFMDFIX0002 | C8: Security Status | D8: 20004 | E8: =VLOOKUP($D8,'Tag(Glossary)'!$B:$G,2,0) -> BoardID | F8: Y | G8: =VLOOKUP($D8,'Tag(Glossary)'!$B:$G,4,0) -> String | H8: =VLOOKUP($D8,'Tag(Glossary)'!$B:$G,5,0) -> 2 | I8: =VLOOKUP($D8,'Tag(Glossary)'!$B:$H,6,0)&IF(ISBLANK(VLOOKUP($D8,'Tag(Glossary)'!$B:$H,7,0)),"",CHAR(10))&VLOOKUP($D8,'Tag(Glossary)'!$B:$H,7,0) -> Unique identifier to a Board where a given instrument is traded G1 : Main G2 : Pre open G3 : Post closing G4 : Odd lot G7 : Buy-in G8 : Sell-out T1 : Negotiation (regular) T4 : Negotiation (regular for Odd lot) T2 : Negotiation (pre) T3 : Negotiation (post) T6 : Negotiation (post for Odd lot) R1 : Negotiation (Repo) AL : All Boards
B9: =INDEX('Interface List'!$D$7:$D$45,MATCH($C9,'Interface List'!$E$7:$E$45,0)) -> IFMDFIX0002 | C9: Security Status | D9: 20005 | E9: =VLOOKUP($D9,'Tag(Glossary)'!$B:$G,2,0) -> BoardEvtID | F9: Y | G9: =VLOOKUP($D9,'Tag(Glossary)'!$B:$G,4,0) -> String | H9: =VLOOKUP($D9,'Tag(Glossary)'!$B:$G,5,0) -> 3 | I9: =VLOOKUP($D9,'Tag(Glossary)'!$B:$H,6,0)&IF(ISBLANK(VLOOKUP($D9,'Tag(Glossary)'!$B:$H,7,0)),"",CHAR(10))&VLOOKUP($D9,'Tag(Glossary)'!$B:$H,7,0) -> Indicates Board event ID which is defined in the trading system. Trading schedule is essentially a sequence (list) of Board events, and each event is identified by three-character code or ID. AA1: Opening CA Open AB1: Cont.A Open AB2: Board Trading Close AC2: Closing CA Execution AD1: Order Reception Start AD2: CA Excecution AE1: Market Halt Release AE8: Market Halt AF1: CA Open after CB AF6: CB Notice AF7: CB Notice Clear AF8: Suspension by CB AQ3: Interface Connection Cut-off AT6: PLE Notice AW8: Lunch Break AW9: Open after Lunch Break AX1: Board Start BB1: Cont.A Open for Non-PCA Instr. BC1: Closing CA Open BE9: Cont.A Open after Market Halt BF9: Cont.A Open after CB CC1: Closing PCA Open CD1: PCA Open CD3: PCA Execution DB2: Trading Close for LTD Instr. DC2: Closing CA Execution for LTD Instr. EI1: Trading Halt Release by Instr./Product EI8: Instr./Product Halt EI9: Cont.A Open after Instr./Product Halt GT1: GT Order Load
B10: =INDEX('Interface List'!$D$7:$D$45,MATCH($C10,'Interface List'!$E$7:$E$45,0)) -> IFMDFIX0002 | C10: Security Status | D10: 20008 | E10: =VLOOKUP($D10,'Tag(Glossary)'!$B:$G,2,0) -> SessOpenCloseCode | F10: N | G10: =VLOOKUP($D10,'Tag(Glossary)'!$B:$G,4,0) -> String | H10: =VLOOKUP($D10,'Tag(Glossary)'!$B:$G,5,0) -> 2 | I10: =VLOOKUP($D10,'Tag(Glossary)'!$B:$H,6,0)&IF(ISBLANK(VLOOKUP($D10,'Tag(Glossary)'!$B:$H,7,0)),"",CHAR(10))&VLOOKUP($D10,'Tag(Glossary)'!$B:$H,7,0) -> Indicates whether a given Board or Session is started or ended. BS : Board Start BE : Board End SS : Session Start SE : Session End SH : Session Halt SR : Session Restart
B11: =INDEX('Interface List'!$D$7:$D$45,MATCH($C11,'Interface List'!$E$7:$E$45,0)) -> IFMDFIX0002 | C11: Security Status | D11: 55 | E11: =VLOOKUP($D11,'Tag(Glossary)'!$B:$G,2,0) -> Symbol | F11: N | G11: =VLOOKUP($D11,'Tag(Glossary)'!$B:$G,4,0) -> String | H11: =VLOOKUP($D11,'Tag(Glossary)'!$B:$G,5,0) -> 12 | I11: =VLOOKUP($D11,'Tag(Glossary)'!$B:$H,6,0)&IF(ISBLANK(VLOOKUP($D11,'Tag(Glossary)'!$B:$H,7,0)),"",CHAR(10))&VLOOKUP($D11,'Tag(Glossary)'!$B:$H,7,0) -> The unique code of an issue (a.k.a. instrument or symbol). Generally it is ISIN code but in case of Repo market it is defined as the exchange staffs want
B12: =INDEX('Interface List'!$D$7:$D$45,MATCH($C12,'Interface List'!$E$7:$E$45,0)) -> IFMDFIX0002 | C12: Security Status | D12: 336 | E12: =VLOOKUP($D12,'Tag(Glossary)'!$B:$G,2,0) -> TradingSessionID | F12: N | G12: =VLOOKUP($D12,'Tag(Glossary)'!$B:$G,4,0) -> String | H12: =VLOOKUP($D12,'Tag(Glossary)'!$B:$G,5,0) -> 2 | I12: =VLOOKUP($D12,'Tag(Glossary)'!$B:$H,6,0)&IF(ISBLANK(VLOOKUP($D12,'Tag(Glossary)'!$B:$H,7,0)),"",CHAR(10))&VLOOKUP($D12,'Tag(Glossary)'!$B:$H,7,0) -> Trading Session 01 = GT Order Load 10 = Opening Call Auction 11 = Opening Call Auction Extension 20 = Call Auction after Halt 21 = Call Auction after Halt Extension 30 = Closing Call Auction 40 = Continuous Auction 50 = VI Call Auction 51 = VI Call Auction Extension 60 = Order Accept Only 80 = Periodic Call Auction 90 = Trading Halt 99 = Board Closing
B13: =INDEX('Interface List'!$D$7:$D$45,MATCH($C13,'Interface List'!$E$7:$E$45,0)) -> IFMDFIX0002 | C13: Security Status | D13: 30651 | E13: =VLOOKUP($D13,'Tag(Glossary)'!$B:$G,2,0) -> HaltRsnCode | F13: N | G13: String | H13: 3 | I13: =VLOOKUP($D13,'Tag(Glossary)'!$B:$H,6,0)&IF(ISBLANK(VLOOKUP($D13,'Tag(Glossary)'!$B:$H,7,0)),"",CHAR(10))&VLOOKUP($D13,'Tag(Glossary)'!$B:$H,7,0) -> Halt Reason Code ▦▦ Codes ▦▦ B10 The result of the inquiry disclosure for rumor and news B11 Unsubmission of annual/half-yearly/quarterly report B21 Capital is less than 10 billion VND B23 Auditor's Opinion is adverse or disclaimer B24 Issuers default B25 Dissolution B26 Bankruptcy B27 Sanction on Business B28 Suspension by courts decision B29 False information/omission of listing document B30 Accounting standards of violation B31 Investor warning/protection B40 Issues for administration B60 Falsification of securities B70 Investor protection during a workout program B80 Bankruptcy of guarantee institution B90 Other reasons B99 When maturity date will be a holiday D11 Corresponded cash market stop trading D21 Investor warning/protection D22 Volatile price movement D23 Bankruptcy D24 Issuers default D25 Liquidation D26 Sanction on Business D27 Suspension by courts decision D28 Stock split or reverse stock split D31 HNX trading system have problem D32 Lot of HNX’s members have problem D33 VSD have problem D41 Requested by SSC O01 Volatile price movement O02 Information Disclosure Special Warning O03 Stock split or reverse stock split O04 Bond Converting O05 Capital Decrease O06 Investor warning/protection O07 Other reasons O08 Volatile price movement O09 Investor warning/protection O10 Other reasons O12 Volatile price movement (Intraday) O13 Investor warning/protection (Intraday) O14 Other reasons (Intraday) X01 Volatile price movement X02 Information Disclosure Special Warning X03 Stock split or reverse stock split X04 Bond Converting X05 Capital Decrease X06 Investor warning/protection X07 Other reasons X08 Violation on information disclosure X09 Volatile volume movement X10 Fault to fix controlled status X11 Continue to violate information disclosure when controlled X12 Volatile volume movement (Intraday) X13 Investor warning/protection (Intraday) X14 Other reasons (Intraday)
B14: =INDEX('Interface List'!$D$7:$D$45,MATCH($C14,'Interface List'!$E$7:$E$45,0)) -> IFMDFIX0002 | C14: Security Status | E14: Standard Trailer | F14: Y

Sheet Security Info Notification
B2: Security Information Notification
B4: Interface ID | C4: Interface Name | D4: Tag | E4: Field Name | F4: Req'd | G4: Format | H4: Length | I4: Comments
B5: =INDEX('Interface List'!$D$7:$D$45,MATCH($C5,'Interface List'!$E$7:$E$45,0)) -> IFMDFIX0003 | C5: Security Information Notification | E5: Standard Header | F5: Y | I5: MsgType = M7
B6: =INDEX('Interface List'!$D$7:$D$45,MATCH($C6,'Interface List'!$E$7:$E$45,0)) -> IFMDFIX0003 | C6: Security Information Notification | D6: 30001 | E6: =VLOOKUP($D6,'Tag(Glossary)'!$B:$G,2,0) -> MarketID | F6: Y | G6: =VLOOKUP($D6,'Tag(Glossary)'!$B:$G,4,0) -> String | H6: =VLOOKUP($D6,'Tag(Glossary)'!$B:$G,5,0) -> 3 | I6: =VLOOKUP($D6,'Tag(Glossary)'!$B:$H,6,0)&IF(ISBLANK(VLOOKUP($D6,'Tag(Glossary)'!$B:$H,7,0)),"",CHAR(10))&VLOOKUP($D6,'Tag(Glossary)'!$B:$H,7,0) -> ID for identifying the market <Hochiminh Exchange> - STO: HoSE Stock Market - BDO: HoSE Bond Market - RPO: HoSE Repo Market <Hanoi Exchange> - STX: HNX Listed Stock Market - BDX: HNX Government Bond Market - DVX: HNX Derivative Market - UPX: HNX UpCoM Stock Market - HCX: HNX Corporate Bond Market
B7: =INDEX('Interface List'!$D$7:$D$45,MATCH($C7,'Interface List'!$E$7:$E$45,0)) -> IFMDFIX0003 | C7: Security Information Notification | D7: 20004 | E7: =VLOOKUP($D7,'Tag(Glossary)'!$B:$G,2,0) -> BoardID | F7: Y | G7: =VLOOKUP($D7,'Tag(Glossary)'!$B:$G,4,0) -> String | H7: =VLOOKUP($D7,'Tag(Glossary)'!$B:$G,5,0) -> 2 | I7: =VLOOKUP($D7,'Tag(Glossary)'!$B:$H,6,0)&IF(ISBLANK(VLOOKUP($D7,'Tag(Glossary)'!$B:$H,7,0)),"",CHAR(10))&VLOOKUP($D7,'Tag(Glossary)'!$B:$H,7,0) -> Unique identifier to a Board where a given instrument is traded G1 : Main G2 : Pre open G3 : Post closing G4 : Odd lot G7 : Buy-in G8 : Sell-out T1 : Negotiation (regular) T4 : Negotiation (regular for Odd lot) T2 : Negotiation (pre) T3 : Negotiation (post) T6 : Negotiation (post for Odd lot) R1 : Negotiation (Repo) AL : All Boards
B8: =INDEX('Interface List'!$D$7:$D$45,MATCH($C8,'Interface List'!$E$7:$E$45,0)) -> IFMDFIX0003 | C8: Security Information Notification | D8: 55 | E8: =VLOOKUP($D8,'Tag(Glossary)'!$B:$G,2,0) -> Symbol | F8: Y | G8: =VLOOKUP($D8,'Tag(Glossary)'!$B:$G,4,0) -> String | H8: =VLOOKUP($D8,'Tag(Glossary)'!$B:$G,5,0) -> 12 | I8: =VLOOKUP($D8,'Tag(Glossary)'!$B:$H,6,0)&IF(ISBLANK(VLOOKUP($D8,'Tag(Glossary)'!$B:$H,7,0)),"",CHAR(10))&VLOOKUP($D8,'Tag(Glossary)'!$B:$H,7,0) -> The unique code of an issue (a.k.a. instrument or symbol). Generally it is ISIN code but in case of Repo market it is defined as the exchange staffs want
B9: =INDEX('Interface List'!$D$7:$D$45,MATCH($C9,'Interface List'!$E$7:$E$45,0)) -> IFMDFIX0003 | C9: Security Information Notification | D9: 20013 | E9: =VLOOKUP($D9,'Tag(Glossary)'!$B:$G,2,0) -> ReferencePrice | F9: N | G9: =VLOOKUP($D9,'Tag(Glossary)'!$B:$G,4,0) -> Price | H9: =VLOOKUP($D9,'Tag(Glossary)'!$B:$G,5,0) -> 15(9.4) | I9: =VLOOKUP($D9,'Tag(Glossary)'!$B:$H,6,0)&IF(ISBLANK(VLOOKUP($D9,'Tag(Glossary)'!$B:$H,7,0)),"",CHAR(10))&VLOOKUP($D9,'Tag(Glossary)'!$B:$H,7,0) -> Reference price of a given instrument. Price limit is determined based on this price.
B10: =INDEX('Interface List'!$D$7:$D$45,MATCH($C10,'Interface List'!$E$7:$E$45,0)) -> IFMDFIX0003 | C10: Security Information Notification | D10: 1149 | E10: =VLOOKUP($D10,'Tag(Glossary)'!$B:$G,2,0) -> HighLimitPrice | F10: N | G10: =VLOOKUP($D10,'Tag(Glossary)'!$B:$G,4,0) -> Price | H10: =VLOOKUP($D10,'Tag(Glossary)'!$B:$G,5,0) -> 15(9.4) | I10: =VLOOKUP($D10,'Tag(Glossary)'!$B:$H,6,0)&IF(ISBLANK(VLOOKUP($D10,'Tag(Glossary)'!$B:$H,7,0)),"",CHAR(10))&VLOOKUP($D10,'Tag(Glossary)'!$B:$H,7,0) -> Available high limit price for the tradig day
B11: =INDEX('Interface List'!$D$7:$D$45,MATCH($C11,'Interface List'!$E$7:$E$45,0)) -> IFMDFIX0003 | C11: Security Information Notification | D11: 1148 | E11: =VLOOKUP($D11,'Tag(Glossary)'!$B:$G,2,0) -> LowLimitPrice | F11: N | G11: =VLOOKUP($D11,'Tag(Glossary)'!$B:$G,4,0) -> Price | H11: =VLOOKUP($D11,'Tag(Glossary)'!$B:$G,5,0) -> 15(9.4) | I11: =VLOOKUP($D11,'Tag(Glossary)'!$B:$H,6,0)&IF(ISBLANK(VLOOKUP($D11,'Tag(Glossary)'!$B:$H,7,0)),"",CHAR(10))&VLOOKUP($D11,'Tag(Glossary)'!$B:$H,7,0) -> Available low limit price for the tradig day
B12: =INDEX('Interface List'!$D$7:$D$45,MATCH($C12,'Interface List'!$E$7:$E$45,0)) -> IFMDFIX0003 | C12: Security Information Notification | D12: 20014 | E12: =VLOOKUP($D12,'Tag(Glossary)'!$B:$G,2,0) -> EvaluationPrice | F12: N | G12: =VLOOKUP($D12,'Tag(Glossary)'!$B:$G,4,0) -> Price | H12: =VLOOKUP($D12,'Tag(Glossary)'!$B:$G,5,0) -> 15(9.4) | I12: =VLOOKUP($D12,'Tag(Glossary)'!$B:$H,6,0)&IF(ISBLANK(VLOOKUP($D12,'Tag(Glossary)'!$B:$H,7,0)),"",CHAR(10))&VLOOKUP($D12,'Tag(Glossary)'!$B:$H,7,0) -> Valuation price for a 'Re-Valuation' instrument. For such instrument, price limit is set based on this price until the first execution. Once the first execution is occurred, price limit is set again base on the price of the first execution.
B13: =INDEX('Interface List'!$D$7:$D$45,MATCH($C13,'Interface List'!$E$7:$E$45,0)) -> IFMDFIX0003 | C13: Security Information Notification | D13: 20015 | E13: =VLOOKUP($D13,'Tag(Glossary)'!$B:$G,2,0) -> HgstOrderPrice | F13: N | G13: =VLOOKUP($D13,'Tag(Glossary)'!$B:$G,4,0) -> Price | H13: =VLOOKUP($D13,'Tag(Glossary)'!$B:$G,5,0) -> 15 (9.4) | I13: =VLOOKUP($D13,'Tag(Glossary)'!$B:$H,6,0)&IF(ISBLANK(VLOOKUP($D13,'Tag(Glossary)'!$B:$H,7,0)),"",CHAR(10))&VLOOKUP($D13,'Tag(Glossary)'!$B:$H,7,0) -> Upper price limit for a 'Re-Valuation' instrument during the opening call auction (or until the first execution).
B14: =INDEX('Interface List'!$D$7:$D$45,MATCH($C14,'Interface List'!$E$7:$E$45,0)) -> IFMDFIX0003 | C14: Security Information Notification | D14: 20016 | E14: =VLOOKUP($D14,'Tag(Glossary)'!$B:$G,2,0) -> LwstOrderPrice | F14: N | G14: =VLOOKUP($D14,'Tag(Glossary)'!$B:$G,4,0) -> Price | H14: =VLOOKUP($D14,'Tag(Glossary)'!$B:$G,5,0) -> 15 (9.4) | I14: =VLOOKUP($D14,'Tag(Glossary)'!$B:$H,6,0)&IF(ISBLANK(VLOOKUP($D14,'Tag(Glossary)'!$B:$H,7,0)),"",CHAR(10))&VLOOKUP($D14,'Tag(Glossary)'!$B:$H,7,0) -> Lower price limit for a 'Re-Valuation' instrument during the opening call auction (or until the first execution).
B15: =INDEX('Interface List'!$D$7:$D$45,MATCH($C15,'Interface List'!$E$7:$E$45,0)) -> IFMDFIX0003 | C15: Security Information Notification | D15: 20020 | E15: =VLOOKUP($D15,'Tag(Glossary)'!$B:$G,2,0) -> ListedShares | F15: N | G15: =VLOOKUP($D15,'Tag(Glossary)'!$B:$G,4,0) -> Int | H15: =VLOOKUP($D15,'Tag(Glossary)'!$B:$G,5,0) -> 16 | I15: =VLOOKUP($D15,'Tag(Glossary)'!$B:$H,6,0)&IF(ISBLANK(VLOOKUP($D15,'Tag(Glossary)'!$B:$H,7,0)),"",CHAR(10))&VLOOKUP($D15,'Tag(Glossary)'!$B:$H,7,0) -> Number of listed stocks
B16: =INDEX('Interface List'!$D$7:$D$45,MATCH($C16,'Interface List'!$E$7:$E$45,0)) -> IFMDFIX0003 | C16: Security Information Notification | D16: 20018 | E16: =VLOOKUP($D16,'Tag(Glossary)'!$B:$G,2,0) -> ExClassType | F16: N | G16: =VLOOKUP($D16,'Tag(Glossary)'!$B:$G,4,0) -> String | H16: =VLOOKUP($D16,'Tag(Glossary)'!$B:$G,5,0) -> 2 | I16: =VLOOKUP($D16,'Tag(Glossary)'!$B:$H,6,0)&IF(ISBLANK(VLOOKUP($D16,'Tag(Glossary)'!$B:$H,7,0)),"",CHAR(10))&VLOOKUP($D16,'Tag(Glossary)'!$B:$H,7,0) -> Corporate action type that may affect reference price. 00: N/A 01: Stock Dividend/Bonus (D/B) 02: Cash Dividend 04: Right Offering (RO) 03: Stock D/B + Cash D 05: RO + Stock D/B 06: RO + Cash D 07: RO + Stock D/B + Cash D 08: Convertible Bond 16: Treasury Stock Div. P1: Stock Split P2: Stock Merge XX: Etc.
B17: =INDEX('Interface List'!$D$7:$D$45,MATCH($C17,'Interface List'!$E$7:$E$45,0)) -> IFMDFIX0003 | C17: Security Information Notification | E17: Standard Trailer | F17: Y

Sheet Symbol Closing Info
B2: Symbol Closing Information
A4: 추 | B4: Interface ID | C4: Interface Name | D4: Tag | E4: Field Name | F4: Req'd | G4: Format | H4: Length | I4: Comments
B5: =INDEX('Interface List'!$D$7:$D$45,MATCH($C5,'Interface List'!$E$7:$E$45,0)) -> IFMDFIX0004 | C5: Symbol Closing Information | E5: Standard Header | F5: Y | I5: MsgType = M8
B6: =INDEX('Interface List'!$D$7:$D$45,MATCH($C6,'Interface List'!$E$7:$E$45,0)) -> IFMDFIX0004 | C6: Symbol Closing Information | D6: 30001 | E6: =VLOOKUP($D6,'Tag(Glossary)'!$B:$G,2,0) -> MarketID | F6: Y | G6: =VLOOKUP($D6,'Tag(Glossary)'!$B:$G,4,0) -> String | H6: =VLOOKUP($D6,'Tag(Glossary)'!$B:$G,5,0) -> 3 | I6: =VLOOKUP($D6,'Tag(Glossary)'!$B:$H,6,0)&IF(ISBLANK(VLOOKUP($D6,'Tag(Glossary)'!$B:$H,7,0)),"",CHAR(10))&VLOOKUP($D6,'Tag(Glossary)'!$B:$H,7,0) -> ID for identifying the market <Hochiminh Exchange> - STO: HoSE Stock Market - BDO: HoSE Bond Market - RPO: HoSE Repo Market <Hanoi Exchange> - STX: HNX Listed Stock Market - BDX: HNX Government Bond Market - DVX: HNX Derivative Market - UPX: HNX UpCoM Stock Market - HCX: HNX Corporate Bond Market
B7: =INDEX('Interface List'!$D$7:$D$45,MATCH($C7,'Interface List'!$E$7:$E$45,0)) -> IFMDFIX0004 | C7: Symbol Closing Information | D7: 20004 | E7: =VLOOKUP($D7,'Tag(Glossary)'!$B:$G,2,0) -> BoardID | F7: Y | G7: =VLOOKUP($D7,'Tag(Glossary)'!$B:$G,4,0) -> String | H7: =VLOOKUP($D7,'Tag(Glossary)'!$B:$G,5,0) -> 2 | I7: =VLOOKUP($D7,'Tag(Glossary)'!$B:$H,6,0)&IF(ISBLANK(VLOOKUP($D7,'Tag(Glossary)'!$B:$H,7,0)),"",CHAR(10))&VLOOKUP($D7,'Tag(Glossary)'!$B:$H,7,0) -> Unique identifier to a Board where a given instrument is traded G1 : Main G2 : Pre open G3 : Post closing G4 : Odd lot G7 : Buy-in G8 : Sell-out T1 : Negotiation (regular) T4 : Negotiation (regular for Odd lot) T2 : Negotiation (pre) T3 : Negotiation (post) T6 : Negotiation (post for Odd lot) R1 : Negotiation (Repo) AL : All Boards
B8: =INDEX('Interface List'!$D$7:$D$45,MATCH($C8,'Interface List'!$E$7:$E$45,0)) -> IFMDFIX0004 | C8: Symbol Closing Information | D8: 55 | E8: =VLOOKUP($D8,'Tag(Glossary)'!$B:$G,2,0) -> Symbol | F8: Y | G8: =VLOOKUP($D8,'Tag(Glossary)'!$B:$G,4,0) -> String | H8: =VLOOKUP($D8,'Tag(Glossary)'!$B:$G,5,0) -> 12 | I8: =VLOOKUP($D8,'Tag(Glossary)'!$B:$H,6,0)&IF(ISBLANK(VLOOKUP($D8,'Tag(Glossary)'!$B:$H,7,0)),"",CHAR(10))&VLOOKUP($D8,'Tag(Glossary)'!$B:$H,7,0) -> The unique code of an issue (a.k.a. instrument or symbol). Generally it is ISIN code but in case of Repo market it is defined as the exchange staffs want
B9: =INDEX('Interface List'!$D$7:$D$45,MATCH($C9,'Interface List'!$E$7:$E$45,0)) -> IFMDFIX0004 | C9: Symbol Closing Information | D9: 20026 | E9: =VLOOKUP($D9,'Tag(Glossary)'!$B:$G,2,0) -> SymbolCloseInfoPx | F9: Y | G9: =VLOOKUP($D9,'Tag(Glossary)'!$B:$G,4,0) -> Price | H9: =VLOOKUP($D9,'Tag(Glossary)'!$B:$G,5,0) -> 15(9.4) | I9: =VLOOKUP($D9,'Tag(Glossary)'!$B:$H,6,0)&IF(ISBLANK(VLOOKUP($D9,'Tag(Glossary)'!$B:$H,7,0)),"",CHAR(10))&VLOOKUP($D9,'Tag(Glossary)'!$B:$H,7,0) -> The last execution price of that day. If there is no execution it is replaced with the reference price, and if no reference price is given then it will be 0 (zero)
B10: =INDEX('Interface List'!$D$7:$D$45,MATCH($C10,'Interface List'!$E$7:$E$45,0)) -> IFMDFIX0004 | C10: Symbol Closing Information | D10: 30541 | E10: =VLOOKUP($D10,'Tag(Glossary)'!$B:$G,2,0) -> SymbolCloseInfoYield | F10: Y | G10: =VLOOKUP($D10,'Tag(Glossary)'!$B:$G,4,0) -> Float | H10: =VLOOKUP($D10,'Tag(Glossary)'!$B:$G,5,0) -> 13(5.6) | I10: =VLOOKUP($D10,'Tag(Glossary)'!$B:$H,6,0)&IF(ISBLANK(VLOOKUP($D10,'Tag(Glossary)'!$B:$H,7,0)),"",CHAR(10))&VLOOKUP($D10,'Tag(Glossary)'!$B:$H,7,0) -> Final yield of a bond calculated using the closing price of that day
B11: =INDEX('Interface List'!$D$7:$D$45,MATCH($C11,'Interface List'!$E$7:$E$45,0)) -> IFMDFIX0004 | C11: Symbol Closing Information | D11: 20027 | E11: =VLOOKUP($D11,'Tag(Glossary)'!$B:$G,2,0) -> SymbolCloseInfoPxType | F11: Y | G11: =VLOOKUP($D11,'Tag(Glossary)'!$B:$G,4,0) -> String | H11: =VLOOKUP($D11,'Tag(Glossary)'!$B:$G,5,0) -> 1 | I11: =VLOOKUP($D11,'Tag(Glossary)'!$B:$H,6,0)&IF(ISBLANK(VLOOKUP($D11,'Tag(Glossary)'!$B:$H,7,0)),"",CHAR(10))&VLOOKUP($D11,'Tag(Glossary)'!$B:$H,7,0) -> Type of closing price 1: Actual Trade 2: Biased Quotation 3: No Trade 4: Biased Quotation of an Re-Valuation Instr.
B12: =INDEX('Interface List'!$D$7:$D$45,MATCH($C12,'Interface List'!$E$7:$E$45,0)) -> IFMDFIX0004 | C12: Symbol Closing Information | E12: Standard Trailer | F12: Y

Sheet Volatility Interruption
B2: Volatility Interruption
B4: Interface ID | C4: Interface Name | D4: Tag | E4: Field Name | F4: Req'd | G4: Format | H4: Length | I4: Comments
B5: =INDEX('Interface List'!$D$7:$D$45,MATCH($C5,'Interface List'!$E$7:$E$45,0)) -> IFMDFIX0005 | C5: Volatility Interruption | E5: Standard Header | F5: Y | I5: MsgType = MD
B6: =INDEX('Interface List'!$D$7:$D$45,MATCH($C6,'Interface List'!$E$7:$E$45,0)) -> IFMDFIX0005 | C6: Volatility Interruption | D6: 30001 | E6: =VLOOKUP($D6,'Tag(Glossary)'!$B:$G,2,0) -> MarketID | F6: Y | G6: =VLOOKUP($D6,'Tag(Glossary)'!$B:$G,4,0) -> String | H6: =VLOOKUP($D6,'Tag(Glossary)'!$B:$G,5,0) -> 3 | I6: =VLOOKUP($D6,'Tag(Glossary)'!$B:$H,6,0)&IF(ISBLANK(VLOOKUP($D6,'Tag(Glossary)'!$B:$H,7,0)),"",CHAR(10))&VLOOKUP($D6,'Tag(Glossary)'!$B:$H,7,0) -> ID for identifying the market <Hochiminh Exchange> - STO: HoSE Stock Market - BDO: HoSE Bond Market - RPO: HoSE Repo Market <Hanoi Exchange> - STX: HNX Listed Stock Market - BDX: HNX Government Bond Market - DVX: HNX Derivative Market - UPX: HNX UpCoM Stock Market - HCX: HNX Corporate Bond Market
B7: =INDEX('Interface List'!$D$7:$D$45,MATCH($C7,'Interface List'!$E$7:$E$45,0)) -> IFMDFIX0005 | C7: Volatility Interruption | D7: 20004 | E7: =VLOOKUP($D7,'Tag(Glossary)'!$B:$G,2,0) -> BoardID | F7: Y | G7: =VLOOKUP($D7,'Tag(Glossary)'!$B:$G,4,0) -> String | H7: =VLOOKUP($D7,'Tag(Glossary)'!$B:$G,5,0) -> 2 | I7: =VLOOKUP($D7,'Tag(Glossary)'!$B:$H,6,0)&IF(ISBLANK(VLOOKUP($D7,'Tag(Glossary)'!$B:$H,7,0)),"",CHAR(10))&VLOOKUP($D7,'Tag(Glossary)'!$B:$H,7,0) -> Unique identifier to a Board where a given instrument is traded G1 : Main G2 : Pre open G3 : Post closing G4 : Odd lot G7 : Buy-in G8 : Sell-out T1 : Negotiation (regular) T4 : Negotiation (regular for Odd lot) T2 : Negotiation (pre) T3 : Negotiation (post) T6 : Negotiation (post for Odd lot) R1 : Negotiation (Repo) AL : All Boards
B8: =INDEX('Interface List'!$D$7:$D$45,MATCH($C8,'Interface List'!$E$7:$E$45,0)) -> IFMDFIX0005 | C8: Volatility Interruption | D8: 55 | E8: =VLOOKUP($D8,'Tag(Glossary)'!$B:$G,2,0) -> Symbol | F8: Y | G8: =VLOOKUP($D8,'Tag(Glossary)'!$B:$G,4,0) -> String | H8: =VLOOKUP($D8,'Tag(Glossary)'!$B:$G,5,0) -> 12 | I8: =VLOOKUP($D8,'Tag(Glossary)'!$B:$H,6,0)&IF(ISBLANK(VLOOKUP($D8,'Tag(Glossary)'!$B:$H,7,0)),"",CHAR(10))&VLOOKUP($D8,'Tag(Glossary)'!$B:$H,7,0) -> The unique code of an issue (a.k.a. instrument or symbol). Generally it is ISIN code but in case of Repo market it is defined as the exchange staffs want
B9: =INDEX('Interface List'!$D$7:$D$45,MATCH($C9,'Interface List'!$E$7:$E$45,0)) -> IFMDFIX0005 | C9: Volatility Interruption | D9: 20030 | E9: =VLOOKUP($D9,'Tag(Glossary)'!$B:$G,2,0) -> VITypeCode | F9: Y | G9: =VLOOKUP($D9,'Tag(Glossary)'!$B:$G,4,0) -> String | H9: =VLOOKUP($D9,'Tag(Glossary)'!$B:$G,5,0) -> 1 | I9: =VLOOKUP($D9,'Tag(Glossary)'!$B:$H,6,0)&IF(ISBLANK(VLOOKUP($D9,'Tag(Glossary)'!$B:$H,7,0)),"",CHAR(10))&VLOOKUP($D9,'Tag(Glossary)'!$B:$H,7,0) -> Indicates whether VI is activated or released. 1 = Activated 2 = Released
B10: =INDEX('Interface List'!$D$7:$D$45,MATCH($C10,'Interface List'!$E$7:$E$45,0)) -> IFMDFIX0005 | C10: Volatility Interruption | D10: 20031 | E10: =VLOOKUP($D10,'Tag(Glossary)'!$B:$G,2,0) -> VIKindCode | F10: Y | G10: =VLOOKUP($D10,'Tag(Glossary)'!$B:$G,4,0) -> String | H10: =VLOOKUP($D10,'Tag(Glossary)'!$B:$G,5,0) -> 1 | I10: =VLOOKUP($D10,'Tag(Glossary)'!$B:$H,6,0)&IF(ISBLANK(VLOOKUP($D10,'Tag(Glossary)'!$B:$H,7,0)),"",CHAR(10))&VLOOKUP($D10,'Tag(Glossary)'!$B:$H,7,0) -> Indicates which kind of VI is activated or released. 1 = Static VI 2 = Dynamic VI 3 = Static VI + Dynamic VI
B11: =INDEX('Interface List'!$D$7:$D$45,MATCH($C11,'Interface List'!$E$7:$E$45,0)) -> IFMDFIX0005 | C11: Volatility Interruption | D11: 20032 | E11: =VLOOKUP($D11,'Tag(Glossary)'!$B:$G,2,0) -> StaticVIBasePrice | F11: Y | G11: =VLOOKUP($D11,'Tag(Glossary)'!$B:$G,4,0) -> Price | H11: =VLOOKUP($D11,'Tag(Glossary)'!$B:$G,5,0) -> 15 (9.4) | I11: =VLOOKUP($D11,'Tag(Glossary)'!$B:$H,6,0)&IF(ISBLANK(VLOOKUP($D11,'Tag(Glossary)'!$B:$H,7,0)),"",CHAR(10))&VLOOKUP($D11,'Tag(Glossary)'!$B:$H,7,0) -> Indicates static VI reference price. Price range for static VI is determined based on this price, and static VI is activated when an order is about to be executed outside the VI price range.
B12: =INDEX('Interface List'!$D$7:$D$45,MATCH($C12,'Interface List'!$E$7:$E$45,0)) -> IFMDFIX0005 | C12: Volatility Interruption | D12: 20047 | E12: =VLOOKUP($D12,'Tag(Glossary)'!$B:$G,2,0) -> DynamicVIBasePrice | F12: Y | G12: =VLOOKUP($D12,'Tag(Glossary)'!$B:$G,4,0) -> Price | H12: =VLOOKUP($D12,'Tag(Glossary)'!$B:$G,5,0) -> 15 (9.4) | I12: =VLOOKUP($D12,'Tag(Glossary)'!$B:$H,6,0)&IF(ISBLANK(VLOOKUP($D12,'Tag(Glossary)'!$B:$H,7,0)),"",CHAR(10))&VLOOKUP($D12,'Tag(Glossary)'!$B:$H,7,0) -> Indicates dynamic VI reference price. Price range for dynamic VI is determined based on this price, and dynamic VI is activated when an order is about to be executed outside the VI price range.
B13: =INDEX('Interface List'!$D$7:$D$45,MATCH($C13,'Interface List'!$E$7:$E$45,0)) -> IFMDFIX0005 | C13: Volatility Interruption | D13: 20033 | E13: =VLOOKUP($D13,'Tag(Glossary)'!$B:$G,2,0) -> VIPrice | F13: Y | G13: =VLOOKUP($D13,'Tag(Glossary)'!$B:$G,4,0) -> Price | H13: =VLOOKUP($D13,'Tag(Glossary)'!$B:$G,5,0) -> 15 (9.4) | I13: =VLOOKUP($D13,'Tag(Glossary)'!$B:$H,6,0)&IF(ISBLANK(VLOOKUP($D13,'Tag(Glossary)'!$B:$H,7,0)),"",CHAR(10))&VLOOKUP($D13,'Tag(Glossary)'!$B:$H,7,0) -> VI Triggering Price
B14: =INDEX('Interface List'!$D$7:$D$45,MATCH($C14,'Interface List'!$E$7:$E$45,0)) -> IFMDFIX0005 | C14: Volatility Interruption | D14: 20034 | E14: =VLOOKUP($D14,'Tag(Glossary)'!$B:$G,2,0) -> StaticVIDispartiyRatio | F14: Y | G14: =VLOOKUP($D14,'Tag(Glossary)'!$B:$G,4,0) -> Price | H14: =VLOOKUP($D14,'Tag(Glossary)'!$B:$G,5,0) -> 8(3.3) | I14: =VLOOKUP($D14,'Tag(Glossary)'!$B:$H,6,0)&IF(ISBLANK(VLOOKUP($D14,'Tag(Glossary)'!$B:$H,7,0)),"",CHAR(10))&VLOOKUP($D14,'Tag(Glossary)'!$B:$H,7,0) -> Indicates static VI activation ratio expressed in percent. static VI price range is defined as range from static VI reference price plus/minus this ratio. For example, if static VI reference price is 1000 and this ratio is 2.5, then static VI price range.
B15: =INDEX('Interface List'!$D$7:$D$45,MATCH($C15,'Interface List'!$E$7:$E$45,0)) -> IFMDFIX0005 | C15: Volatility Interruption | D15: 20048 | E15: =VLOOKUP($D15,'Tag(Glossary)'!$B:$G,2,0) -> DynamicVIDispartiyRatio | F15: Y | G15: =VLOOKUP($D15,'Tag(Glossary)'!$B:$G,4,0) -> Price | H15: =VLOOKUP($D15,'Tag(Glossary)'!$B:$G,5,0) -> 8(3.3) | I15: =VLOOKUP($D15,'Tag(Glossary)'!$B:$H,6,0)&IF(ISBLANK(VLOOKUP($D15,'Tag(Glossary)'!$B:$H,7,0)),"",CHAR(10))&VLOOKUP($D15,'Tag(Glossary)'!$B:$H,7,0) -> Indicates dynamic VI activation ratio expressed in percent. Dynamic VI price range is defined as range from Dynamic VI reference price plus/minus this ratio. For example, if Dynamic VI reference price is 1000 and this ratio is 2, then Dynamic VI price range is from 980 to 1020.
B16: =INDEX('Interface List'!$D$7:$D$45,MATCH($C16,'Interface List'!$E$7:$E$45,0)) -> IFMDFIX0005 | C16: Volatility Interruption | E16: Standard Trailer | F16: Y

Sheet Market Maker Information
B2: Market Maker Information
B4: Interface ID | C4: Interface Name | D4: Tag | E4: Field Name | F4: Req'd | G4: Format | H4: Length | I4: Comments
B5: =INDEX('Interface List'!$D$7:$D$45,MATCH($C5,'Interface List'!$E$7:$E$45,0)) -> IFMDFIX0006 | C5: Market Maker Information | E5: Standard Header | F5: Y | I5: MsgType = MH
B6: =INDEX('Interface List'!$D$7:$D$45,MATCH($C6,'Interface List'!$E$7:$E$45,0)) -> IFMDFIX0006 | C6: Market Maker Information | D6: 30001 | E6: =VLOOKUP($D6,'Tag(Glossary)'!$B:$G,2,0) -> MarketID | F6: Y | G6: =VLOOKUP($D6,'Tag(Glossary)'!$B:$G,4,0) -> String | H6: =VLOOKUP($D6,'Tag(Glossary)'!$B:$G,5,0) -> 3 | I6: =VLOOKUP($D6,'Tag(Glossary)'!$B:$H,6,0)&IF(ISBLANK(VLOOKUP($D6,'Tag(Glossary)'!$B:$H,7,0)),"",CHAR(10))&VLOOKUP($D6,'Tag(Glossary)'!$B:$H,7,0) -> ID for identifying the market <Hochiminh Exchange> - STO: HoSE Stock Market - BDO: HoSE Bond Market - RPO: HoSE Repo Market <Hanoi Exchange> - STX: HNX Listed Stock Market - BDX: HNX Government Bond Market - DVX: HNX Derivative Market - UPX: HNX UpCoM Stock Market - HCX: HNX Corporate Bond Market
B7: =INDEX('Interface List'!$D$7:$D$45,MATCH($C7,'Interface List'!$E$7:$E$45,0)) -> IFMDFIX0006 | C7: Market Maker Information | D7: 30574 | E7: =VLOOKUP($D7,'Tag(Glossary)'!$B:$G,2,0) -> MarketMakerContractCode | F7: Y | G7: =VLOOKUP($D7,'Tag(Glossary)'!$B:$G,4,0) -> String | H7: =VLOOKUP($D7,'Tag(Glossary)'!$B:$G,5,0) -> 12 | I7: =VLOOKUP($D7,'Tag(Glossary)'!$B:$H,6,0)&IF(ISBLANK(VLOOKUP($D7,'Tag(Glossary)'!$B:$H,7,0)),"",CHAR(10))&VLOOKUP($D7,'Tag(Glossary)'!$B:$H,7,0) -> Unit of agreement objects for market making 1) Stock/Bond Market: Instrument ISIN code 2) Derivatives Market: Product ID
B8: =INDEX('Interface List'!$D$7:$D$45,MATCH($C8,'Interface List'!$E$7:$E$45,0)) -> IFMDFIX0006 | C8: Market Maker Information | D8: 20023 | E8: =VLOOKUP($D8,'Tag(Glossary)'!$B:$G,2,0) -> MemberNo | F8: Y | G8: =VLOOKUP($D8,'Tag(Glossary)'!$B:$G,4,0) -> String | H8: =VLOOKUP($D8,'Tag(Glossary)'!$B:$G,5,0) -> 5 | I8: =VLOOKUP($D8,'Tag(Glossary)'!$B:$H,6,0)&IF(ISBLANK(VLOOKUP($D8,'Tag(Glossary)'!$B:$H,7,0)),"",CHAR(10))&VLOOKUP($D8,'Tag(Glossary)'!$B:$H,7,0) -> ID to identify or distinguish market participants or members with 5-digit numeric characters
B9: =INDEX('Interface List'!$D$7:$D$45,MATCH($C9,'Interface List'!$E$7:$E$45,0)) -> IFMDFIX0006 | C9: Market Maker Information | E9: Standard Trailer | F9: Y

Sheet Symbol Event
B2: Symbol Event
B4: Interface ID | C4: Interface Name | D4: Tag | E4: Field Name | F4: Req'd | G4: Format | H4: Length | I4: Comments
B5: =INDEX('Interface List'!$D$7:$D$45,MATCH($C5,'Interface List'!$E$7:$E$45,0)) -> IFMDFIX0007 | C5: Symbol Event | E5: Standard Header | F5: Y | I5: MsgType = MI
B6: =INDEX('Interface List'!$D$7:$D$45,MATCH($C6,'Interface List'!$E$7:$E$45,0)) -> IFMDFIX0007 | C6: Symbol Event | D6: 30001 | E6: =VLOOKUP($D6,'Tag(Glossary)'!$B:$G,2,0) -> MarketID | F6: Y | G6: =VLOOKUP($D6,'Tag(Glossary)'!$B:$G,4,0) -> String | H6: =VLOOKUP($D6,'Tag(Glossary)'!$B:$G,5,0) -> 3 | I6: =VLOOKUP($D6,'Tag(Glossary)'!$B:$H,6,0)&IF(ISBLANK(VLOOKUP($D6,'Tag(Glossary)'!$B:$H,7,0)),"",CHAR(10))&VLOOKUP($D6,'Tag(Glossary)'!$B:$H,7,0) -> ID for identifying the market <Hochiminh Exchange> - STO: HoSE Stock Market - BDO: HoSE Bond Market - RPO: HoSE Repo Market <Hanoi Exchange> - STX: HNX Listed Stock Market - BDX: HNX Government Bond Market - DVX: HNX Derivative Market - UPX: HNX UpCoM Stock Market - HCX: HNX Corporate Bond Market
B7: =INDEX('Interface List'!$D$7:$D$45,MATCH($C7,'Interface List'!$E$7:$E$45,0)) -> IFMDFIX0007 | C7: Symbol Event | D7: 55 | E7: =VLOOKUP($D7,'Tag(Glossary)'!$B:$G,2,0) -> Symbol | F7: Y | G7: =VLOOKUP($D7,'Tag(Glossary)'!$B:$G,4,0) -> String | H7: =VLOOKUP($D7,'Tag(Glossary)'!$B:$G,5,0) -> 12 | I7: =VLOOKUP($D7,'Tag(Glossary)'!$B:$H,6,0)&IF(ISBLANK(VLOOKUP($D7,'Tag(Glossary)'!$B:$H,7,0)),"",CHAR(10))&VLOOKUP($D7,'Tag(Glossary)'!$B:$H,7,0) -> The unique code of an issue (a.k.a. instrument or symbol). Generally it is ISIN code but in case of Repo market it is defined as the exchange staffs want
B8: =INDEX('Interface List'!$D$7:$D$45,MATCH($C8,'Interface List'!$E$7:$E$45,0)) -> IFMDFIX0007 | C8: Symbol Event | D8: 30575 | E8: =VLOOKUP($D8,'Tag(Glossary)'!$B:$G,2,0) -> EventKindCode | F8: Y | G8: =VLOOKUP($D8,'Tag(Glossary)'!$B:$G,4,0) -> String | H8: =VLOOKUP($D8,'Tag(Glossary)'!$B:$G,5,0) -> 2 | I8: =VLOOKUP($D8,'Tag(Glossary)'!$B:$H,6,0)&IF(ISBLANK(VLOOKUP($D8,'Tag(Glossary)'!$B:$H,7,0)),"",CHAR(10))&VLOOKUP($D8,'Tag(Glossary)'!$B:$H,7,0) -> Event code for such as trading halt, low liquidation and so forth. Code '91' (Trading Halt for Repo) is only used in Gateway Repo trading system, not the Terminal Repo trading system 01: Trading Halt 04: Liquidation Trading 91: Trading Halt for Repo
B9: =INDEX('Interface List'!$D$7:$D$45,MATCH($C9,'Interface List'!$E$7:$E$45,0)) -> IFMDFIX0007 | C9: Symbol Event | D9: 30576 | E9: =VLOOKUP($D9,'Tag(Glossary)'!$B:$G,2,0) -> EventOccurrenceReasonCode | F9: Y | G9: =VLOOKUP($D9,'Tag(Glossary)'!$B:$G,4,0) -> String | H9: =VLOOKUP($D9,'Tag(Glossary)'!$B:$G,5,0) -> 4 | I9: =VLOOKUP($D9,'Tag(Glossary)'!$B:$H,6,0)&IF(ISBLANK(VLOOKUP($D9,'Tag(Glossary)'!$B:$H,7,0)),"",CHAR(10))&VLOOKUP($D9,'Tag(Glossary)'!$B:$H,7,0) -> Reason for designating a specific event (trading halt, administrative instrument, etc.) to an instrument or a product
B10: =INDEX('Interface List'!$D$7:$D$45,MATCH($C10,'Interface List'!$E$7:$E$45,0)) -> IFMDFIX0007 | C10: Symbol Event | D10: 30577 | E10: =VLOOKUP($D10,'Tag(Glossary)'!$B:$G,2,0) -> EventStartDate | F10: Y | G10: =VLOOKUP($D10,'Tag(Glossary)'!$B:$G,4,0) -> LocalMktDate | H10: =VLOOKUP($D10,'Tag(Glossary)'!$B:$G,5,0) -> 8 | I10: =VLOOKUP($D10,'Tag(Glossary)'!$B:$H,6,0)&IF(ISBLANK(VLOOKUP($D10,'Tag(Glossary)'!$B:$H,7,0)),"",CHAR(10))&VLOOKUP($D10,'Tag(Glossary)'!$B:$H,7,0) -> Starting date of an event
B11: =INDEX('Interface List'!$D$7:$D$45,MATCH($C11,'Interface List'!$E$7:$E$45,0)) -> IFMDFIX0007 | C11: Symbol Event | D11: 30578 | E11: =VLOOKUP($D11,'Tag(Glossary)'!$B:$G,2,0) -> EventEndDate | F11: Y | G11: =VLOOKUP($D11,'Tag(Glossary)'!$B:$G,4,0) -> LocalMktDate | H11: =VLOOKUP($D11,'Tag(Glossary)'!$B:$G,5,0) -> 8 | I11: =VLOOKUP($D11,'Tag(Glossary)'!$B:$H,6,0)&IF(ISBLANK(VLOOKUP($D11,'Tag(Glossary)'!$B:$H,7,0)),"",CHAR(10))&VLOOKUP($D11,'Tag(Glossary)'!$B:$H,7,0) -> Ending date of an event
B12: =INDEX('Interface List'!$D$7:$D$45,MATCH($C12,'Interface List'!$E$7:$E$45,0)) -> IFMDFIX0007 | C12: Symbol Event | E12: Standard Trailer | F12: Y

Sheet Index Constituents Information
B2: Index Constituents Information
B4: Interface ID | C4: Interface Name | D4: Tag | E4: Field Name | F4: Req'd | G4: Format | H4: Length | I4: Comments
B5: =INDEX('Interface List'!$D$7:$D$45,MATCH($C5,'Interface List'!$E$7:$E$45,0)) -> IFMDFIX0008 | C5: Index Constituents Information | E5: Standard Header | F5: Y | I5: MsgType = ML
B6: =INDEX('Interface List'!$D$7:$D$45,MATCH($C6,'Interface List'!$E$7:$E$45,0)) -> IFMDFIX0008 | C6: Index Constituents Information | D6: 30001 | E6: =VLOOKUP($D6,'Tag(Glossary)'!$B:$G,2,0) -> MarketID | F6: Y | G6: =VLOOKUP($D6,'Tag(Glossary)'!$B:$G,4,0) -> String | H6: =VLOOKUP($D6,'Tag(Glossary)'!$B:$G,5,0) -> 3 | I6: =VLOOKUP($D6,'Tag(Glossary)'!$B:$H,6,0)&IF(ISBLANK(VLOOKUP($D6,'Tag(Glossary)'!$B:$H,7,0)),"",CHAR(10))&VLOOKUP($D6,'Tag(Glossary)'!$B:$H,7,0) -> ID for identifying the market <Hochiminh Exchange> - STO: HoSE Stock Market - BDO: HoSE Bond Market - RPO: HoSE Repo Market <Hanoi Exchange> - STX: HNX Listed Stock Market - BDX: HNX Government Bond Market - DVX: HNX Derivative Market - UPX: HNX UpCoM Stock Market - HCX: HNX Corporate Bond Market
B7: =INDEX('Interface List'!$D$7:$D$45,MATCH($C7,'Interface List'!$E$7:$E$45,0)) -> IFMDFIX0008 | C7: Index Constituents Information | D7: 30569 | E7: =VLOOKUP($D7,'Tag(Glossary)'!$B:$G,2,0) -> MarketIndexClass | F7: Y | G7: =VLOOKUP($D7,'Tag(Glossary)'!$B:$G,4,0) -> String | H7: =VLOOKUP($D7,'Tag(Glossary)'!$B:$G,5,0) -> 1 | I7: =VLOOKUP($D7,'Tag(Glossary)'!$B:$H,6,0)&IF(ISBLANK(VLOOKUP($D7,'Tag(Glossary)'!$B:$H,7,0)),"",CHAR(10))&VLOOKUP($D7,'Tag(Glossary)'!$B:$H,7,0) -> Market code of an index 1: HoSE 2: HNX 3: Composite (HoSE + HNX) 4. UPX
B8: =INDEX('Interface List'!$D$7:$D$45,MATCH($C8,'Interface List'!$E$7:$E$45,0)) -> IFMDFIX0008 | C8: Index Constituents Information | D8: 30167 | E8: =VLOOKUP($D8,'Tag(Glossary)'!$B:$G,2,0) -> IndexsTypeCode | F8: Y | G8: =VLOOKUP($D8,'Tag(Glossary)'!$B:$G,4,0) -> String | H8: =VLOOKUP($D8,'Tag(Glossary)'!$B:$G,5,0) -> 8 | I8: =VLOOKUP($D8,'Tag(Glossary)'!$B:$H,6,0)&IF(ISBLANK(VLOOKUP($D8,'Tag(Glossary)'!$B:$H,7,0)),"",CHAR(10))&VLOOKUP($D8,'Tag(Glossary)'!$B:$H,7,0) -> Industry Index Code for example 001: Composite index 002: VNALLshare index 100: VN30 index
B9: =INDEX('Interface List'!$D$7:$D$45,MATCH($C9,'Interface List'!$E$7:$E$45,0)) -> IFMDFIX0008 | C9: Index Constituents Information | D9: 15 | E9: =VLOOKUP($D9,'Tag(Glossary)'!$B:$G,2,0) -> Currency | F9: Y | G9: =VLOOKUP($D9,'Tag(Glossary)'!$B:$G,4,0) -> String | H9: =VLOOKUP($D9,'Tag(Glossary)'!$B:$G,5,0) -> 3 | I9: =VLOOKUP($D9,'Tag(Glossary)'!$B:$H,6,0)&IF(ISBLANK(VLOOKUP($D9,'Tag(Glossary)'!$B:$H,7,0)),"",CHAR(10))&VLOOKUP($D9,'Tag(Glossary)'!$B:$H,7,0) -> Currency code on ISO 4217 VND: Vietnamese Dong USD: US Dollar EUR: Euro
B10: =INDEX('Interface List'!$D$7:$D$45,MATCH($C10,'Interface List'!$E$7:$E$45,0)) -> IFMDFIX0008 | C10: Index Constituents Information | D10: 30632 | E10: =VLOOKUP($D10,'Tag(Glossary)'!$B:$G,2,0) -> IdxName | F10: Y | G10: =VLOOKUP($D10,'Tag(Glossary)'!$B:$G,4,0) -> String | H10: =VLOOKUP($D10,'Tag(Glossary)'!$B:$G,5,0) -> 120 | I10: =VLOOKUP($D10,'Tag(Glossary)'!$B:$H,6,0)&IF(ISBLANK(VLOOKUP($D10,'Tag(Glossary)'!$B:$H,7,0)),"",CHAR(10))&VLOOKUP($D10,'Tag(Glossary)'!$B:$H,7,0) -> Index Name
B11: =INDEX('Interface List'!$D$7:$D$45,MATCH($C11,'Interface List'!$E$7:$E$45,0)) -> IFMDFIX0008 | C11: Index Constituents Information | D11: 30633 | E11: =VLOOKUP($D11,'Tag(Glossary)'!$B:$G,2,0) -> IdxEnglishName | F11: Y | G11: =VLOOKUP($D11,'Tag(Glossary)'!$B:$G,4,0) -> String | H11: =VLOOKUP($D11,'Tag(Glossary)'!$B:$G,5,0) -> 80 | I11: =VLOOKUP($D11,'Tag(Glossary)'!$B:$H,6,0)&IF(ISBLANK(VLOOKUP($D11,'Tag(Glossary)'!$B:$H,7,0)),"",CHAR(10))&VLOOKUP($D11,'Tag(Glossary)'!$B:$H,7,0) -> Index English Name
B12: =INDEX('Interface List'!$D$7:$D$45,MATCH($C12,'Interface List'!$E$7:$E$45,0)) -> IFMDFIX0008 | C12: Index Constituents Information | D12: 30606 | E12: =VLOOKUP($D12,'Tag(Glossary)'!$B:$G,2,0) -> TotalMsgNo | F12: Y | G12: =VLOOKUP($D12,'Tag(Glossary)'!$B:$G,4,0) -> Int | H12: =VLOOKUP($D12,'Tag(Glossary)'!$B:$G,5,0) -> 16 | I12: =VLOOKUP($D12,'Tag(Glossary)'!$B:$H,6,0)&IF(ISBLANK(VLOOKUP($D12,'Tag(Glossary)'!$B:$H,7,0)),"",CHAR(10))&VLOOKUP($D12,'Tag(Glossary)'!$B:$H,7,0) -> 1. Disclosure : Total message number of messages for a discosure when the length of text is over the size 2. Index Constituents Information : Total number of contituents for an index
B13: =INDEX('Interface List'!$D$7:$D$45,MATCH($C13,'Interface List'!$E$7:$E$45,0)) -> IFMDFIX0008 | C13: Index Constituents Information | D13: 30607 | E13: =VLOOKUP($D13,'Tag(Glossary)'!$B:$G,2,0) -> CurrentMsgNo | F13: Y | G13: =VLOOKUP($D13,'Tag(Glossary)'!$B:$G,4,0) -> Int | H13: =VLOOKUP($D13,'Tag(Glossary)'!$B:$G,5,0) -> 16 | I13: =VLOOKUP($D13,'Tag(Glossary)'!$B:$H,6,0)&IF(ISBLANK(VLOOKUP($D13,'Tag(Glossary)'!$B:$H,7,0)),"",CHAR(10))&VLOOKUP($D13,'Tag(Glossary)'!$B:$H,7,0) -> 1. Disclosure : Current message number of messages for a disclosure when the length of text is over the size 2. Index Constituents Information : Current sequence number of contituents for an index
B14: =INDEX('Interface List'!$D$7:$D$45,MATCH($C14,'Interface List'!$E$7:$E$45,0)) -> IFMDFIX0008 | C14: Index Constituents Information | D14: 55 | E14: =VLOOKUP($D14,'Tag(Glossary)'!$B:$G,2,0) -> Symbol | F14: Y | G14: =VLOOKUP($D14,'Tag(Glossary)'!$B:$G,4,0) -> String | H14: =VLOOKUP($D14,'Tag(Glossary)'!$B:$G,5,0) -> 12 | I14: =VLOOKUP($D14,'Tag(Glossary)'!$B:$H,6,0)&IF(ISBLANK(VLOOKUP($D14,'Tag(Glossary)'!$B:$H,7,0)),"",CHAR(10))&VLOOKUP($D14,'Tag(Glossary)'!$B:$H,7,0) -> The unique code of an issue (a.k.a. instrument or symbol). Generally it is ISIN code but in case of Repo market it is defined as the exchange staffs want
B15: =INDEX('Interface List'!$D$7:$D$45,MATCH($C15,'Interface List'!$E$7:$E$45,0)) -> IFMDFIX0008 | C15: Index Constituents Information | E15: Standard Trailer | F15: Y

Sheet Random End
B2: Random End
B4: Interface ID | C4: Interface Name | D4: Tag | E4: Field Name | F4: Req'd | G4: Format | H4: Length | I4: Comments
B5: =INDEX('Interface List'!$D$7:$D$45,MATCH($C5,'Interface List'!$E$7:$E$45,0)) -> IFMDFIX0023 | C5: Random End | E5: Standard Header | F5: Y | I5: MsgType = MW
B6: =INDEX('Interface List'!$D$7:$D$45,MATCH($C6,'Interface List'!$E$7:$E$45,0)) -> IFMDFIX0023 | C6: Random End | D6: 30001 | E6: =VLOOKUP($D6,'Tag(Glossary)'!$B:$G,2,0) -> MarketID | F6: Y | G6: =VLOOKUP($D6,'Tag(Glossary)'!$B:$G,4,0) -> String | H6: =VLOOKUP($D6,'Tag(Glossary)'!$B:$G,5,0) -> 3 | I6: =VLOOKUP($D6,'Tag(Glossary)'!$B:$H,6,0)&IF(ISBLANK(VLOOKUP($D6,'Tag(Glossary)'!$B:$H,7,0)),"",CHAR(10))&VLOOKUP($D6,'Tag(Glossary)'!$B:$H,7,0) -> ID for identifying the market <Hochiminh Exchange> - STO: HoSE Stock Market - BDO: HoSE Bond Market - RPO: HoSE Repo Market <Hanoi Exchange> - STX: HNX Listed Stock Market - BDX: HNX Government Bond Market - DVX: HNX Derivative Market - UPX: HNX UpCoM Stock Market - HCX: HNX Corporate Bond Market
B7: =INDEX('Interface List'!$D$7:$D$45,MATCH($C7,'Interface List'!$E$7:$E$45,0)) -> IFMDFIX0023 | C7: Random End | D7: 20004 | E7: =VLOOKUP($D7,'Tag(Glossary)'!$B:$G,2,0) -> BoardID | F7: Y | G7: =VLOOKUP($D7,'Tag(Glossary)'!$B:$G,4,0) -> String | H7: =VLOOKUP($D7,'Tag(Glossary)'!$B:$G,5,0) -> 2 | I7: =VLOOKUP($D7,'Tag(Glossary)'!$B:$H,6,0)&IF(ISBLANK(VLOOKUP($D7,'Tag(Glossary)'!$B:$H,7,0)),"",CHAR(10))&VLOOKUP($D7,'Tag(Glossary)'!$B:$H,7,0) -> Unique identifier to a Board where a given instrument is traded G1 : Main G2 : Pre open G3 : Post closing G4 : Odd lot G7 : Buy-in G8 : Sell-out T1 : Negotiation (regular) T4 : Negotiation (regular for Odd lot) T2 : Negotiation (pre) T3 : Negotiation (post) T6 : Negotiation (post for Odd lot) R1 : Negotiation (Repo) AL : All Boards
B8: =INDEX('Interface List'!$D$7:$D$45,MATCH($C8,'Interface List'!$E$7:$E$45,0)) -> IFMDFIX0023 | C8: Random End | D8: 55 | E8: =VLOOKUP($D8,'Tag(Glossary)'!$B:$G,2,0) -> Symbol | F8: Y | G8: =VLOOKUP($D8,'Tag(Glossary)'!$B:$G,4,0) -> String | H8: =VLOOKUP($D8,'Tag(Glossary)'!$B:$G,5,0) -> 12 | I8: =VLOOKUP($D8,'Tag(Glossary)'!$B:$H,6,0)&IF(ISBLANK(VLOOKUP($D8,'Tag(Glossary)'!$B:$H,7,0)),"",CHAR(10))&VLOOKUP($D8,'Tag(Glossary)'!$B:$H,7,0) -> The unique code of an issue (a.k.a. instrument or symbol). Generally it is ISIN code but in case of Repo market it is defined as the exchange staffs want
B9: =INDEX('Interface List'!$D$7:$D$45,MATCH($C9,'Interface List'!$E$7:$E$45,0)) -> IFMDFIX0023 | C9: Random End | D9: 60 | E9: =VLOOKUP($D9,'Tag(Glossary)'!$B:$G,2,0) -> TransactTime | F9: Y | G9: =VLOOKUP($D9,'Tag(Glossary)'!$B:$G,4,0) -> UTCTime | H9: =VLOOKUP($D9,'Tag(Glossary)'!$B:$G,5,0) -> 9 | I9: =VLOOKUP($D9,'Tag(Glossary)'!$B:$H,6,0)&IF(ISBLANK(VLOOKUP($D9,'Tag(Glossary)'!$B:$H,7,0)),"",CHAR(10))&VLOOKUP($D9,'Tag(Glossary)'!$B:$H,7,0) -> Time of execution/order creation HHmmSSsss : Normal Case
B10: =INDEX('Interface List'!$D$7:$D$45,MATCH($C10,'Interface List'!$E$7:$E$45,0)) -> IFMDFIX0023 | C10: Random End | D10: 30615 | E10: =VLOOKUP($D10,'Tag(Glossary)'!$B:$G,2,0) -> RandomEndApplyClassification | F10: Y | G10: =VLOOKUP($D10,'Tag(Glossary)'!$B:$G,4,0) -> String | H10: =VLOOKUP($D10,'Tag(Glossary)'!$B:$G,5,0) -> 1 | I10: =VLOOKUP($D10,'Tag(Glossary)'!$B:$H,6,0)&IF(ISBLANK(VLOOKUP($D10,'Tag(Glossary)'!$B:$H,7,0)),"",CHAR(10))&VLOOKUP($D10,'Tag(Glossary)'!$B:$H,7,0) -> Value of type code for applying or releasing random end 1: Opening call auction session RE set 2: Opening call auction session RE release 3: Closing single price auction session RE set 4: Closing single price auction session RE release 5: Post-market off-hour RE set 6: Post-market off-hour RE release
B11: =INDEX('Interface List'!$D$7:$D$45,MATCH($C11,'Interface List'!$E$7:$E$45,0)) -> IFMDFIX0023 | C11: Random End | D11: 30616 | E11: =VLOOKUP($D11,'Tag(Glossary)'!$B:$G,2,0) -> RandomEndTentativeExecutionPrice | F11: Y | G11: =VLOOKUP($D11,'Tag(Glossary)'!$B:$G,4,0) -> Price | H11: =VLOOKUP($D11,'Tag(Glossary)'!$B:$G,5,0) -> 15(9.4) | I11: =VLOOKUP($D11,'Tag(Glossary)'!$B:$H,6,0)&IF(ISBLANK(VLOOKUP($D11,'Tag(Glossary)'!$B:$H,7,0)),"",CHAR(10))&VLOOKUP($D11,'Tag(Glossary)'!$B:$H,7,0) -> Tentative price of the execution in the call auction when the random end is applied
B12: =INDEX('Interface List'!$D$7:$D$45,MATCH($C12,'Interface List'!$E$7:$E$45,0)) -> IFMDFIX0023 | C12: Random End | D12: 30617 | E12: =VLOOKUP($D12,'Tag(Glossary)'!$B:$G,2,0) -> RandomEndEstimatedHighestPrice | F12: Y | G12: =VLOOKUP($D12,'Tag(Glossary)'!$B:$G,4,0) -> Price | H12: =VLOOKUP($D12,'Tag(Glossary)'!$B:$G,5,0) -> 15(9.4) | I12: =VLOOKUP($D12,'Tag(Glossary)'!$B:$H,6,0)&IF(ISBLANK(VLOOKUP($D12,'Tag(Glossary)'!$B:$H,7,0)),"",CHAR(10))&VLOOKUP($D12,'Tag(Glossary)'!$B:$H,7,0) -> Estimated highest price in the call auction when the random end is applied
B13: =INDEX('Interface List'!$D$7:$D$45,MATCH($C13,'Interface List'!$E$7:$E$45,0)) -> IFMDFIX0023 | C13: Random End | D13: 30618 | E13: =VLOOKUP($D13,'Tag(Glossary)'!$B:$G,2,0) -> RandomEndEstimatedHighestPriceDisparateRatio | F13: Y | G13: =VLOOKUP($D13,'Tag(Glossary)'!$B:$G,4,0) -> Float | H13: =VLOOKUP($D13,'Tag(Glossary)'!$B:$G,5,0) -> 13(5.6) | I13: =VLOOKUP($D13,'Tag(Glossary)'!$B:$H,6,0)&IF(ISBLANK(VLOOKUP($D13,'Tag(Glossary)'!$B:$H,7,0)),"",CHAR(10))&VLOOKUP($D13,'Tag(Glossary)'!$B:$H,7,0) -> Disparate ration between estimated the highest price and tentative price in a call auction
B14: =INDEX('Interface List'!$D$7:$D$45,MATCH($C14,'Interface List'!$E$7:$E$45,0)) -> IFMDFIX0023 | C14: Random End | D14: 30619 | E14: =VLOOKUP($D14,'Tag(Glossary)'!$B:$G,2,0) -> RandomEndEstimatedLowestPrice | F14: Y | G14: =VLOOKUP($D14,'Tag(Glossary)'!$B:$G,4,0) -> Price | H14: =VLOOKUP($D14,'Tag(Glossary)'!$B:$G,5,0) -> 15(9.4) | I14: =VLOOKUP($D14,'Tag(Glossary)'!$B:$H,6,0)&IF(ISBLANK(VLOOKUP($D14,'Tag(Glossary)'!$B:$H,7,0)),"",CHAR(10))&VLOOKUP($D14,'Tag(Glossary)'!$B:$H,7,0) -> Estimated lowest price in the call auction when the random end is applied
B15: =INDEX('Interface List'!$D$7:$D$45,MATCH($C15,'Interface List'!$E$7:$E$45,0)) -> IFMDFIX0023 | C15: Random End | D15: 30620 | E15: =VLOOKUP($D15,'Tag(Glossary)'!$B:$G,2,0) -> RandomEndEstimatedLowestPriceDisparateRatio | F15: Y | G15: =VLOOKUP($D15,'Tag(Glossary)'!$B:$G,4,0) -> Float | H15: =VLOOKUP($D15,'Tag(Glossary)'!$B:$G,5,0) -> 13(5.6) | I15: =VLOOKUP($D15,'Tag(Glossary)'!$B:$H,6,0)&IF(ISBLANK(VLOOKUP($D15,'Tag(Glossary)'!$B:$H,7,0)),"",CHAR(10))&VLOOKUP($D15,'Tag(Glossary)'!$B:$H,7,0) -> Disparate ration between estimated the lowest price and tentative price in a call auction
B16: =INDEX('Interface List'!$D$7:$D$45,MATCH($C16,'Interface List'!$E$7:$E$45,0)) -> IFMDFIX0023 | C16: Random End | D16: 30621 | E16: =VLOOKUP($D16,'Tag(Glossary)'!$B:$G,2,0) -> LatestPrice | F16: Y | G16: =VLOOKUP($D16,'Tag(Glossary)'!$B:$G,4,0) -> Price | H16: =VLOOKUP($D16,'Tag(Glossary)'!$B:$G,5,0) -> 15(9.4) | I16: =VLOOKUP($D16,'Tag(Glossary)'!$B:$H,6,0)&IF(ISBLANK(VLOOKUP($D16,'Tag(Glossary)'!$B:$H,7,0)),"",CHAR(10))&VLOOKUP($D16,'Tag(Glossary)'!$B:$H,7,0) -> Price of the latest execution before the call auction
B17: =INDEX('Interface List'!$D$7:$D$45,MATCH($C17,'Interface List'!$E$7:$E$45,0)) -> IFMDFIX0023 | C17: Random End | D17: 30622 | E17: =VLOOKUP($D17,'Tag(Glossary)'!$B:$G,2,0) -> LatestPriceDisparateRatio | F17: Y | G17: =VLOOKUP($D17,'Tag(Glossary)'!$B:$G,4,0) -> Float | H17: =VLOOKUP($D17,'Tag(Glossary)'!$B:$G,5,0) -> 13(5.6) | I17: =VLOOKUP($D17,'Tag(Glossary)'!$B:$H,6,0)&IF(ISBLANK(VLOOKUP($D17,'Tag(Glossary)'!$B:$H,7,0)),"",CHAR(10))&VLOOKUP($D17,'Tag(Glossary)'!$B:$H,7,0) -> Disparate ration between the latest execution price and tentative price in a call auction
B18: =INDEX('Interface List'!$D$7:$D$45,MATCH($C18,'Interface List'!$E$7:$E$45,0)) -> IFMDFIX0023 | C18: Random End | D18: 30623 | E18: =VLOOKUP($D18,'Tag(Glossary)'!$B:$G,2,0) -> RandomEndReleaseTime | F18: N | G18: =VLOOKUP($D18,'Tag(Glossary)'!$B:$G,4,0) -> String | H18: =VLOOKUP($D18,'Tag(Glossary)'!$B:$G,5,0) -> 9 | I18: =VLOOKUP($D18,'Tag(Glossary)'!$B:$H,6,0)&IF(ISBLANK(VLOOKUP($D18,'Tag(Glossary)'!$B:$H,7,0)),"",CHAR(10))&VLOOKUP($D18,'Tag(Glossary)'!$B:$H,7,0) -> Time of releasing the random end HHmmSSsss
B19: =INDEX('Interface List'!$D$7:$D$45,MATCH($C19,'Interface List'!$E$7:$E$45,0)) -> IFMDFIX0023 | C19: Random End | E19: Standard Trailer | F19: Y

Sheet Price
B2: Price
B4: Interface ID | C4: Interface Name | D4: Tag | E4: Field Name | F4: Req'd | G4: Format | H4: Length | I4: Comments
B5: =INDEX('Interface List'!$D$7:$D$45,MATCH($C5,'Interface List'!$E$7:$E$45,0)) -> IFMDFIX0009 | C5: Price | E5: Standard Header | F5: Y | I5: MsgType = X
B6: =INDEX('Interface List'!$D$7:$D$45,MATCH($C6,'Interface List'!$E$7:$E$45,0)) -> IFMDFIX0009 | C6: Price | D6: 30001 | E6: =VLOOKUP($D6,'Tag(Glossary)'!$B:$G,2,0) -> MarketID | F6: Y | G6: =VLOOKUP($D6,'Tag(Glossary)'!$B:$G,4,0) -> String | H6: =VLOOKUP($D6,'Tag(Glossary)'!$B:$G,5,0) -> 3 | I6: =VLOOKUP($D6,'Tag(Glossary)'!$B:$H,6,0)&IF(ISBLANK(VLOOKUP($D6,'Tag(Glossary)'!$B:$H,7,0)),"",CHAR(10))&VLOOKUP($D6,'Tag(Glossary)'!$B:$H,7,0) -> ID for identifying the market <Hochiminh Exchange> - STO: HoSE Stock Market - BDO: HoSE Bond Market - RPO: HoSE Repo Market <Hanoi Exchange> - STX: HNX Listed Stock Market - BDX: HNX Government Bond Market - DVX: HNX Derivative Market - UPX: HNX UpCoM Stock Market - HCX: HNX Corporate Bond Market
B7: =INDEX('Interface List'!$D$7:$D$45,MATCH($C7,'Interface List'!$E$7:$E$45,0)) -> IFMDFIX0009 | C7: Price | D7: 20004 | E7: =VLOOKUP($D7,'Tag(Glossary)'!$B:$G,2,0) -> BoardID | F7: Y | G7: =VLOOKUP($D7,'Tag(Glossary)'!$B:$G,4,0) -> String | H7: =VLOOKUP($D7,'Tag(Glossary)'!$B:$G,5,0) -> 2 | I7: =VLOOKUP($D7,'Tag(Glossary)'!$B:$H,6,0)&IF(ISBLANK(VLOOKUP($D7,'Tag(Glossary)'!$B:$H,7,0)),"",CHAR(10))&VLOOKUP($D7,'Tag(Glossary)'!$B:$H,7,0) -> Unique identifier to a Board where a given instrument is traded G1 : Main G2 : Pre open G3 : Post closing G4 : Odd lot G7 : Buy-in G8 : Sell-out T1 : Negotiation (regular) T4 : Negotiation (regular for Odd lot) T2 : Negotiation (pre) T3 : Negotiation (post) T6 : Negotiation (post for Odd lot) R1 : Negotiation (Repo) AL : All Boards
B8: =INDEX('Interface List'!$D$7:$D$45,MATCH($C8,'Interface List'!$E$7:$E$45,0)) -> IFMDFIX0009 | C8: Price | D8: 336 | E8: =VLOOKUP($D8,'Tag(Glossary)'!$B:$G,2,0) -> TradingSessionID | F8: Y | G8: =VLOOKUP($D8,'Tag(Glossary)'!$B:$G,4,0) -> String | H8: =VLOOKUP($D8,'Tag(Glossary)'!$B:$G,5,0) -> 2 | I8: =VLOOKUP($D8,'Tag(Glossary)'!$B:$H,6,0)&IF(ISBLANK(VLOOKUP($D8,'Tag(Glossary)'!$B:$H,7,0)),"",CHAR(10))&VLOOKUP($D8,'Tag(Glossary)'!$B:$H,7,0) -> Trading Session 01 = GT Order Load 10 = Opening Call Auction 11 = Opening Call Auction Extension 20 = Call Auction after Halt 21 = Call Auction after Halt Extension 30 = Closing Call Auction 40 = Continuous Auction 50 = VI Call Auction 51 = VI Call Auction Extension 60 = Order Accept Only 80 = Periodic Call Auction 90 = Trading Halt 99 = Board Closing
B9: =INDEX('Interface List'!$D$7:$D$45,MATCH($C9,'Interface List'!$E$7:$E$45,0)) -> IFMDFIX0009 | C9: Price | D9: 55 | E9: =VLOOKUP($D9,'Tag(Glossary)'!$B:$G,2,0) -> Symbol | F9: Y | G9: =VLOOKUP($D9,'Tag(Glossary)'!$B:$G,4,0) -> String | H9: =VLOOKUP($D9,'Tag(Glossary)'!$B:$G,5,0) -> 12 | I9: =VLOOKUP($D9,'Tag(Glossary)'!$B:$H,6,0)&IF(ISBLANK(VLOOKUP($D9,'Tag(Glossary)'!$B:$H,7,0)),"",CHAR(10))&VLOOKUP($D9,'Tag(Glossary)'!$B:$H,7,0) -> The unique code of an issue (a.k.a. instrument or symbol). Generally it is ISIN code but in case of Repo market it is defined as the exchange staffs want
B10: =INDEX('Interface List'!$D$7:$D$45,MATCH($C10,'Interface List'!$E$7:$E$45,0)) -> IFMDFIX0009 | C10: Price | D10: 75 | E10: =VLOOKUP($D10,'Tag(Glossary)'!$B:$G,2,0) -> TradeDate | F10: Y | G10: =VLOOKUP($D10,'Tag(Glossary)'!$B:$G,4,0) -> LocalMktDate | H10: =VLOOKUP($D10,'Tag(Glossary)'!$B:$G,5,0) -> 8 | I10: =VLOOKUP($D10,'Tag(Glossary)'!$B:$H,6,0)&IF(ISBLANK(VLOOKUP($D10,'Tag(Glossary)'!$B:$H,7,0)),"",CHAR(10))&VLOOKUP($D10,'Tag(Glossary)'!$B:$H,7,0) -> Indicates local date of trade refereneced in this message in YYYYMMDD format. YYYYMMDD
B11: =INDEX('Interface List'!$D$7:$D$45,MATCH($C11,'Interface List'!$E$7:$E$45,0)) -> IFMDFIX0009 | C11: Price | D11: 60 | E11: =VLOOKUP($D11,'Tag(Glossary)'!$B:$G,2,0) -> TransactTime | F11: Y | G11: =VLOOKUP($D11,'Tag(Glossary)'!$B:$G,4,0) -> UTCTime | H11: =VLOOKUP($D11,'Tag(Glossary)'!$B:$G,5,0) -> 9 | I11: =VLOOKUP($D11,'Tag(Glossary)'!$B:$H,6,0)&IF(ISBLANK(VLOOKUP($D11,'Tag(Glossary)'!$B:$H,7,0)),"",CHAR(10))&VLOOKUP($D11,'Tag(Glossary)'!$B:$H,7,0) -> Time of execution/order creation HHmmSSsss : Normal Case
B12: =INDEX('Interface List'!$D$7:$D$45,MATCH($C12,'Interface List'!$E$7:$E$45,0)) -> IFMDFIX0009 | C12: Price | D12: 387 | E12: =VLOOKUP($D12,'Tag(Glossary)'!$B:$G,2,0) -> TotalVolumeTraded | F12: N | G12: =VLOOKUP($D12,'Tag(Glossary)'!$B:$G,4,0) -> Int | H12: =VLOOKUP($D12,'Tag(Glossary)'!$B:$G,5,0) -> 12 | I12: =VLOOKUP($D12,'Tag(Glossary)'!$B:$H,6,0)&IF(ISBLANK(VLOOKUP($D12,'Tag(Glossary)'!$B:$H,7,0)),"",CHAR(10))&VLOOKUP($D12,'Tag(Glossary)'!$B:$H,7,0) -> Total volume traded
B13: =INDEX('Interface List'!$D$7:$D$45,MATCH($C13,'Interface List'!$E$7:$E$45,0)) -> IFMDFIX0009 | C13: Price | D13: 381 | E13: =VLOOKUP($D13,'Tag(Glossary)'!$B:$G,2,0) -> GrossTradeAmt | F13: N | G13: =VLOOKUP($D13,'Tag(Glossary)'!$B:$G,4,0) -> Float | H13: =VLOOKUP($D13,'Tag(Glossary)'!$B:$G,5,0) -> 23(18.4) | I13: =VLOOKUP($D13,'Tag(Glossary)'!$B:$H,6,0)&IF(ISBLANK(VLOOKUP($D13,'Tag(Glossary)'!$B:$H,7,0)),"",CHAR(10))&VLOOKUP($D13,'Tag(Glossary)'!$B:$H,7,0) -> Gross amount traded
B14: =INDEX('Interface List'!$D$7:$D$45,MATCH($C14,'Interface List'!$E$7:$E$45,0)) -> IFMDFIX0009 | C14: Price | D14: 30521 | E14: =VLOOKUP($D14,'Tag(Glossary)'!$B:$G,2,0) -> SellTotOrderQty | F14: N | G14: =VLOOKUP($D14,'Tag(Glossary)'!$B:$G,4,0) -> Int | H14: =VLOOKUP($D14,'Tag(Glossary)'!$B:$G,5,0) -> 12 | I14: =VLOOKUP($D14,'Tag(Glossary)'!$B:$H,6,0)&IF(ISBLANK(VLOOKUP($D14,'Tag(Glossary)'!$B:$H,7,0)),"",CHAR(10))&VLOOKUP($D14,'Tag(Glossary)'!$B:$H,7,0) -> Total quantity of remaining orders in ask side
B15: =INDEX('Interface List'!$D$7:$D$45,MATCH($C15,'Interface List'!$E$7:$E$45,0)) -> IFMDFIX0009 | C15: Price | D15: 30522 | E15: =VLOOKUP($D15,'Tag(Glossary)'!$B:$G,2,0) -> BuyTotOrderQty | F15: N | G15: =VLOOKUP($D15,'Tag(Glossary)'!$B:$G,4,0) -> Int | H15: =VLOOKUP($D15,'Tag(Glossary)'!$B:$G,5,0) -> 12 | I15: =VLOOKUP($D15,'Tag(Glossary)'!$B:$H,6,0)&IF(ISBLANK(VLOOKUP($D15,'Tag(Glossary)'!$B:$H,7,0)),"",CHAR(10))&VLOOKUP($D15,'Tag(Glossary)'!$B:$H,7,0) -> Total quantity of remaining orders in bid side
B16: =INDEX('Interface List'!$D$7:$D$45,MATCH($C16,'Interface List'!$E$7:$E$45,0)) -> IFMDFIX0009 | C16: Price | D16: 30523 | E16: =VLOOKUP($D16,'Tag(Glossary)'!$B:$G,2,0) -> SellValidOrderCnt | F16: N | G16: =VLOOKUP($D16,'Tag(Glossary)'!$B:$G,4,0) -> Int | H16: =VLOOKUP($D16,'Tag(Glossary)'!$B:$G,5,0) -> 11 | I16: =VLOOKUP($D16,'Tag(Glossary)'!$B:$H,6,0)&IF(ISBLANK(VLOOKUP($D16,'Tag(Glossary)'!$B:$H,7,0)),"",CHAR(10))&VLOOKUP($D16,'Tag(Glossary)'!$B:$H,7,0) -> Valid count of orders in ask side
B17: =INDEX('Interface List'!$D$7:$D$45,MATCH($C17,'Interface List'!$E$7:$E$45,0)) -> IFMDFIX0009 | C17: Price | D17: 30524 | E17: =VLOOKUP($D17,'Tag(Glossary)'!$B:$G,2,0) -> BuyValidOrderCnt | F17: N | G17: =VLOOKUP($D17,'Tag(Glossary)'!$B:$G,4,0) -> Int | H17: =VLOOKUP($D17,'Tag(Glossary)'!$B:$G,5,0) -> 11 | I17: =VLOOKUP($D17,'Tag(Glossary)'!$B:$H,6,0)&IF(ISBLANK(VLOOKUP($D17,'Tag(Glossary)'!$B:$H,7,0)),"",CHAR(10))&VLOOKUP($D17,'Tag(Glossary)'!$B:$H,7,0) -> Valid count of orders in bid side
B18: =INDEX('Interface List'!$D$7:$D$45,MATCH($C18,'Interface List'!$E$7:$E$45,0)) -> IFMDFIX0009 | C18: Price | D18: 268 | E18: =VLOOKUP($D18,'Tag(Glossary)'!$B:$G,2,0) -> NoMDEntries | F18: Y | G18: =VLOOKUP($D18,'Tag(Glossary)'!$B:$G,4,0) -> Int | H18: =VLOOKUP($D18,'Tag(Glossary)'!$B:$G,5,0) -> 9 | I18: =VLOOKUP($D18,'Tag(Glossary)'!$B:$H,6,0)&IF(ISBLANK(VLOOKUP($D18,'Tag(Glossary)'!$B:$H,7,0)),"",CHAR(10))&VLOOKUP($D18,'Tag(Glossary)'!$B:$H,7,0) -> Number(Depth) of market data entries repeated as following
B19: Repeating Group
B20: =INDEX('Interface List'!$D$7:$D$45,MATCH($C20,'Interface List'!$E$7:$E$45,0)) -> IFMDFIX0009 | C20: Price | D20: 83 | E20: =VLOOKUP($D20,'Tag(Glossary)'!$B:$G,2,0) -> RptSeq | F20: Y | G20: =VLOOKUP($D20,'Tag(Glossary)'!$B:$G,4,0) -> Int | H20: =VLOOKUP($D20,'Tag(Glossary)'!$B:$G,5,0) -> 9 | I20: =VLOOKUP($D20,'Tag(Glossary)'!$B:$H,6,0)&IF(ISBLANK(VLOOKUP($D20,'Tag(Glossary)'!$B:$H,7,0)),"",CHAR(10))&VLOOKUP($D20,'Tag(Glossary)'!$B:$H,7,0) -> Data sequential number within repeated record
B21: =INDEX('Interface List'!$D$7:$D$45,MATCH($C21,'Interface List'!$E$7:$E$45,0)) -> IFMDFIX0009 | C21: Price | D21: 279 | E21: =VLOOKUP($D21,'Tag(Glossary)'!$B:$G,2,0) -> MDUpdateAction | F21: Y | G21: =VLOOKUP($D21,'Tag(Glossary)'!$B:$G,4,0) -> String | H21: =VLOOKUP($D21,'Tag(Glossary)'!$B:$G,5,0) -> 1 | I21: =VLOOKUP($D21,'Tag(Glossary)'!$B:$H,6,0)&IF(ISBLANK(VLOOKUP($D21,'Tag(Glossary)'!$B:$H,7,0)),"",CHAR(10))&VLOOKUP($D21,'Tag(Glossary)'!$B:$H,7,0) -> Type code of update action for an entry of market data 0 = New
B22: =INDEX('Interface List'!$D$7:$D$45,MATCH($C22,'Interface List'!$E$7:$E$45,0)) -> IFMDFIX0009 | C22: Price | D22: 269 | E22: =VLOOKUP($D22,'Tag(Glossary)'!$B:$G,2,0) -> MDEntryType | F22: Y | G22: =VLOOKUP($D22,'Tag(Glossary)'!$B:$G,4,0) -> String | H22: =VLOOKUP($D22,'Tag(Glossary)'!$B:$G,5,0) -> 1 | I22: =VLOOKUP($D22,'Tag(Glossary)'!$B:$H,6,0)&IF(ISBLANK(VLOOKUP($D22,'Tag(Glossary)'!$B:$H,7,0)),"",CHAR(10))&VLOOKUP($D22,'Tag(Glossary)'!$B:$H,7,0) -> Data classification for an entry of market data Possible values in message X (Price) . 0 = Bid 1 = Offer 2 = Trade 4 = Opening Price 7 = Trading Session High Price 8 = Trading Session Low Price Possible values in message W (Price Recovery) . 0 = Bid 1 = Offer
B23: =INDEX('Interface List'!$D$7:$D$45,MATCH($C23,'Interface List'!$E$7:$E$45,0)) -> IFMDFIX0009 | C23: Price | D23: 290 | E23: =VLOOKUP($D23,'Tag(Glossary)'!$B:$G,2,0) -> MDEntryPositionNo | F23: Y | G23: =VLOOKUP($D23,'Tag(Glossary)'!$B:$G,4,0) -> Int | H23: =VLOOKUP($D23,'Tag(Glossary)'!$B:$G,5,0) -> 2 | I23: =VLOOKUP($D23,'Tag(Glossary)'!$B:$H,6,0)&IF(ISBLANK(VLOOKUP($D23,'Tag(Glossary)'!$B:$H,7,0)),"",CHAR(10))&VLOOKUP($D23,'Tag(Glossary)'!$B:$H,7,0) -> Position no (or level) for an entry of market data
B24: =INDEX('Interface List'!$D$7:$D$45,MATCH($C24,'Interface List'!$E$7:$E$45,0)) -> IFMDFIX0009 | C24: Price | D24: 270 | E24: =VLOOKUP($D24,'Tag(Glossary)'!$B:$G,2,0) -> MDEntryPx | F24: Y | G24: =VLOOKUP($D24,'Tag(Glossary)'!$B:$G,4,0) -> Price | H24: =VLOOKUP($D24,'Tag(Glossary)'!$B:$G,5,0) -> 15(9.4) | I24: =VLOOKUP($D24,'Tag(Glossary)'!$B:$H,6,0)&IF(ISBLANK(VLOOKUP($D24,'Tag(Glossary)'!$B:$H,7,0)),"",CHAR(10))&VLOOKUP($D24,'Tag(Glossary)'!$B:$H,7,0) -> Price for an entry of market data
B25: =INDEX('Interface List'!$D$7:$D$45,MATCH($C25,'Interface List'!$E$7:$E$45,0)) -> IFMDFIX0009 | C25: Price | D25: 271 | E25: =VLOOKUP($D25,'Tag(Glossary)'!$B:$G,2,0) -> MDEntrySize | F25: Y | G25: =VLOOKUP($D25,'Tag(Glossary)'!$B:$G,4,0) -> Int | H25: =VLOOKUP($D25,'Tag(Glossary)'!$B:$G,5,0) -> 12 | I25: =VLOOKUP($D25,'Tag(Glossary)'!$B:$H,6,0)&IF(ISBLANK(VLOOKUP($D25,'Tag(Glossary)'!$B:$H,7,0)),"",CHAR(10))&VLOOKUP($D25,'Tag(Glossary)'!$B:$H,7,0) -> Size (or quantity) for an entry of market data
B26: =INDEX('Interface List'!$D$7:$D$45,MATCH($C26,'Interface List'!$E$7:$E$45,0)) -> IFMDFIX0009 | C26: Price | D26: 346 | E26: =VLOOKUP($D26,'Tag(Glossary)'!$B:$G,2,0) -> NumberOfOrders | F26: N | G26: =VLOOKUP($D26,'Tag(Glossary)'!$B:$G,4,0) -> Int | H26: =VLOOKUP($D26,'Tag(Glossary)'!$B:$G,5,0) -> 11 | I26: =VLOOKUP($D26,'Tag(Glossary)'!$B:$H,6,0)&IF(ISBLANK(VLOOKUP($D26,'Tag(Glossary)'!$B:$H,7,0)),"",CHAR(10))&VLOOKUP($D26,'Tag(Glossary)'!$B:$H,7,0) -> Number of orders
B27: =INDEX('Interface List'!$D$7:$D$45,MATCH($C27,'Interface List'!$E$7:$E$45,0)) -> IFMDFIX0009 | C27: Price | D27: 30270 | E27: =VLOOKUP($D27,'Tag(Glossary)'!$B:$G,2,0) -> MDEntryYield | F27: N | G27: =VLOOKUP($D27,'Tag(Glossary)'!$B:$G,4,0) -> Float | H27: =VLOOKUP($D27,'Tag(Glossary)'!$B:$G,5,0) -> 13(5.6) | I27: =VLOOKUP($D27,'Tag(Glossary)'!$B:$H,6,0)&IF(ISBLANK(VLOOKUP($D27,'Tag(Glossary)'!$B:$H,7,0)),"",CHAR(10))&VLOOKUP($D27,'Tag(Glossary)'!$B:$H,7,0) -> Yield of the entry. Bond market only.
B28: =INDEX('Interface List'!$D$7:$D$45,MATCH($C28,'Interface List'!$E$7:$E$45,0)) -> IFMDFIX0009 | C28: Price | D28: 30271 | E28: =VLOOKUP($D28,'Tag(Glossary)'!$B:$G,2,0) -> MDEntryMMSize | F28: N | G28: =VLOOKUP($D28,'Tag(Glossary)'!$B:$G,4,0) -> Int | H28: =VLOOKUP($D28,'Tag(Glossary)'!$B:$G,5,0) -> 12 | I28: =VLOOKUP($D28,'Tag(Glossary)'!$B:$H,6,0)&IF(ISBLANK(VLOOKUP($D28,'Tag(Glossary)'!$B:$H,7,0)),"",CHAR(10))&VLOOKUP($D28,'Tag(Glossary)'!$B:$H,7,0) -> Size of the entry provided from market makers
B29: =INDEX('Interface List'!$D$7:$D$45,MATCH($C29,'Interface List'!$E$7:$E$45,0)) -> IFMDFIX0009 | C29: Price | E29: Standard Trailer | F29: Y

Sheet PriceRecovery
B2: Price Recovery
B4: Interface ID | C4: Interface Name | D4: Tag | E4: Field Name | F4: Req'd | G4: Format | H4: Length | I4: Comments
B5: =INDEX('Interface List'!$D$7:$D$45,MATCH($C5,'Interface List'!$E$7:$E$45,0)) -> IFMDFIX0010 | C5: Price Recovery | E5: Standard Header | F5: Y | I5: MsgType = W
B6: =INDEX('Interface List'!$D$7:$D$45,MATCH($C6,'Interface List'!$E$7:$E$45,0)) -> IFMDFIX0010 | C6: Price Recovery | D6: 30001 | E6: =VLOOKUP($D6,'Tag(Glossary)'!$B:$G,2,0) -> MarketID | F6: Y | G6: =VLOOKUP($D6,'Tag(Glossary)'!$B:$G,4,0) -> String | H6: =VLOOKUP($D6,'Tag(Glossary)'!$B:$G,5,0) -> 3 | I6: =VLOOKUP($D6,'Tag(Glossary)'!$B:$H,6,0)&IF(ISBLANK(VLOOKUP($D6,'Tag(Glossary)'!$B:$H,7,0)),"",CHAR(10))&VLOOKUP($D6,'Tag(Glossary)'!$B:$H,7,0) -> ID for identifying the market <Hochiminh Exchange> - STO: HoSE Stock Market - BDO: HoSE Bond Market - RPO: HoSE Repo Market <Hanoi Exchange> - STX: HNX Listed Stock Market - BDX: HNX Government Bond Market - DVX: HNX Derivative Market - UPX: HNX UpCoM Stock Market - HCX: HNX Corporate Bond Market
B7: =INDEX('Interface List'!$D$7:$D$45,MATCH($C7,'Interface List'!$E$7:$E$45,0)) -> IFMDFIX0010 | C7: Price Recovery | D7: 20004 | E7: =VLOOKUP($D7,'Tag(Glossary)'!$B:$G,2,0) -> BoardID | F7: Y | G7: =VLOOKUP($D7,'Tag(Glossary)'!$B:$G,4,0) -> String | H7: =VLOOKUP($D7,'Tag(Glossary)'!$B:$G,5,0) -> 2 | I7: =VLOOKUP($D7,'Tag(Glossary)'!$B:$H,6,0)&IF(ISBLANK(VLOOKUP($D7,'Tag(Glossary)'!$B:$H,7,0)),"",CHAR(10))&VLOOKUP($D7,'Tag(Glossary)'!$B:$H,7,0) -> Unique identifier to a Board where a given instrument is traded G1 : Main G2 : Pre open G3 : Post closing G4 : Odd lot G7 : Buy-in G8 : Sell-out T1 : Negotiation (regular) T4 : Negotiation (regular for Odd lot) T2 : Negotiation (pre) T3 : Negotiation (post) T6 : Negotiation (post for Odd lot) R1 : Negotiation (Repo) AL : All Boards
B8: =INDEX('Interface List'!$D$7:$D$45,MATCH($C8,'Interface List'!$E$7:$E$45,0)) -> IFMDFIX0010 | C8: Price Recovery | D8: 336 | E8: =VLOOKUP($D8,'Tag(Glossary)'!$B:$G,2,0) -> TradingSessionID | F8: Y | G8: =VLOOKUP($D8,'Tag(Glossary)'!$B:$G,4,0) -> String | H8: =VLOOKUP($D8,'Tag(Glossary)'!$B:$G,5,0) -> 2 | I8: =VLOOKUP($D8,'Tag(Glossary)'!$B:$H,6,0)&IF(ISBLANK(VLOOKUP($D8,'Tag(Glossary)'!$B:$H,7,0)),"",CHAR(10))&VLOOKUP($D8,'Tag(Glossary)'!$B:$H,7,0) -> Trading Session 01 = GT Order Load 10 = Opening Call Auction 11 = Opening Call Auction Extension 20 = Call Auction after Halt 21 = Call Auction after Halt Extension 30 = Closing Call Auction 40 = Continuous Auction 50 = VI Call Auction 51 = VI Call Auction Extension 60 = Order Accept Only 80 = Periodic Call Auction 90 = Trading Halt 99 = Board Closing
B9: =INDEX('Interface List'!$D$7:$D$45,MATCH($C9,'Interface List'!$E$7:$E$45,0)) -> IFMDFIX0010 | C9: Price Recovery | D9: 55 | E9: =VLOOKUP($D9,'Tag(Glossary)'!$B:$G,2,0) -> Symbol | F9: Y | G9: =VLOOKUP($D9,'Tag(Glossary)'!$B:$G,4,0) -> String | H9: =VLOOKUP($D9,'Tag(Glossary)'!$B:$G,5,0) -> 12 | I9: =VLOOKUP($D9,'Tag(Glossary)'!$B:$H,6,0)&IF(ISBLANK(VLOOKUP($D9,'Tag(Glossary)'!$B:$H,7,0)),"",CHAR(10))&VLOOKUP($D9,'Tag(Glossary)'!$B:$H,7,0) -> The unique code of an issue (a.k.a. instrument or symbol). Generally it is ISIN code but in case of Repo market it is defined as the exchange staffs want
B10: =INDEX('Interface List'!$D$7:$D$45,MATCH($C10,'Interface List'!$E$7:$E$45,0)) -> IFMDFIX0010 | C10: Price Recovery | D10: 30561 | E10: =VLOOKUP($D10,'Tag(Glossary)'!$B:$G,2,0) -> OpnPx | F10: Y | G10: =VLOOKUP($D10,'Tag(Glossary)'!$B:$G,4,0) -> Price | H10: =VLOOKUP($D10,'Tag(Glossary)'!$B:$G,5,0) -> 15(9.4) | I10: =VLOOKUP($D10,'Tag(Glossary)'!$B:$H,6,0)&IF(ISBLANK(VLOOKUP($D10,'Tag(Glossary)'!$B:$H,7,0)),"",CHAR(10))&VLOOKUP($D10,'Tag(Glossary)'!$B:$H,7,0) -> The first price during that day
B11: =INDEX('Interface List'!$D$7:$D$45,MATCH($C11,'Interface List'!$E$7:$E$45,0)) -> IFMDFIX0010 | C11: Price Recovery | D11: 30562 | E11: =VLOOKUP($D11,'Tag(Glossary)'!$B:$G,2,0) -> TrdSessnHighPx | F11: Y | G11: =VLOOKUP($D11,'Tag(Glossary)'!$B:$G,4,0) -> Price | H11: =VLOOKUP($D11,'Tag(Glossary)'!$B:$G,5,0) -> 15(9.4) | I11: =VLOOKUP($D11,'Tag(Glossary)'!$B:$H,6,0)&IF(ISBLANK(VLOOKUP($D11,'Tag(Glossary)'!$B:$H,7,0)),"",CHAR(10))&VLOOKUP($D11,'Tag(Glossary)'!$B:$H,7,0) -> Highest price during that day
B12: =INDEX('Interface List'!$D$7:$D$45,MATCH($C12,'Interface List'!$E$7:$E$45,0)) -> IFMDFIX0010 | C12: Price Recovery | D12: 30563 | E12: =VLOOKUP($D12,'Tag(Glossary)'!$B:$G,2,0) -> TrdSessnLowPx | F12: Y | G12: =VLOOKUP($D12,'Tag(Glossary)'!$B:$G,4,0) -> Price | H12: =VLOOKUP($D12,'Tag(Glossary)'!$B:$G,5,0) -> 15(9.4) | I12: =VLOOKUP($D12,'Tag(Glossary)'!$B:$H,6,0)&IF(ISBLANK(VLOOKUP($D12,'Tag(Glossary)'!$B:$H,7,0)),"",CHAR(10))&VLOOKUP($D12,'Tag(Glossary)'!$B:$H,7,0) -> Lowest price during that day
B13: =INDEX('Interface List'!$D$7:$D$45,MATCH($C13,'Interface List'!$E$7:$E$45,0)) -> IFMDFIX0010 | C13: Price Recovery | D13: 20026 | E13: =VLOOKUP($D13,'Tag(Glossary)'!$B:$G,2,0) -> SymbolCloseInfoPx | F13: Y | G13: =VLOOKUP($D13,'Tag(Glossary)'!$B:$G,4,0) -> Price | H13: =VLOOKUP($D13,'Tag(Glossary)'!$B:$G,5,0) -> 15(9.4) | I13: =VLOOKUP($D13,'Tag(Glossary)'!$B:$H,6,0)&IF(ISBLANK(VLOOKUP($D13,'Tag(Glossary)'!$B:$H,7,0)),"",CHAR(10))&VLOOKUP($D13,'Tag(Glossary)'!$B:$H,7,0) -> The last execution price of that day. If there is no execution it is replaced with the reference price, and if no reference price is given then it will be 0 (zero)
B14: =INDEX('Interface List'!$D$7:$D$45,MATCH($C14,'Interface List'!$E$7:$E$45,0)) -> IFMDFIX0010 | C14: Price Recovery | D14: 387 | E14: =VLOOKUP($D14,'Tag(Glossary)'!$B:$G,2,0) -> TotalVolumeTraded | F14: Y | G14: =VLOOKUP($D14,'Tag(Glossary)'!$B:$G,4,0) -> Int | H14: =VLOOKUP($D14,'Tag(Glossary)'!$B:$G,5,0) -> 12 | I14: =VLOOKUP($D14,'Tag(Glossary)'!$B:$H,6,0)&IF(ISBLANK(VLOOKUP($D14,'Tag(Glossary)'!$B:$H,7,0)),"",CHAR(10))&VLOOKUP($D14,'Tag(Glossary)'!$B:$H,7,0) -> Total volume traded
B15: =INDEX('Interface List'!$D$7:$D$45,MATCH($C15,'Interface List'!$E$7:$E$45,0)) -> IFMDFIX0010 | C15: Price Recovery | D15: 381 | E15: =VLOOKUP($D15,'Tag(Glossary)'!$B:$G,2,0) -> GrossTradeAmt | F15: Y | G15: =VLOOKUP($D15,'Tag(Glossary)'!$B:$G,4,0) -> Float | H15: =VLOOKUP($D15,'Tag(Glossary)'!$B:$G,5,0) -> 23(18.4) | I15: =VLOOKUP($D15,'Tag(Glossary)'!$B:$H,6,0)&IF(ISBLANK(VLOOKUP($D15,'Tag(Glossary)'!$B:$H,7,0)),"",CHAR(10))&VLOOKUP($D15,'Tag(Glossary)'!$B:$H,7,0) -> Gross amount traded
B16: =INDEX('Interface List'!$D$7:$D$45,MATCH($C16,'Interface List'!$E$7:$E$45,0)) -> IFMDFIX0010 | C16: Price Recovery | D16: 30521 | E16: =VLOOKUP($D16,'Tag(Glossary)'!$B:$G,2,0) -> SellTotOrderQty | F16: N | G16: =VLOOKUP($D16,'Tag(Glossary)'!$B:$G,4,0) -> Int | H16: =VLOOKUP($D16,'Tag(Glossary)'!$B:$G,5,0) -> 12 | I16: =VLOOKUP($D16,'Tag(Glossary)'!$B:$H,6,0)&IF(ISBLANK(VLOOKUP($D16,'Tag(Glossary)'!$B:$H,7,0)),"",CHAR(10))&VLOOKUP($D16,'Tag(Glossary)'!$B:$H,7,0) -> Total quantity of remaining orders in ask side
B17: =INDEX('Interface List'!$D$7:$D$45,MATCH($C17,'Interface List'!$E$7:$E$45,0)) -> IFMDFIX0010 | C17: Price Recovery | D17: 30522 | E17: =VLOOKUP($D17,'Tag(Glossary)'!$B:$G,2,0) -> BuyTotOrderQty | F17: N | G17: =VLOOKUP($D17,'Tag(Glossary)'!$B:$G,4,0) -> Int | H17: =VLOOKUP($D17,'Tag(Glossary)'!$B:$G,5,0) -> 12 | I17: =VLOOKUP($D17,'Tag(Glossary)'!$B:$H,6,0)&IF(ISBLANK(VLOOKUP($D17,'Tag(Glossary)'!$B:$H,7,0)),"",CHAR(10))&VLOOKUP($D17,'Tag(Glossary)'!$B:$H,7,0) -> Total quantity of remaining orders in bid side
... B20: =INDEX('Interface List'!$D$7:$D$45,MATCH($C20,'Interface List'!$E$7:$E$45,0)) -> IFMDFIX0010 | C20: Price Recovery | D20: 268 | E20: =VLOOKUP($D20,'Tag(Glossary)'!$B:$G,2,0) -> NoMDEntries | F20: Y | G20: =VLOOKUP($D20,'Tag(Glossary)'!$B:$G,4,0) -> Int | H20: =VLOOKUP($D20,'Tag(Glossary)'!$B:$G,5,0) -> 9 | I20: =VLOOKUP($D20,'Tag(Glossary)'!$B:$H,6,0)&IF(ISBLANK(VLOOKUP($D20,'Tag(Glossary)'!$B:$H,7,0)),"",CHAR(10))&VLOOKUP($D20,'Tag(Glossary)'!$B:$H,7,0) -> Number(Depth) of market data entries repeated as following
B21: Repeating Group
B22: =INDEX('Interface List'!$D$7:$D$45,MATCH($C22,'Interface List'!$E$7:$E$45,0)) -> IFMDFIX0010 | C22: Price Recovery | D22: 83 | E22: =VLOOKUP($D22,'Tag(Glossary)'!$B:$G,2,0) -> RptSeq | F22: Y | G22: =VLOOKUP($D22,'Tag(Glossary)'!$B:$G,4,0) -> Int | H22: =VLOOKUP($D22,'Tag(Glossary)'!$B:$G,5,0) -> 9 | I22: =VLOOKUP($D22,'Tag(Glossary)'!$B:$H,6,0)&IF(ISBLANK(VLOOKUP($D22,'Tag(Glossary)'!$B:$H,7,0)),"",CHAR(10))&VLOOKUP($D22,'Tag(Glossary)'!$B:$H,7,0) -> Data sequential number within repeated record
B23: =INDEX('Interface List'!$D$7:$D$45,MATCH($C23,'Interface List'!$E$7:$E$45,0)) -> IFMDFIX0010 | C23: Price Recovery | D23: 279 | E23: =VLOOKUP($D23,'Tag(Glossary)'!$B:$G,2,0) -> MDUpdateAction | F23: Y | G23: =VLOOKUP($D23,'Tag(Glossary)'!$B:$G,4,0) -> String | H23: =VLOOKUP($D23,'Tag(Glossary)'!$B:$G,5,0) -> 1 | I23: =VLOOKUP($D23,'Tag(Glossary)'!$B:$H,6,0)&IF(ISBLANK(VLOOKUP($D23,'Tag(Glossary)'!$B:$H,7,0)),"",CHAR(10))&VLOOKUP($D23,'Tag(Glossary)'!$B:$H,7,0) -> Type code of update action for an entry of market data 0 = New
B24: =INDEX('Interface List'!$D$7:$D$45,MATCH($C24,'Interface List'!$E$7:$E$45,0)) -> IFMDFIX0010 | C24: Price Recovery | D24: 269 | E24: =VLOOKUP($D24,'Tag(Glossary)'!$B:$G,2,0) -> MDEntryType | F24: Y | G24: =VLOOKUP($D24,'Tag(Glossary)'!$B:$G,4,0) -> String | H24: =VLOOKUP($D24,'Tag(Glossary)'!$B:$G,5,0) -> 1 | I24: =VLOOKUP($D24,'Tag(Glossary)'!$B:$H,6,0)&IF(ISBLANK(VLOOKUP($D24,'Tag(Glossary)'!$B:$H,7,0)),"",CHAR(10))&VLOOKUP($D24,'Tag(Glossary)'!$B:$H,7,0) -> Data classification for an entry of market data Possible values in message X (Price) . 0 = Bid 1 = Offer 2 = Trade 4 = Opening Price 7 = Trading Session High Price 8 = Trading Session Low Price Possible values in message W (Price Recovery) . 0 = Bid 1 = Offer
B25: =INDEX('Interface List'!$D$7:$D$45,MATCH($C25,'Interface List'!$E$7:$E$45,0)) -> IFMDFIX0010 | C25: Price Recovery | D25: 290 | E25: =VLOOKUP($D25,'Tag(Glossary)'!$B:$G,2,0) -> MDEntryPositionNo | F25: Y | G25: =VLOOKUP($D25,'Tag(Glossary)'!$B:$G,4,0) -> Int | H25: =VLOOKUP($D25,'Tag(Glossary)'!$B:$G,5,0) -> 2 | I25: =VLOOKUP($D25,'Tag(Glossary)'!$B:$H,6,0)&IF(ISBLANK(VLOOKUP($D25,'Tag(Glossary)'!$B:$H,7,0)),"",CHAR(10))&VLOOKUP($D25,'Tag(Glossary)'!$B:$H,7,0) -> Position no (or level) for an entry of market data
B26: =INDEX('Interface List'!$D$7:$D$45,MATCH($C26,'Interface List'!$E$7:$E$45,0)) -> IFMDFIX0010 | C26: Price Recovery | D26: 270 | E26: =VLOOKUP($D26,'Tag(Glossary)'!$B:$G,2,0) -> MDEntryPx | F26: Y | G26: =VLOOKUP($D26,'Tag(Glossary)'!$B:$G,4,0) -> Price | H26: =VLOOKUP($D26,'Tag(Glossary)'!$B:$G,5,0) -> 15(9.4) | I26: =VLOOKUP($D26,'Tag(Glossary)'!$B:$H,6,0)&IF(ISBLANK(VLOOKUP($D26,'Tag(Glossary)'!$B:$H,7,0)),"",CHAR(10))&VLOOKUP($D26,'Tag(Glossary)'!$B:$H,7,0) -> Price for an entry of market data
B27: =INDEX('Interface List'!$D$7:$D$45,MATCH($C27,'Interface List'!$E$7:$E$45,0)) -> IFMDFIX0010 | C27: Price Recovery | D27: 271 | E27: =VLOOKUP($D27,'Tag(Glossary)'!$B:$G,2,0) -> MDEntrySize | F27: Y | G27: =VLOOKUP($D27,'Tag(Glossary)'!$B:$G,4,0) -> Int | H27: =VLOOKUP($D27,'Tag(Glossary)'!$B:$G,5,0) -> 12 | I27: =VLOOKUP($D27,'Tag(Glossary)'!$B:$H,6,0)&IF(ISBLANK(VLOOKUP($D27,'Tag(Glossary)'!$B:$H,7,0)),"",CHAR(10))&VLOOKUP($D27,'Tag(Glossary)'!$B:$H,7,0) -> Size (or quantity) for an entry of market data
B28: =INDEX('Interface List'!$D$7:$D$45,MATCH($C28,'Interface List'!$E$7:$E$45,0)) -> IFMDFIX0010 | C28: Price Recovery | D28: 346 | E28: =VLOOKUP($D28,'Tag(Glossary)'!$B:$G,2,0) -> NumberOfOrders | F28: N | G28: =VLOOKUP($D28,'Tag(Glossary)'!$B:$G,4,0) -> Int | H28: =VLOOKUP($D28,'Tag(Glossary)'!$B:$G,5,0) -> 11 | I28: =VLOOKUP($D28,'Tag(Glossary)'!$B:$H,6,0)&IF(ISBLANK(VLOOKUP($D28,'Tag(Glossary)'!$B:$H,7,0)),"",CHAR(10))&VLOOKUP($D28,'Tag(Glossary)'!$B:$H,7,0) -> Number of orders
B29: =INDEX('Interface List'!$D$7:$D$45,MATCH($C29,'Interface List'!$E$7:$E$45,0)) -> IFMDFIX0010 | C29: Price Recovery | D29: 30271 | E29: =VLOOKUP($D29,'Tag(Glossary)'!$B:$G,2,0) -> MDEntryMMSize | F29: Y | G29: =VLOOKUP($D29,'Tag(Glossary)'!$B:$G,4,0) -> Int | H29: =VLOOKUP($D29,'Tag(Glossary)'!$B:$G,5,0) -> 12 | I29: =VLOOKUP($D29,'Tag(Glossary)'!$B:$H,6,0)&IF(ISBLANK(VLOOKUP($D29,'Tag(Glossary)'!$B:$H,7,0)),"",CHAR(10))&VLOOKUP($D29,'Tag(Glossary)'!$B:$H,7,0) -> Size of the entry provided from market makers
B30: =INDEX('Interface List'!$D$7:$D$45,MATCH($C30,'Interface List'!$E$7:$E$45,0)) -> IFMDFIX0010 | C30: Price Recovery | E30: Standard Trailer | F30: Y

Sheet PriceRecovery(Bond)
B2: Price Recovery(Bond)
B4: Interface ID | C4: Interface Name | D4: Tag | E4: Field Name | F4: Req'd | G4: Format | H4: Length | I4: Comments
B5: =INDEX('Interface List'!$D$7:$D$45,MATCH($C5,'Interface List'!$E$7:$E$45,0)) -> IFMDFIX0011 | C5: Price Recovery(Bond) | E5: Standard Header | F5: Y | I5: MsgType = W
B6: =INDEX('Interface List'!$D$7:$D$45,MATCH($C6,'Interface List'!$E$7:$E$45,0)) -> IFMDFIX0011 | C6: Price Recovery(Bond) | D6: 30001 | E6: =VLOOKUP($D6,'Tag(Glossary)'!$B:$G,2,0) -> MarketID | F6: Y | G6: =VLOOKUP($D6,'Tag(Glossary)'!$B:$G,4,0) -> String | H6: =VLOOKUP($D6,'Tag(Glossary)'!$B:$G,5,0) -> 3 | I6: =VLOOKUP($D6,'Tag(Glossary)'!$B:$H,6,0)&IF(ISBLANK(VLOOKUP($D6,'Tag(Glossary)'!$B:$H,7,0)),"",CHAR(10))&VLOOKUP($D6,'Tag(Glossary)'!$B:$H,7,0) -> ID for identifying the market <Hochiminh Exchange> - STO: HoSE Stock Market - BDO: HoSE Bond Market - RPO: HoSE Repo Market <Hanoi Exchange> - STX: HNX Listed Stock Market - BDX: HNX Government Bond Market - DVX: HNX Derivative Market - UPX: HNX UpCoM Stock Market - HCX: HNX Corporate Bond Market
B7: =INDEX('Interface List'!$D$7:$D$45,MATCH($C7,'Interface List'!$E$7:$E$45,0)) -> IFMDFIX0011 | C7: Price Recovery(Bond) | D7: 20004 | E7: =VLOOKUP($D7,'Tag(Glossary)'!$B:$G,2,0) -> BoardID | F7: Y | G7: =VLOOKUP($D7,'Tag(Glossary)'!$B:$G,4,0) -> String | H7: =VLOOKUP($D7,'Tag(Glossary)'!$B:$G,5,0) -> 2 | I7: =VLOOKUP($D7,'Tag(Glossary)'!$B:$H,6,0)&IF(ISBLANK(VLOOKUP($D7,'Tag(Glossary)'!$B:$H,7,0)),"",CHAR(10))&VLOOKUP($D7,'Tag(Glossary)'!$B:$H,7,0) -> Unique identifier to a Board where a given instrument is traded G1 : Main G2 : Pre open G3 : Post closing G4 : Odd lot G7 : Buy-in G8 : Sell-out T1 : Negotiation (regular) T4 : Negotiation (regular for Odd lot) T2 : Negotiation (pre) T3 : Negotiation (post) T6 : Negotiation (post for Odd lot) R1 : Negotiation (Repo) AL : All Boards
B8: =INDEX('Interface List'!$D$7:$D$45,MATCH($C8,'Interface List'!$E$7:$E$45,0)) -> IFMDFIX0011 | C8: Price Recovery(Bond) | D8: 336 | E8: =VLOOKUP($D8,'Tag(Glossary)'!$B:$G,2,0) -> TradingSessionID | F8: Y | G8: =VLOOKUP($D8,'Tag(Glossary)'!$B:$G,4,0) -> String | H8: =VLOOKUP($D8,'Tag(Glossary)'!$B:$G,5,0) -> 2 | I8: =VLOOKUP($D8,'Tag(Glossary)'!$B:$H,6,0)&IF(ISBLANK(VLOOKUP($D8,'Tag(Glossary)'!$B:$H,7,0)),"",CHAR(10))&VLOOKUP($D8,'Tag(Glossary)'!$B:$H,7,0) -> Trading Session 01 = GT Order Load 10 = Opening Call Auction 11 = Opening Call Auction Extension 20 = Call Auction after Halt 21 = Call Auction after Halt Extension 30 = Closing Call Auction 40 = Continuous Auction 50 = VI Call Auction 51 = VI Call Auction Extension 60 = Order Accept Only 80 = Periodic Call Auction 90 = Trading Halt 99 = Board Closing
B9: =INDEX('Interface List'!$D$7:$D$45,MATCH($C9,'Interface List'!$E$7:$E$45,0)) -> IFMDFIX0011 | C9: Price Recovery(Bond) | D9: 55 | E9: =VLOOKUP($D9,'Tag(Glossary)'!$B:$G,2,0) -> Symbol | F9: Y | G9: =VLOOKUP($D9,'Tag(Glossary)'!$B:$G,4,0) -> String | H9: =VLOOKUP($D9,'Tag(Glossary)'!$B:$G,5,0) -> 12 | I9: =VLOOKUP($D9,'Tag(Glossary)'!$B:$H,6,0)&IF(ISBLANK(VLOOKUP($D9,'Tag(Glossary)'!$B:$H,7,0)),"",CHAR(10))&VLOOKUP($D9,'Tag(Glossary)'!$B:$H,7,0) -> The unique code of an issue (a.k.a. instrument or symbol). Generally it is ISIN code but in case of Repo market it is defined as the exchange staffs want
B10: =INDEX('Interface List'!$D$7:$D$45,MATCH($C10,'Interface List'!$E$7:$E$45,0)) -> IFMDFIX0011 | C10: Price Recovery(Bond) | D10: 30561 | E10: =VLOOKUP($D10,'Tag(Glossary)'!$B:$G,2,0) -> OpnPx | F10: Y | G10: =VLOOKUP($D10,'Tag(Glossary)'!$B:$G,4,0) -> Price | H10: =VLOOKUP($D10,'Tag(Glossary)'!$B:$G,5,0) -> 15(9.4) | I10: =VLOOKUP($D10,'Tag(Glossary)'!$B:$H,6,0)&IF(ISBLANK(VLOOKUP($D10,'Tag(Glossary)'!$B:$H,7,0)),"",CHAR(10))&VLOOKUP($D10,'Tag(Glossary)'!$B:$H,7,0) -> The first price during that day
B11: =INDEX('Interface List'!$D$7:$D$45,MATCH($C11,'Interface List'!$E$7:$E$45,0)) -> IFMDFIX0011 | C11: Price Recovery(Bond) | D11: 30562 | E11: =VLOOKUP($D11,'Tag(Glossary)'!$B:$G,2,0) -> TrdSessnHighPx | F11: Y | G11: =VLOOKUP($D11,'Tag(Glossary)'!$B:$G,4,0) -> Price | H11: =VLOOKUP($D11,'Tag(Glossary)'!$B:$G,5,0) -> 15(9.4) | I11: =VLOOKUP($D11,'Tag(Glossary)'!$B:$H,6,0)&IF(ISBLANK(VLOOKUP($D11,'Tag(Glossary)'!$B:$H,7,0)),"",CHAR(10))&VLOOKUP($D11,'Tag(Glossary)'!$B:$H,7,0) -> Highest price during that day
B12: =INDEX('Interface List'!$D$7:$D$45,MATCH($C12,'Interface List'!$E$7:$E$45,0)) -> IFMDFIX0011 | C12: Price Recovery(Bond) | D12: 30563 | E12: =VLOOKUP($D12,'Tag(Glossary)'!$B:$G,2,0) -> TrdSessnLowPx | F12: Y | G12: =VLOOKUP($D12,'Tag(Glossary)'!$B:$G,4,0) -> Price | H12: =VLOOKUP($D12,'Tag(Glossary)'!$B:$G,5,0) -> 15(9.4) | I12: =VLOOKUP($D12,'Tag(Glossary)'!$B:$H,6,0)&IF(ISBLANK(VLOOKUP($D12,'Tag(Glossary)'!$B:$H,7,0)),"",CHAR(10))&VLOOKUP($D12,'Tag(Glossary)'!$B:$H,7,0) -> Lowest price during that day
B13: =INDEX('Interface List'!$D$7:$D$45,MATCH($C13,'Interface List'!$E$7:$E$45,0)) -> IFMDFIX0011 | C13: Price Recovery(Bond) | D13: 20026 | E13: =VLOOKUP($D13,'Tag(Glossary)'!$B:$G,2,0) -> SymbolCloseInfoPx | F13: Y | G13: =VLOOKUP($D13,'Tag(Glossary)'!$B:$G,4,0) -> Price | H13: =VLOOKUP($D13,'Tag(Glossary)'!$B:$G,5,0) -> 15(9.4) | I13: =VLOOKUP($D13,'Tag(Glossary)'!$B:$H,6,0)&IF(ISBLANK(VLOOKUP($D13,'Tag(Glossary)'!$B:$H,7,0)),"",CHAR(10))&VLOOKUP($D13,'Tag(Glossary)'!$B:$H,7,0) -> The last execution price of that day. If there is no execution it is replaced with the reference price, and if no reference price is given then it will be 0 (zero)
B14: =INDEX('Interface List'!$D$7:$D$45,MATCH($C14,'Interface List'!$E$7:$E$45,0)) -> IFMDFIX0011 | C14: Price Recovery(Bond) | D14: 30565 | E14: =VLOOKUP($D14,'Tag(Glossary)'!$B:$G,2,0) -> OpnPxYld | F14: Y | G14: =VLOOKUP($D14,'Tag(Glossary)'!$B:$G,4,0) -> Float | H14: =VLOOKUP($D14,'Tag(Glossary)'!$B:$G,5,0) -> 13(5.6) | I14: =VLOOKUP($D14,'Tag(Glossary)'!$B:$H,6,0)&IF(ISBLANK(VLOOKUP($D14,'Tag(Glossary)'!$B:$H,7,0)),"",CHAR(10))&VLOOKUP($D14,'Tag(Glossary)'!$B:$H,7,0) -> Yield rate for opening price
B15: =INDEX('Interface List'!$D$7:$D$45,MATCH($C15,'Interface List'!$E$7:$E$45,0)) -> IFMDFIX0011 | C15: Price Recovery(Bond) | D15: 30566 | E15: =VLOOKUP($D15,'Tag(Glossary)'!$B:$G,2,0) -> TrdSessnHighPxYld | F15: Y | G15: =VLOOKUP($D15,'Tag(Glossary)'!$B:$G,4,0) -> Float | H15: =VLOOKUP($D15,'Tag(Glossary)'!$B:$G,5,0) -> 13(5.6) | I15: =VLOOKUP($D15,'Tag(Glossary)'!$B:$H,6,0)&IF(ISBLANK(VLOOKUP($D15,'Tag(Glossary)'!$B:$H,7,0)),"",CHAR(10))&VLOOKUP($D15,'Tag(Glossary)'!$B:$H,7,0) -> Yield rate for high price
B16: =INDEX('Interface List'!$D$7:$D$45,MATCH($C16,'Interface List'!$E$7:$E$45,0)) -> IFMDFIX0011 | C16: Price Recovery(Bond) | D16: 30567 | E16: =VLOOKUP($D16,'Tag(Glossary)'!$B:$G,2,0) -> TrdSessnLowPxYld | F16: Y | G16: =VLOOKUP($D16,'Tag(Glossary)'!$B:$G,4,0) -> Float | H16: =VLOOKUP($D16,'Tag(Glossary)'!$B:$G,5,0) -> 13(5.6) | I16: =VLOOKUP($D16,'Tag(Glossary)'!$B:$H,6,0)&IF(ISBLANK(VLOOKUP($D16,'Tag(Glossary)'!$B:$H,7,0)),"",CHAR(10))&VLOOKUP($D16,'Tag(Glossary)'!$B:$H,7,0) -> Yield rate for low price
B17: =INDEX('Interface List'!$D$7:$D$45,MATCH($C17,'Interface List'!$E$7:$E$45,0)) -> IFMDFIX0011 | C17: Price Recovery(Bond) | D17: 30568 | E17: =VLOOKUP($D17,'Tag(Glossary)'!$B:$G,2,0) -> ClsPxYld | F17: Y | G17: =VLOOKUP($D17,'Tag(Glossary)'!$B:$G,4,0) -> Float | H17: =VLOOKUP($D17,'Tag(Glossary)'!$B:$G,5,0) -> 13(5.6) | I17: =VLOOKUP($D17,'Tag(Glossary)'!$B:$H,6,0)&IF(ISBLANK(VLOOKUP($D17,'Tag(Glossary)'!$B:$H,7,0)),"",CHAR(10))&VLOOKUP($D17,'Tag(Glossary)'!$B:$H,7,0) -> Final yield of a bond calculated using the closing price of that day
... B24: =INDEX('Interface List'!$D$7:$D$45,MATCH($C24,'Interface List'!$E$7:$E$45,0)) -> IFMDFIX0011 | C24: Price Recovery(Bond) | D24: 268 | E24: =VLOOKUP($D24,'Tag(Glossary)'!$B:$G,2,0) -> NoMDEntries | F24: Y | G24: =VLOOKUP($D24,'Tag(Glossary)'!$B:$G,4,0) -> Int | H24: =VLOOKUP($D24,'Tag(Glossary)'!$B:$G,5,0) -> 9 | I24: =VLOOKUP($D24,'Tag(Glossary)'!$B:$H,6,0)&IF(ISBLANK(VLOOKUP($D24,'Tag(Glossary)'!$B:$H,7,0)),"",CHAR(10))&VLOOKUP($D24,'Tag(Glossary)'!$B:$H,7,0) -> Number(Depth) of market data entries repeated as following
B25: Repeating Group
B26: =INDEX('Interface List'!$D$7:$D$45,MATCH($C26,'Interface List'!$E$7:$E$45,0)) -> IFMDFIX0011 | C26: Price Recovery(Bond) | D26: 83 | E26: =VLOOKUP($D26,'Tag(Glossary)'!$B:$G,2,0) -> RptSeq | F26: Y | G26: =VLOOKUP($D26,'Tag(Glossary)'!$B:$G,4,0) -> Int | H26: =VLOOKUP($D26,'Tag(Glossary)'!$B:$G,5,0) -> 9 | I26: =VLOOKUP($D26,'Tag(Glossary)'!$B:$H,6,0)&IF(ISBLANK(VLOOKUP($D26,'Tag(Glossary)'!$B:$H,7,0)),"",CHAR(10))&VLOOKUP($D26,'Tag(Glossary)'!$B:$H,7,0) -> Data sequential number within repeated record
B27: =INDEX('Interface List'!$D$7:$D$45,MATCH($C27,'Interface List'!$E$7:$E$45,0)) -> IFMDFIX0011 | C27: Price Recovery(Bond) | D27: 279 | E27: =VLOOKUP($D27,'Tag(Glossary)'!$B:$G,2,0) -> MDUpdateAction | F27: Y | G27: =VLOOKUP($D27,'Tag(Glossary)'!$B:$G,4,0) -> String | H27: =VLOOKUP($D27,'Tag(Glossary)'!$B:$G,5,0) -> 1 | I27: =VLOOKUP($D27,'Tag(Glossary)'!$B:$H,6,0)&IF(ISBLANK(VLOOKUP($D27,'Tag(Glossary)'!$B:$H,7,0)),"",CHAR(10))&VLOOKUP($D27,'Tag(Glossary)'!$B:$H,7,0) -> Type code of update action for an entry of market data 0 = New
B28: =INDEX('Interface List'!$D$7:$D$45,MATCH($C28,'Interface List'!$E$7:$E$45,0)) -> IFMDFIX0011 | C28: Price Recovery(Bond) | D28: 269 | E28: =VLOOKUP($D28,'Tag(Glossary)'!$B:$G,2,0) -> MDEntryType | F28: Y | G28: =VLOOKUP($D28,'Tag(Glossary)'!$B:$G,4,0) -> String | H28: =VLOOKUP($D28,'Tag(Glossary)'!$B:$G,5,0) -> 1 | I28: =VLOOKUP($D28,'Tag(Glossary)'!$B:$H,6,0)&IF(ISBLANK(VLOOKUP($D28,'Tag(Glossary)'!$B:$H,7,0)),"",CHAR(10))&VLOOKUP($D28,'Tag(Glossary)'!$B:$H,7,0) -> Data classification for an entry of market data Possible values in message X (Price) . 0 = Bid 1 = Offer 2 = Trade 4 = Opening Price 7 = Trading Session High Price 8 = Trading Session Low Price Possible values in message W (Price Recovery) . 0 = Bid 1 = Offer
B29: =INDEX('Interface List'!$D$7:$D$45,MATCH($C29,'Interface List'!$E$7:$E$45,0)) -> IFMDFIX0011 | C29: Price Recovery(Bond) | D29: 290 | E29: =VLOOKUP($D29,'Tag(Glossary)'!$B:$G,2,0) -> MDEntryPositionNo | F29: Y | G29: =VLOOKUP($D29,'Tag(Glossary)'!$B:$G,4,0) -> Int | H29: =VLOOKUP($D29,'Tag(Glossary)'!$B:$G,5,0) -> 2 | I29: =VLOOKUP($D29,'Tag(Glossary)'!$B:$H,6,0)&IF(ISBLANK(VLOOKUP($D29,'Tag(Glossary)'!$B:$H,7,0)),"",CHAR(10))&VLOOKUP($D29,'Tag(Glossary)'!$B:$H,7,0) -> Position no (or level) for an entry of market data
B30: =INDEX('Interface List'!$D$7:$D$45,MATCH($C30,'Interface List'!$E$7:$E$45,0)) -> IFMDFIX0011 | C30: Price Recovery(Bond) | D30: 270 | E30: =VLOOKUP($D30,'Tag(Glossary)'!$B:$G,2,0) -> MDEntryPx | F30: Y | G30: =VLOOKUP($D30,'Tag(Glossary)'!$B:$G,4,0) -> Price | H30: =VLOOKUP($D30,'Tag(Glossary)'!$B:$G,5,0) -> 15(9.4) | I30: =VLOOKUP($D30,'Tag(Glossary)'!$B:$H,6,0)&IF(ISBLANK(VLOOKUP($D30,'Tag(Glossary)'!$B:$H,7,0)),"",CHAR(10))&VLOOKUP($D30,'Tag(Glossary)'!$B:$H,7,0) -> Price for an entry of market data
B31: =INDEX('Interface List'!$D$7:$D$45,MATCH($C31,'Interface List'!$E$7:$E$45,0)) -> IFMDFIX0011 | C31: Price Recovery(Bond) | D31: 271 | E31: =VLOOKUP($D31,'Tag(Glossary)'!$B:$G,2,0) -> MDEntrySize | F31: Y | G31: =VLOOKUP($D31,'Tag(Glossary)'!$B:$G,4,0) -> Int | H31: =VLOOKUP($D31,'Tag(Glossary)'!$B:$G,5,0) -> 12 | I31: =VLOOKUP($D31,'Tag(Glossary)'!$B:$H,6,0)&IF(ISBLANK(VLOOKUP($D31,'Tag(Glossary)'!$B:$H,7,0)),"",CHAR(10))&VLOOKUP($D31,'Tag(Glossary)'!$B:$H,7,0) -> Size (or quantity) for an entry of market data
B32: =INDEX('Interface List'!$D$7:$D$45,MATCH($C32,'Interface List'!$E$7:$E$45,0)) -> IFMDFIX0011 | C32: Price Recovery(Bond) | D32: 346 | E32: =VLOOKUP($D32,'Tag(Glossary)'!$B:$G,2,0) -> NumberOfOrders | F32: N | G32: =VLOOKUP($D32,'Tag(Glossary)'!$B:$G,4,0) -> Int | H32: =VLOOKUP($D32,'Tag(Glossary)'!$B:$G,5,0) -> 11 | I32: =VLOOKUP($D32,'Tag(Glossary)'!$B:$H,6,0)&IF(ISBLANK(VLOOKUP($D32,'Tag(Glossary)'!$B:$H,7,0)),"",CHAR(10))&VLOOKUP($D32,'Tag(Glossary)'!$B:$H,7,0) -> Number of orders
B33: =INDEX('Interface List'!$D$7:$D$45,MATCH($C33,'Interface List'!$E$7:$E$45,0)) -> IFMDFIX0011 | C33: Price Recovery(Bond) | D33: 30270 | E33: =VLOOKUP($D33,'Tag(Glossary)'!$B:$G,2,0) -> MDEntryYield | F33: Y | G33: =VLOOKUP($D33,'Tag(Glossary)'!$B:$G,4,0) -> Float | H33: =VLOOKUP($D33,'Tag(Glossary)'!$B:$G,5,0) -> 13(5.6) | I33: =VLOOKUP($D33,'Tag(Glossary)'!$B:$H,6,0)&IF(ISBLANK(VLOOKUP($D33,'Tag(Glossary)'!$B:$H,7,0)),"",CHAR(10))&VLOOKUP($D33,'Tag(Glossary)'!$B:$H,7,0) -> Yield of the entry. Bond market only.
B34: =INDEX('Interface List'!$D$7:$D$45,MATCH($C34,'Interface List'!$E$7:$E$45,0)) -> IFMDFIX0011 | C34: Price Recovery(Bond) | D34: 30271 | E34: =VLOOKUP($D34,'Tag(Glossary)'!$B:$G,2,0) -> MDEntryMMSize | F34: Y | G34: =VLOOKUP($D34,'Tag(Glossary)'!$B:$G,4,0) -> Int | H34: =VLOOKUP($D34,'Tag(Glossary)'!$B:$G,5,0) -> 12 | I34: =VLOOKUP($D34,'Tag(Glossary)'!$B:$H,6,0)&IF(ISBLANK(VLOOKUP($D34,'Tag(Glossary)'!$B:$H,7,0)),"",CHAR(10))&VLOOKUP($D34,'Tag(Glossary)'!$B:$H,7,0) -> Size of the entry provided from market makers
B35: =INDEX('Interface List'!$D$7:$D$45,MATCH($C35,'Interface List'!$E$7:$E$45,0)) -> IFMDFIX0011 | C35: Price Recovery(Bond) | E35: Standard Trailer | F35: Y

Sheet (Block Trade) PriceRecovery
B2: (Block Trade) Price Recovery
B4: Interface ID | C4: Interface Name | D4: Tag | E4: Field Name | F4: Req'd | G4: Format | H4: Length | I4: Comments
B5: =INDEX('Interface List'!$D$7:$D$45,MATCH($C5,'Interface List'!$E$7:$E$45,0)) -> IFMDFIX0012 | C5: (Block Trade) Price Recovery | E5: Standard Header | F5: Y | I5: MsgType = W
B6: =INDEX('Interface List'!$D$7:$D$45,MATCH($C6,'Interface List'!$E$7:$E$45,0)) -> IFMDFIX0012 | C6: (Block Trade) Price Recovery | D6: 30001 | E6: =VLOOKUP($D6,'Tag(Glossary)'!$B:$G,2,0) -> MarketID | F6: Y | G6: =VLOOKUP($D6,'Tag(Glossary)'!$B:$G,4,0) -> String | H6: =VLOOKUP($D6,'Tag(Glossary)'!$B:$G,5,0) -> 3 | I6: =VLOOKUP($D6,'Tag(Glossary)'!$B:$H,6,0)&IF(ISBLANK(VLOOKUP($D6,'Tag(Glossary)'!$B:$H,7,0)),"",CHAR(10))&VLOOKUP($D6,'Tag(Glossary)'!$B:$H,7,0) -> ID for identifying the market <Hochiminh Exchange> - STO: HoSE Stock Market - BDO: HoSE Bond Market - RPO: HoSE Repo Market <Hanoi Exchange> - STX: HNX Listed Stock Market - BDX: HNX Government Bond Market - DVX: HNX Derivative Market - UPX: HNX UpCoM Stock Market - HCX: HNX Corporate Bond Market
B7: =INDEX('Interface List'!$D$7:$D$45,MATCH($C7,'Interface List'!$E$7:$E$45,0)) -> IFMDFIX0012 | C7: (Block Trade) Price Recovery | D7: 20004 | E7: =VLOOKUP($D7,'Tag(Glossary)'!$B:$G,2,0) -> BoardID | F7: Y | G7: =VLOOKUP($D7,'Tag(Glossary)'!$B:$G,4,0) -> String | H7: =VLOOKUP($D7,'Tag(Glossary)'!$B:$G,5,0) -> 2 | I7: =VLOOKUP($D7,'Tag(Glossary)'!$B:$H,6,0)&IF(ISBLANK(VLOOKUP($D7,'Tag(Glossary)'!$B:$H,7,0)),"",CHAR(10))&VLOOKUP($D7,'Tag(Glossary)'!$B:$H,7,0) -> Unique identifier to a Board where a given instrument is traded G1 : Main G2 : Pre open G3 : Post closing G4 : Odd lot G7 : Buy-in G8 : Sell-out T1 : Negotiation (regular) T4 : Negotiation (regular for Odd lot) T2 : Negotiation (pre) T3 : Negotiation (post) T6 : Negotiation (post for Odd lot) R1 : Negotiation (Repo) AL : All Boards
B8: =INDEX('Interface List'!$D$7:$D$45,MATCH($C8,'Interface List'!$E$7:$E$45,0)) -> IFMDFIX0012 | C8: (Block Trade) Price Recovery | D8: 336 | E8: =VLOOKUP($D8,'Tag(Glossary)'!$B:$G,2,0) -> TradingSessionID | F8: Y | G8: =VLOOKUP($D8,'Tag(Glossary)'!$B:$G,4,0) -> String | H8: =VLOOKUP($D8,'Tag(Glossary)'!$B:$G,5,0) -> 2 | I8: =VLOOKUP($D8,'Tag(Glossary)'!$B:$H,6,0)&IF(ISBLANK(VLOOKUP($D8,'Tag(Glossary)'!$B:$H,7,0)),"",CHAR(10))&VLOOKUP($D8,'Tag(Glossary)'!$B:$H,7,0) -> Trading Session 01 = GT Order Load 10 = Opening Call Auction 11 = Opening Call Auction Extension 20 = Call Auction after Halt 21 = Call Auction after Halt Extension 30 = Closing Call Auction 40 = Continuous Auction 50 = VI Call Auction 51 = VI Call Auction Extension 60 = Order Accept Only 80 = Periodic Call Auction 90 = Trading Halt 99 = Board Closing
B9: =INDEX('Interface List'!$D$7:$D$45,MATCH($C9,'Interface List'!$E$7:$E$45,0)) -> IFMDFIX0012 | C9: (Block Trade) Price Recovery | D9: 55 | E9: =VLOOKUP($D9,'Tag(Glossary)'!$B:$G,2,0) -> Symbol | F9: Y | G9: =VLOOKUP($D9,'Tag(Glossary)'!$B:$G,4,0) -> String | H9: =VLOOKUP($D9,'Tag(Glossary)'!$B:$G,5,0) -> 12 | I9: =VLOOKUP($D9,'Tag(Glossary)'!$B:$H,6,0)&IF(ISBLANK(VLOOKUP($D9,'Tag(Glossary)'!$B:$H,7,0)),"",CHAR(10))&VLOOKUP($D9,'Tag(Glossary)'!$B:$H,7,0) -> The unique code of an issue (a.k.a. instrument or symbol). Generally it is ISIN code but in case of Repo market it is defined as the exchange staffs want
B10: =INDEX('Interface List'!$D$7:$D$45,MATCH($C10,'Interface List'!$E$7:$E$45,0)) -> IFMDFIX0012 | C10: (Block Trade) Price Recovery | D10: 30561 | E10: =VLOOKUP($D10,'Tag(Glossary)'!$B:$G,2,0) -> OpnPx | F10: Y | G10: =VLOOKUP($D10,'Tag(Glossary)'!$B:$G,4,0) -> Price | H10: =VLOOKUP($D10,'Tag(Glossary)'!$B:$G,5,0) -> 15(9.4) | I10: =VLOOKUP($D10,'Tag(Glossary)'!$B:$H,6,0)&IF(ISBLANK(VLOOKUP($D10,'Tag(Glossary)'!$B:$H,7,0)),"",CHAR(10))&VLOOKUP($D10,'Tag(Glossary)'!$B:$H,7,0) -> The first price during that day
B11: =INDEX('Interface List'!$D$7:$D$45,MATCH($C11,'Interface List'!$E$7:$E$45,0)) -> IFMDFIX0012 | C11: (Block Trade) Price Recovery | D11: 30562 | E11: =VLOOKUP($D11,'Tag(Glossary)'!$B:$G,2,0) -> TrdSessnHighPx | F11: Y | G11: =VLOOKUP($D11,'Tag(Glossary)'!$B:$G,4,0) -> Price | H11: =VLOOKUP($D11,'Tag(Glossary)'!$B:$G,5,0) -> 15(9.4) | I11: =VLOOKUP($D11,'Tag(Glossary)'!$B:$H,6,0)&IF(ISBLANK(VLOOKUP($D11,'Tag(Glossary)'!$B:$H,7,0)),"",CHAR(10))&VLOOKUP($D11,'Tag(Glossary)'!$B:$H,7,0) -> Highest price during that day
B12: =INDEX('Interface List'!$D$7:$D$45,MATCH($C12,'Interface List'!$E$7:$E$45,0)) -> IFMDFIX0012 | C12: (Block Trade) Price Recovery | D12: 30563 | E12: =VLOOKUP($D12,'Tag(Glossary)'!$B:$G,2,0) -> TrdSessnLowPx | F12: Y | G12: =VLOOKUP($D12,'Tag(Glossary)'!$B:$G,4,0) -> Price | H12: =VLOOKUP($D12,'Tag(Glossary)'!$B:$G,5,0) -> 15(9.4) | I12: =VLOOKUP($D12,'Tag(Glossary)'!$B:$H,6,0)&IF(ISBLANK(VLOOKUP($D12,'Tag(Glossary)'!$B:$H,7,0)),"",CHAR(10))&VLOOKUP($D12,'Tag(Glossary)'!$B:$H,7,0) -> Lowest price during that day
B13: =INDEX('Interface List'!$D$7:$D$45,MATCH($C13,'Interface List'!$E$7:$E$45,0)) -> IFMDFIX0012 | C13: (Block Trade) Price Recovery | D13: 20026 | E13: =VLOOKUP($D13,'Tag(Glossary)'!$B:$G,2,0) -> SymbolCloseInfoPx | F13: Y | G13: =VLOOKUP($D13,'Tag(Glossary)'!$B:$G,4,0) -> Price | H13: =VLOOKUP($D13,'Tag(Glossary)'!$B:$G,5,0) -> 15(9.4) | I13: =VLOOKUP($D13,'Tag(Glossary)'!$B:$H,6,0)&IF(ISBLANK(VLOOKUP($D13,'Tag(Glossary)'!$B:$H,7,0)),"",CHAR(10))&VLOOKUP($D13,'Tag(Glossary)'!$B:$H,7,0) -> The last execution price of that day. If there is no execution it is replaced with the reference price, and if no reference price is given then it will be 0 (zero)
B14: =INDEX('Interface List'!$D$7:$D$45,MATCH($C14,'Interface List'!$E$7:$E$45,0)) -> IFMDFIX0012 | C14: (Block Trade) Price Recovery | D14: 387 | E14: =VLOOKUP($D14,'Tag(Glossary)'!$B:$G,2,0) -> TotalVolumeTraded | F14: Y | G14: =VLOOKUP($D14,'Tag(Glossary)'!$B:$G,4,0) -> Int | H14: =VLOOKUP($D14,'Tag(Glossary)'!$B:$G,5,0) -> 12 | I14: =VLOOKUP($D14,'Tag(Glossary)'!$B:$H,6,0)&IF(ISBLANK(VLOOKUP($D14,'Tag(Glossary)'!$B:$H,7,0)),"",CHAR(10))&VLOOKUP($D14,'Tag(Glossary)'!$B:$H,7,0) -> Total volume traded
B15: =INDEX('Interface List'!$D$7:$D$45,MATCH($C15,'Interface List'!$E$7:$E$45,0)) -> IFMDFIX0012 | C15: (Block Trade) Price Recovery | D15: 381 | E15: =VLOOKUP($D15,'Tag(Glossary)'!$B:$G,2,0) -> GrossTradeAmt | F15: Y | G15: =VLOOKUP($D15,'Tag(Glossary)'!$B:$G,4,0) -> Float | H15: =VLOOKUP($D15,'Tag(Glossary)'!$B:$G,5,0) -> 23(18.4) | I15: =VLOOKUP($D15,'Tag(Glossary)'!$B:$H,6,0)&IF(ISBLANK(VLOOKUP($D15,'Tag(Glossary)'!$B:$H,7,0)),"",CHAR(10))&VLOOKUP($D15,'Tag(Glossary)'!$B:$H,7,0) -> Gross amount traded
B16: =INDEX('Interface List'!$D$7:$D$45,MATCH($C16,'Interface List'!$E$7:$E$45,0)) -> IFMDFIX0012 | C16: (Block Trade) Price Recovery | E16: Standard Trailer | F16: Y

Sheet (Block Trade) PriceRecovery(B) 
B2: (Block Trade) Price Recovery(Bond)
B4: Interface ID | C4: Interface Name | D4: Tag | E4: Field Name | F4: Req'd | G4: Format | H4: Length | I4: Comments
B5: =INDEX('Interface List'!$D$7:$D$45,MATCH($C5,'Interface List'!$E$7:$E$45,0)) -> IFMDFIX0013 | C5: (Block Trade) Price Recovery(Bond) | E5: Standard Header | F5: Y | I5: MsgType = W
B6: =INDEX('Interface List'!$D$7:$D$45,MATCH($C6,'Interface List'!$E$7:$E$45,0)) -> IFMDFIX0013 | C6: (Block Trade) Price Recovery(Bond) | D6: 30001 | E6: =VLOOKUP($D6,'Tag(Glossary)'!$B:$G,2,0) -> MarketID | F6: Y | G6: =VLOOKUP($D6,'Tag(Glossary)'!$B:$G,4,0) -> String | H6: =VLOOKUP($D6,'Tag(Glossary)'!$B:$G,5,0) -> 3 | I6: =VLOOKUP($D6,'Tag(Glossary)'!$B:$H,6,0)&IF(ISBLANK(VLOOKUP($D6,'Tag(Glossary)'!$B:$H,7,0)),"",CHAR(10))&VLOOKUP($D6,'Tag(Glossary)'!$B:$H,7,0) -> ID for identifying the market <Hochiminh Exchange> - STO: HoSE Stock Market - BDO: HoSE Bond Market - RPO: HoSE Repo Market <Hanoi Exchange> - STX: HNX Listed Stock Market - BDX: HNX Government Bond Market - DVX: HNX Derivative Market - UPX: HNX UpCoM Stock Market - HCX: HNX Corporate Bond Market
B7: =INDEX('Interface List'!$D$7:$D$45,MATCH($C7,'Interface List'!$E$7:$E$45,0)) -> IFMDFIX0013 | C7: (Block Trade) Price Recovery(Bond) | D7: 20004 | E7: =VLOOKUP($D7,'Tag(Glossary)'!$B:$G,2,0) -> BoardID | F7: Y | G7: =VLOOKUP($D7,'Tag(Glossary)'!$B:$G,4,0) -> String | H7: =VLOOKUP($D7,'Tag(Glossary)'!$B:$G,5,0) -> 2 | I7: =VLOOKUP($D7,'Tag(Glossary)'!$B:$H,6,0)&IF(ISBLANK(VLOOKUP($D7,'Tag(Glossary)'!$B:$H,7,0)),"",CHAR(10))&VLOOKUP($D7,'Tag(Glossary)'!$B:$H,7,0) -> Unique identifier to a Board where a given instrument is traded G1 : Main G2 : Pre open G3 : Post closing G4 : Odd lot G7 : Buy-in G8 : Sell-out T1 : Negotiation (regular) T4 : Negotiation (regular for Odd lot) T2 : Negotiation (pre) T3 : Negotiation (post) T6 : Negotiation (post for Odd lot) R1 : Negotiation (Repo) AL : All Boards
B8: =INDEX('Interface List'!$D$7:$D$45,MATCH($C8,'Interface List'!$E$7:$E$45,0)) -> IFMDFIX0013 | C8: (Block Trade) Price Recovery(Bond) | D8: 336 | E8: =VLOOKUP($D8,'Tag(Glossary)'!$B:$G,2,0) -> TradingSessionID | F8: Y | G8: =VLOOKUP($D8,'Tag(Glossary)'!$B:$G,4,0) -> String | H8: =VLOOKUP($D8,'Tag(Glossary)'!$B:$G,5,0) -> 2 | I8: =VLOOKUP($D8,'Tag(Glossary)'!$B:$H,6,0)&IF(ISBLANK(VLOOKUP($D8,'Tag(Glossary)'!$B:$H,7,0)),"",CHAR(10))&VLOOKUP($D8,'Tag(Glossary)'!$B:$H,7,0) -> Trading Session 01 = GT Order Load 10 = Opening Call Auction 11 = Opening Call Auction Extension 20 = Call Auction after Halt 21 = Call Auction after Halt Extension 30 = Closing Call Auction 40 = Continuous Auction 50 = VI Call Auction 51 = VI Call Auction Extension 60 = Order Accept Only 80 = Periodic Call Auction 90 = Trading Halt 99 = Board Closing
B9: =INDEX('Interface List'!$D$7:$D$45,MATCH($C9,'Interface List'!$E$7:$E$45,0)) -> IFMDFIX0013 | C9: (Block Trade) Price Recovery(Bond) | D9: 55 | E9: =VLOOKUP($D9,'Tag(Glossary)'!$B:$G,2,0) -> Symbol | F9: Y | G9: =VLOOKUP($D9,'Tag(Glossary)'!$B:$G,4,0) -> String | H9: =VLOOKUP($D9,'Tag(Glossary)'!$B:$G,5,0) -> 12 | I9: =VLOOKUP($D9,'Tag(Glossary)'!$B:$H,6,0)&IF(ISBLANK(VLOOKUP($D9,'Tag(Glossary)'!$B:$H,7,0)),"",CHAR(10))&VLOOKUP($D9,'Tag(Glossary)'!$B:$H,7,0) -> The unique code of an issue (a.k.a. instrument or symbol). Generally it is ISIN code but in case of Repo market it is defined as the exchange staffs want
B10: =INDEX('Interface List'!$D$7:$D$45,MATCH($C10,'Interface List'!$E$7:$E$45,0)) -> IFMDFIX0013 | C10: (Block Trade) Price Recovery(Bond) | D10: 30561 | E10: =VLOOKUP($D10,'Tag(Glossary)'!$B:$G,2,0) -> OpnPx | F10: Y | G10: =VLOOKUP($D10,'Tag(Glossary)'!$B:$G,4,0) -> Price | H10: =VLOOKUP($D10,'Tag(Glossary)'!$B:$G,5,0) -> 15(9.4) | I10: =VLOOKUP($D10,'Tag(Glossary)'!$B:$H,6,0)&IF(ISBLANK(VLOOKUP($D10,'Tag(Glossary)'!$B:$H,7,0)),"",CHAR(10))&VLOOKUP($D10,'Tag(Glossary)'!$B:$H,7,0) -> The first price during that day
B11: =INDEX('Interface List'!$D$7:$D$45,MATCH($C11,'Interface List'!$E$7:$E$45,0)) -> IFMDFIX0013 | C11: (Block Trade) Price Recovery(Bond) | D11: 30562 | E11: =VLOOKUP($D11,'Tag(Glossary)'!$B:$G,2,0) -> TrdSessnHighPx | F11: Y | G11: =VLOOKUP($D11,'Tag(Glossary)'!$B:$G,4,0) -> Price | H11: =VLOOKUP($D11,'Tag(Glossary)'!$B:$G,5,0) -> 15(9.4) | I11: =VLOOKUP($D11,'Tag(Glossary)'!$B:$H,6,0)&IF(ISBLANK(VLOOKUP($D11,'Tag(Glossary)'!$B:$H,7,0)),"",CHAR(10))&VLOOKUP($D11,'Tag(Glossary)'!$B:$H,7,0) -> Highest price during that day
B12: =INDEX('Interface List'!$D$7:$D$45,MATCH($C12,'Interface List'!$E$7:$E$45,0)) -> IFMDFIX0013 | C12: (Block Trade) Price Recovery(Bond) | D12: 30563 | E12: =VLOOKUP($D12,'Tag(Glossary)'!$B:$G,2,0) -> TrdSessnLowPx | F12: Y | G12: =VLOOKUP($D12,'Tag(Glossary)'!$B:$G,4,0) -> Price | H12: =VLOOKUP($D12,'Tag(Glossary)'!$B:$G,5,0) -> 15(9.4) | I12: =VLOOKUP($D12,'Tag(Glossary)'!$B:$H,6,0)&IF(ISBLANK(VLOOKUP($D12,'Tag(Glossary)'!$B:$H,7,0)),"",CHAR(10))&VLOOKUP($D12,'Tag(Glossary)'!$B:$H,7,0) -> Lowest price during that day
B13: =INDEX('Interface List'!$D$7:$D$45,MATCH($C13,'Interface List'!$E$7:$E$45,0)) -> IFMDFIX0013 | C13: (Block Trade) Price Recovery(Bond) | D13: 20026 | E13: =VLOOKUP($D13,'Tag(Glossary)'!$B:$G,2,0) -> SymbolCloseInfoPx | F13: Y | G13: =VLOOKUP($D13,'Tag(Glossary)'!$B:$G,4,0) -> Price | H13: =VLOOKUP($D13,'Tag(Glossary)'!$B:$G,5,0) -> 15(9.4) | I13: =VLOOKUP($D13,'Tag(Glossary)'!$B:$H,6,0)&IF(ISBLANK(VLOOKUP($D13,'Tag(Glossary)'!$B:$H,7,0)),"",CHAR(10))&VLOOKUP($D13,'Tag(Glossary)'!$B:$H,7,0) -> The last execution price of that day. If there is no execution it is replaced with the reference price, and if no reference price is given then it will be 0 (zero)
B14: =INDEX('Interface List'!$D$7:$D$45,MATCH($C14,'Interface List'!$E$7:$E$45,0)) -> IFMDFIX0013 | C14: (Block Trade) Price Recovery(Bond) | D14: 30565 | E14: =VLOOKUP($D14,'Tag(Glossary)'!$B:$G,2,0) -> OpnPxYld | F14: Y | G14: =VLOOKUP($D14,'Tag(Glossary)'!$B:$G,4,0) -> Float | H14: =VLOOKUP($D14,'Tag(Glossary)'!$B:$G,5,0) -> 13(5.6) | I14: =VLOOKUP($D14,'Tag(Glossary)'!$B:$H,6,0)&IF(ISBLANK(VLOOKUP($D14,'Tag(Glossary)'!$B:$H,7,0)),"",CHAR(10))&VLOOKUP($D14,'Tag(Glossary)'!$B:$H,7,0) -> Yield rate for opening price
B15: =INDEX('Interface List'!$D$7:$D$45,MATCH($C15,'Interface List'!$E$7:$E$45,0)) -> IFMDFIX0013 | C15: (Block Trade) Price Recovery(Bond) | D15: 30566 | E15: =VLOOKUP($D15,'Tag(Glossary)'!$B:$G,2,0) -> TrdSessnHighPxYld | F15: Y | G15: =VLOOKUP($D15,'Tag(Glossary)'!$B:$G,4,0) -> Float | H15: =VLOOKUP($D15,'Tag(Glossary)'!$B:$G,5,0) -> 13(5.6) | I15: =VLOOKUP($D15,'Tag(Glossary)'!$B:$H,6,0)&IF(ISBLANK(VLOOKUP($D15,'Tag(Glossary)'!$B:$H,7,0)),"",CHAR(10))&VLOOKUP($D15,'Tag(Glossary)'!$B:$H,7,0) -> Yield rate for high price
B16: =INDEX('Interface List'!$D$7:$D$45,MATCH($C16,'Interface List'!$E$7:$E$45,0)) -> IFMDFIX0013 | C16: (Block Trade) Price Recovery(Bond) | D16: 30567 | E16: =VLOOKUP($D16,'Tag(Glossary)'!$B:$G,2,0) -> TrdSessnLowPxYld | F16: Y | G16: =VLOOKUP($D16,'Tag(Glossary)'!$B:$G,4,0) -> Float | H16: =VLOOKUP($D16,'Tag(Glossary)'!$B:$G,5,0) -> 13(5.6) | I16: =VLOOKUP($D16,'Tag(Glossary)'!$B:$H,6,0)&IF(ISBLANK(VLOOKUP($D16,'Tag(Glossary)'!$B:$H,7,0)),"",CHAR(10))&VLOOKUP($D16,'Tag(Glossary)'!$B:$H,7,0) -> Yield rate for low price
B17: =INDEX('Interface List'!$D$7:$D$45,MATCH($C17,'Interface List'!$E$7:$E$45,0)) -> IFMDFIX0013 | C17: (Block Trade) Price Recovery(Bond) | D17: 30568 | E17: =VLOOKUP($D17,'Tag(Glossary)'!$B:$G,2,0) -> ClsPxYld | F17: Y | G17: =VLOOKUP($D17,'Tag(Glossary)'!$B:$G,4,0) -> Float | H17: =VLOOKUP($D17,'Tag(Glossary)'!$B:$G,5,0) -> 13(5.6) | I17: =VLOOKUP($D17,'Tag(Glossary)'!$B:$H,6,0)&IF(ISBLANK(VLOOKUP($D17,'Tag(Glossary)'!$B:$H,7,0)),"",CHAR(10))&VLOOKUP($D17,'Tag(Glossary)'!$B:$H,7,0) -> Final yield of a bond calculated using the closing price of that day
... B19: =INDEX('Interface List'!$D$7:$D$45,MATCH($C19,'Interface List'!$E$7:$E$45,0)) -> IFMDFIX0013 | C19: (Block Trade) Price Recovery(Bond) | D19: 381 | E19: =VLOOKUP($D19,'Tag(Glossary)'!$B:$G,2,0) -> GrossTradeAmt | F19: Y | G19: =VLOOKUP($D19,'Tag(Glossary)'!$B:$G,4,0) -> Float | H19: =VLOOKUP($D19,'Tag(Glossary)'!$B:$G,5,0) -> 23(18.4) | I19: =VLOOKUP($D19,'Tag(Glossary)'!$B:$H,6,0)&IF(ISBLANK(VLOOKUP($D19,'Tag(Glossary)'!$B:$H,7,0)),"",CHAR(10))&VLOOKUP($D19,'Tag(Glossary)'!$B:$H,7,0) -> Gross amount traded
B20: =INDEX('Interface List'!$D$7:$D$45,MATCH($C20,'Interface List'!$E$7:$E$45,0)) -> IFMDFIX0013 | C20: (Block Trade) Price Recovery(Bond) | E20: Standard Trailer | F20: Y

Sheet Index
B2: Index
B4: Interface ID | C4: Interface Name | D4: Tag | E4: Field Name | F4: Req'd | G4: Format | H4: Length | I4: Comments
B5: =INDEX('Interface List'!$D$7:$D$45,MATCH($C5,'Interface List'!$E$7:$E$45,0)) -> IFMDFIX0014 | C5: Index | E5: Standard Header | F5: Y | I5: MsgType = M1
B6: =INDEX('Interface List'!$D$7:$D$45,MATCH($C6,'Interface List'!$E$7:$E$45,0)) -> IFMDFIX0014 | C6: Index | D6: 30001 | E6: =VLOOKUP($D6,'Tag(Glossary)'!$B:$G,2,0) -> MarketID | F6: Y | G6: =VLOOKUP($D6,'Tag(Glossary)'!$B:$G,4,0) -> String | H6: =VLOOKUP($D6,'Tag(Glossary)'!$B:$G,5,0) -> 3 | I6: =VLOOKUP($D6,'Tag(Glossary)'!$B:$H,6,0)&IF(ISBLANK(VLOOKUP($D6,'Tag(Glossary)'!$B:$H,7,0)),"",CHAR(10))&VLOOKUP($D6,'Tag(Glossary)'!$B:$H,7,0) -> ID for identifying the market <Hochiminh Exchange> - STO: HoSE Stock Market - BDO: HoSE Bond Market - RPO: HoSE Repo Market <Hanoi Exchange> - STX: HNX Listed Stock Market - BDX: HNX Government Bond Market - DVX: HNX Derivative Market - UPX: HNX UpCoM Stock Market - HCX: HNX Corporate Bond Market
B7: =INDEX('Interface List'!$D$7:$D$45,MATCH($C7,'Interface List'!$E$7:$E$45,0)) -> IFMDFIX0014 | C7: Index | D7: 336 | E7: =VLOOKUP($D7,'Tag(Glossary)'!$B:$G,2,0) -> TradingSessionID | F7: Y | G7: =VLOOKUP($D7,'Tag(Glossary)'!$B:$G,4,0) -> String | H7: =VLOOKUP($D7,'Tag(Glossary)'!$B:$G,5,0) -> 2 | I7: =VLOOKUP($D7,'Tag(Glossary)'!$B:$H,6,0)&IF(ISBLANK(VLOOKUP($D7,'Tag(Glossary)'!$B:$H,7,0)),"",CHAR(10))&VLOOKUP($D7,'Tag(Glossary)'!$B:$H,7,0) -> Trading Session 01 = GT Order Load 10 = Opening Call Auction 11 = Opening Call Auction Extension 20 = Call Auction after Halt 21 = Call Auction after Halt Extension 30 = Closing Call Auction 40 = Continuous Auction 50 = VI Call Auction 51 = VI Call Auction Extension 60 = Order Accept Only 80 = Periodic Call Auction 90 = Trading Halt 99 = Board Closing
B8: =INDEX('Interface List'!$D$7:$D$45,MATCH($C8,'Interface List'!$E$7:$E$45,0)) -> IFMDFIX0014 | C8: Index | D8: 30569 | E8: =VLOOKUP($D8,'Tag(Glossary)'!$B:$G,2,0) -> MarketIndexClass | F8: Y | G8: =VLOOKUP($D8,'Tag(Glossary)'!$B:$G,4,0) -> String | H8: =VLOOKUP($D8,'Tag(Glossary)'!$B:$G,5,0) -> 1 | I8: =VLOOKUP($D8,'Tag(Glossary)'!$B:$H,6,0)&IF(ISBLANK(VLOOKUP($D8,'Tag(Glossary)'!$B:$H,7,0)),"",CHAR(10))&VLOOKUP($D8,'Tag(Glossary)'!$B:$H,7,0) -> Market code of an index 1: HoSE 2: HNX 3: Composite (HoSE + HNX) 4. UPX
B9: =INDEX('Interface List'!$D$7:$D$45,MATCH($C9,'Interface List'!$E$7:$E$45,0)) -> IFMDFIX0014 | C9: Index | D9: 30167 | E9: =VLOOKUP($D9,'Tag(Glossary)'!$B:$G,2,0) -> IndexsTypeCode | F9: Y | G9: =VLOOKUP($D9,'Tag(Glossary)'!$B:$G,4,0) -> String | H9: =VLOOKUP($D9,'Tag(Glossary)'!$B:$G,5,0) -> 8 | I9: =VLOOKUP($D9,'Tag(Glossary)'!$B:$H,6,0)&IF(ISBLANK(VLOOKUP($D9,'Tag(Glossary)'!$B:$H,7,0)),"",CHAR(10))&VLOOKUP($D9,'Tag(Glossary)'!$B:$H,7,0) -> Industry Index Code for example 001: Composite index 002: VNALLshare index 100: VN30 index
B10: =INDEX('Interface List'!$D$7:$D$45,MATCH($C10,'Interface List'!$E$7:$E$45,0)) -> IFMDFIX0014 | C10: Index | D10: 15 | E10: =VLOOKUP($D10,'Tag(Glossary)'!$B:$G,2,0) -> Currency | F10: Y | G10: =VLOOKUP($D10,'Tag(Glossary)'!$B:$G,4,0) -> String | H10: =VLOOKUP($D10,'Tag(Glossary)'!$B:$G,5,0) -> 3 | I10: =VLOOKUP($D10,'Tag(Glossary)'!$B:$H,6,0)&IF(ISBLANK(VLOOKUP($D10,'Tag(Glossary)'!$B:$H,7,0)),"",CHAR(10))&VLOOKUP($D10,'Tag(Glossary)'!$B:$H,7,0) -> Currency code on ISO 4217 VND: Vietnamese Dong USD: US Dollar EUR: Euro
B11: =INDEX('Interface List'!$D$7:$D$45,MATCH($C11,'Interface List'!$E$7:$E$45,0)) -> IFMDFIX0014 | C11: Index | D11: 60 | E11: =VLOOKUP($D11,'Tag(Glossary)'!$B:$G,2,0) -> TransactTime | F11: Y | G11: =VLOOKUP($D11,'Tag(Glossary)'!$B:$G,4,0) -> UTCTime | H11: =VLOOKUP($D11,'Tag(Glossary)'!$B:$G,5,0) -> 9 | I11: =VLOOKUP($D11,'Tag(Glossary)'!$B:$H,6,0)&IF(ISBLANK(VLOOKUP($D11,'Tag(Glossary)'!$B:$H,7,0)),"",CHAR(10))&VLOOKUP($D11,'Tag(Glossary)'!$B:$H,7,0) -> Time of execution/order creation HHmmSSsss : Normal Case
B12: =INDEX('Interface List'!$D$7:$D$45,MATCH($C12,'Interface List'!$E$7:$E$45,0)) -> IFMDFIX0014 | C12: Index | D12: 30217 | E12: =VLOOKUP($D12,'Tag(Glossary)'!$B:$G,2,0) -> ValueIndexes | F12: Y | G12: =VLOOKUP($D12,'Tag(Glossary)'!$B:$G,4,0) -> Float | H12: =VLOOKUP($D12,'Tag(Glossary)'!$B:$G,5,0) -> 10(6.2) | I12: =VLOOKUP($D12,'Tag(Glossary)'!$B:$H,6,0)&IF(ISBLANK(VLOOKUP($D12,'Tag(Glossary)'!$B:$H,7,0)),"",CHAR(10))&VLOOKUP($D12,'Tag(Glossary)'!$B:$H,7,0) -> Value of the index calculated
B13: =INDEX('Interface List'!$D$7:$D$45,MATCH($C13,'Interface List'!$E$7:$E$45,0)) -> IFMDFIX0014 | C13: Index | D13: 387 | E13: =VLOOKUP($D13,'Tag(Glossary)'!$B:$G,2,0) -> TotalVolumeTraded | F13: Y | G13: =VLOOKUP($D13,'Tag(Glossary)'!$B:$G,4,0) -> Int | H13: =VLOOKUP($D13,'Tag(Glossary)'!$B:$G,5,0) -> 12 | I13: =VLOOKUP($D13,'Tag(Glossary)'!$B:$H,6,0)&IF(ISBLANK(VLOOKUP($D13,'Tag(Glossary)'!$B:$H,7,0)),"",CHAR(10))&VLOOKUP($D13,'Tag(Glossary)'!$B:$H,7,0) -> Total volume traded
B14: =INDEX('Interface List'!$D$7:$D$45,MATCH($C14,'Interface List'!$E$7:$E$45,0)) -> IFMDFIX0014 | C14: Index | D14: 381 | E14: =VLOOKUP($D14,'Tag(Glossary)'!$B:$G,2,0) -> GrossTradeAmt | F14: Y | G14: =VLOOKUP($D14,'Tag(Glossary)'!$B:$G,4,0) -> Float | H14: =VLOOKUP($D14,'Tag(Glossary)'!$B:$G,5,0) -> 23(18.4) | I14: =VLOOKUP($D14,'Tag(Glossary)'!$B:$H,6,0)&IF(ISBLANK(VLOOKUP($D14,'Tag(Glossary)'!$B:$H,7,0)),"",CHAR(10))&VLOOKUP($D14,'Tag(Glossary)'!$B:$H,7,0) -> Gross amount traded
B15: =INDEX('Interface List'!$D$7:$D$45,MATCH($C15,'Interface List'!$E$7:$E$45,0)) -> IFMDFIX0014 | C15: Index | D15: 30638 | E15: =VLOOKUP($D15,'Tag(Glossary)'!$B:$G,2,0) -> ContauctAccTrdvol | F15: Y | G15: =VLOOKUP($D15,'Tag(Glossary)'!$B:$G,4,0) -> Int | H15: =VLOOKUP($D15,'Tag(Glossary)'!$B:$G,5,0) -> 12 | I15: =VLOOKUP($D15,'Tag(Glossary)'!$B:$H,6,0)&IF(ISBLANK(VLOOKUP($D15,'Tag(Glossary)'!$B:$H,7,0)),"",CHAR(10))&VLOOKUP($D15,'Tag(Glossary)'!$B:$H,7,0) -> Accumulative trading volume of boards in continuous trading method
B16: =INDEX('Interface List'!$D$7:$D$45,MATCH($C16,'Interface List'!$E$7:$E$45,0)) -> IFMDFIX0014 | C16: Index | D16: 30639 | E16: =VLOOKUP($D16,'Tag(Glossary)'!$B:$G,2,0) -> ContauctAccTrdval | F16: Y | G16: =VLOOKUP($D16,'Tag(Glossary)'!$B:$G,4,0) -> Float | H16: =VLOOKUP($D16,'Tag(Glossary)'!$B:$G,5,0) -> 23(18.4) | I16: =VLOOKUP($D16,'Tag(Glossary)'!$B:$H,6,0)&IF(ISBLANK(VLOOKUP($D16,'Tag(Glossary)'!$B:$H,7,0)),"",CHAR(10))&VLOOKUP($D16,'Tag(Glossary)'!$B:$H,7,0) -> Accumulative trading value of boards in continuous trading method
B17: =INDEX('Interface List'!$D$7:$D$45,MATCH($C17,'Interface List'!$E$7:$E$45,0)) -> IFMDFIX0014 | C17: Index | D17: 30640 | E17: =VLOOKUP($D17,'Tag(Glossary)'!$B:$G,2,0) -> BlktrdAccTrdvol | F17: Y | G17: =VLOOKUP($D17,'Tag(Glossary)'!$B:$G,4,0) -> Int | H17: =VLOOKUP($D17,'Tag(Glossary)'!$B:$G,5,0) -> 12 | I17: =VLOOKUP($D17,'Tag(Glossary)'!$B:$H,6,0)&IF(ISBLANK(VLOOKUP($D17,'Tag(Glossary)'!$B:$H,7,0)),"",CHAR(10))&VLOOKUP($D17,'Tag(Glossary)'!$B:$H,7,0) -> Accumulative trading volume of boards in block trading method
... B26: =INDEX('Interface List'!$D$7:$D$45,MATCH($C26,'Interface List'!$E$7:$E$45,0)) -> IFMDFIX0014 | C26: Index | D26: 30596 | E26: =VLOOKUP($D26,'Tag(Glossary)'!$B:$G,2,0) -> FluctuationSteadinessIssueVolume | F26: Y | G26: =VLOOKUP($D26,'Tag(Glossary)'!$B:$G,4,0) -> Int | H26: =VLOOKUP($D26,'Tag(Glossary)'!$B:$G,5,0) -> 12 | I26: =VLOOKUP($D26,'Tag(Glossary)'!$B:$H,6,0)&IF(ISBLANK(VLOOKUP($D26,'Tag(Glossary)'!$B:$H,7,0)),"",CHAR(10))&VLOOKUP($D26,'Tag(Glossary)'!$B:$H,7,0) -> Sum of trading volumes of issues of which price is not changed
B27: =INDEX('Interface List'!$D$7:$D$45,MATCH($C27,'Interface List'!$E$7:$E$45,0)) -> IFMDFIX0014 | C27: Index | E27: Standard Trailer

Sheet Investor by Industry
B2: Investor per Industry
B4: Interface ID | C4: Interface Name | D4: Tag | E4: Field Name | F4: Req'd | G4: Format | H4: Length | I4: Comments
B5: =INDEX('Interface List'!$D$7:$D$45,MATCH($C5,'Interface List'!$E$7:$E$45,0)) -> IFMDFIX0015 | C5: Investor per Industry | E5: Standard Header | F5: Y | I5: MsgType = M2
B6: =INDEX('Interface List'!$D$7:$D$45,MATCH($C6,'Interface List'!$E$7:$E$45,0)) -> IFMDFIX0015 | C6: Investor per Industry | D6: 30001 | E6: =VLOOKUP($D6,'Tag(Glossary)'!$B:$G,2,0) -> MarketID | F6: Y | G6: =VLOOKUP($D6,'Tag(Glossary)'!$B:$G,4,0) -> String | H6: =VLOOKUP($D6,'Tag(Glossary)'!$B:$G,5,0) -> 3 | I6: =VLOOKUP($D6,'Tag(Glossary)'!$B:$H,6,0)&IF(ISBLANK(VLOOKUP($D6,'Tag(Glossary)'!$B:$H,7,0)),"",CHAR(10))&VLOOKUP($D6,'Tag(Glossary)'!$B:$H,7,0) -> ID for identifying the market <Hochiminh Exchange> - STO: HoSE Stock Market - BDO: HoSE Bond Market - RPO: HoSE Repo Market <Hanoi Exchange> - STX: HNX Listed Stock Market - BDX: HNX Government Bond Market - DVX: HNX Derivative Market - UPX: HNX UpCoM Stock Market - HCX: HNX Corporate Bond Market
B7: =INDEX('Interface List'!$D$7:$D$45,MATCH($C7,'Interface List'!$E$7:$E$45,0)) -> IFMDFIX0015 | C7: Investor per Industry | D7: 60 | E7: =VLOOKUP($D7,'Tag(Glossary)'!$B:$G,2,0) -> TransactTime | F7: Y | G7: =VLOOKUP($D7,'Tag(Glossary)'!$B:$G,4,0) -> UTCTime | H7: =VLOOKUP($D7,'Tag(Glossary)'!$B:$G,5,0) -> 9 | I7: =VLOOKUP($D7,'Tag(Glossary)'!$B:$H,6,0)&IF(ISBLANK(VLOOKUP($D7,'Tag(Glossary)'!$B:$H,7,0)),"",CHAR(10))&VLOOKUP($D7,'Tag(Glossary)'!$B:$H,7,0) -> Time of execution/order creation HHmmSSsss : Normal Case
B8: =INDEX('Interface List'!$D$7:$D$45,MATCH($C8,'Interface List'!$E$7:$E$45,0)) -> IFMDFIX0015 | C8: Investor per Industry | D8: 30569 | E8: =VLOOKUP($D8,'Tag(Glossary)'!$B:$G,2,0) -> MarketIndexClass | F8: Y | G8: =VLOOKUP($D8,'Tag(Glossary)'!$B:$G,4,0) -> String | H8: =VLOOKUP($D8,'Tag(Glossary)'!$B:$G,5,0) -> 1 | I8: =VLOOKUP($D8,'Tag(Glossary)'!$B:$H,6,0)&IF(ISBLANK(VLOOKUP($D8,'Tag(Glossary)'!$B:$H,7,0)),"",CHAR(10))&VLOOKUP($D8,'Tag(Glossary)'!$B:$H,7,0) -> Market code of an index 1: HoSE 2: HNX 3: Composite (HoSE + HNX) 4. UPX
B9: =INDEX('Interface List'!$D$7:$D$45,MATCH($C9,'Interface List'!$E$7:$E$45,0)) -> IFMDFIX0015 | C9: Investor per Industry | D9: 30167 | E9: =VLOOKUP($D9,'Tag(Glossary)'!$B:$G,2,0) -> IndexsTypeCode | F9: Y | G9: =VLOOKUP($D9,'Tag(Glossary)'!$B:$G,4,0) -> String | H9: =VLOOKUP($D9,'Tag(Glossary)'!$B:$G,5,0) -> 8 | I9: =VLOOKUP($D9,'Tag(Glossary)'!$B:$H,6,0)&IF(ISBLANK(VLOOKUP($D9,'Tag(Glossary)'!$B:$H,7,0)),"",CHAR(10))&VLOOKUP($D9,'Tag(Glossary)'!$B:$H,7,0) -> Industry Index Code for example 001: Composite index 002: VNALLshare index 100: VN30 index
B10: =INDEX('Interface List'!$D$7:$D$45,MATCH($C10,'Interface List'!$E$7:$E$45,0)) -> IFMDFIX0015 | C10: Investor per Industry | D10: 15 | E10: =VLOOKUP($D10,'Tag(Glossary)'!$B:$G,2,0) -> Currency | F10: Y | G10: =VLOOKUP($D10,'Tag(Glossary)'!$B:$G,4,0) -> String | H10: =VLOOKUP($D10,'Tag(Glossary)'!$B:$G,5,0) -> 3 | I10: =VLOOKUP($D10,'Tag(Glossary)'!$B:$H,6,0)&IF(ISBLANK(VLOOKUP($D10,'Tag(Glossary)'!$B:$H,7,0)),"",CHAR(10))&VLOOKUP($D10,'Tag(Glossary)'!$B:$H,7,0) -> Currency code on ISO 4217 VND: Vietnamese Dong USD: US Dollar EUR: Euro
B11: =INDEX('Interface List'!$D$7:$D$45,MATCH($C11,'Interface List'!$E$7:$E$45,0)) -> IFMDFIX0015 | C11: Investor per Industry | D11: 20000 | E11: =VLOOKUP($D11,'Tag(Glossary)'!$B:$G,2,0) -> InvestCode | F11: Y | G11: =VLOOKUP($D11,'Tag(Glossary)'!$B:$G,4,0) -> String | H11: =VLOOKUP($D11,'Tag(Glossary)'!$B:$G,5,0) -> 4 | I11: =VLOOKUP($D11,'Tag(Glossary)'!$B:$H,6,0)&IF(ISBLANK(VLOOKUP($D11,'Tag(Glossary)'!$B:$H,7,0)),"",CHAR(10))&VLOOKUP($D11,'Tag(Glossary)'!$B:$H,7,0) -> This field indicates which category the owner of a given order or quote belongs to. This field is validated against AccountType field as below: - If AccountType is Customer (1), any value is permitted for this field. - If AccountType is House (3), this field must be 1000. 1000 = Securities company 2000 = Insurance company 3000 = Asset management company and Investment company 3200 = Fund 4000 = Bank 5000 = General finance company 6000 = Pension Fund 7000 = Goverment representation 7030 = International organization 7100 = Misc corporation 8000 = Indivisual
B12: =INDEX('Interface List'!$D$7:$D$45,MATCH($C12,'Interface List'!$E$7:$E$45,0)) -> IFMDFIX0015 | C12: Investor per Industry | D12: 331 | E12: =VLOOKUP($D12,'Tag(Glossary)'!$B:$G,2,0) -> SellVolume | F12: Y | G12: =VLOOKUP($D12,'Tag(Glossary)'!$B:$G,4,0) -> Int | H12: =VLOOKUP($D12,'Tag(Glossary)'!$B:$G,5,0) -> 12 | I12: =VLOOKUP($D12,'Tag(Glossary)'!$B:$H,6,0)&IF(ISBLANK(VLOOKUP($D12,'Tag(Glossary)'!$B:$H,7,0)),"",CHAR(10))&VLOOKUP($D12,'Tag(Glossary)'!$B:$H,7,0) -> Trading volume in sell side
B13: =INDEX('Interface List'!$D$7:$D$45,MATCH($C13,'Interface List'!$E$7:$E$45,0)) -> IFMDFIX0015 | C13: Investor per Industry | D13: 30168 | E13: =VLOOKUP($D13,'Tag(Glossary)'!$B:$G,2,0) -> SellTradeAmount | F13: Y | G13: =VLOOKUP($D13,'Tag(Glossary)'!$B:$G,4,0) -> Float | H13: =VLOOKUP($D13,'Tag(Glossary)'!$B:$G,5,0) -> 23(18.4) | I13: =VLOOKUP($D13,'Tag(Glossary)'!$B:$H,6,0)&IF(ISBLANK(VLOOKUP($D13,'Tag(Glossary)'!$B:$H,7,0)),"",CHAR(10))&VLOOKUP($D13,'Tag(Glossary)'!$B:$H,7,0) -> Trading value in ask side
B14: =INDEX('Interface List'!$D$7:$D$45,MATCH($C14,'Interface List'!$E$7:$E$45,0)) -> IFMDFIX0015 | C14: Investor per Industry | D14: 330 | E14: =VLOOKUP($D14,'Tag(Glossary)'!$B:$G,2,0) -> BuyVolume | F14: Y | G14: =VLOOKUP($D14,'Tag(Glossary)'!$B:$G,4,0) -> Int | H14: =VLOOKUP($D14,'Tag(Glossary)'!$B:$G,5,0) -> 12 | I14: =VLOOKUP($D14,'Tag(Glossary)'!$B:$H,6,0)&IF(ISBLANK(VLOOKUP($D14,'Tag(Glossary)'!$B:$H,7,0)),"",CHAR(10))&VLOOKUP($D14,'Tag(Glossary)'!$B:$H,7,0) -> Trading volume in buy side
B15: =INDEX('Interface List'!$D$7:$D$45,MATCH($C15,'Interface List'!$E$7:$E$45,0)) -> IFMDFIX0015 | C15: Investor per Industry | D15: 30169 | E15: =VLOOKUP($D15,'Tag(Glossary)'!$B:$G,2,0) -> BuyTradedAmount | F15: Y | G15: =VLOOKUP($D15,'Tag(Glossary)'!$B:$G,4,0) -> Float | H15: =VLOOKUP($D15,'Tag(Glossary)'!$B:$G,5,0) -> 23(18.4) | I15: =VLOOKUP($D15,'Tag(Glossary)'!$B:$H,6,0)&IF(ISBLANK(VLOOKUP($D15,'Tag(Glossary)'!$B:$H,7,0)),"",CHAR(10))&VLOOKUP($D15,'Tag(Glossary)'!$B:$H,7,0) -> Trading value in bid side
B16: =INDEX('Interface List'!$D$7:$D$45,MATCH($C16,'Interface List'!$E$7:$E$45,0)) -> IFMDFIX0015 | C16: Investor per Industry | E16: Standard Trailer | F16: Y

Sheet Investor by Industry(Bond)
B2: Investor per Industry(Bond)
B4: Interface ID | C4: Interface Name | D4: Tag | E4: Field Name | F4: Req'd | G4: Format | H4: Length | I4: Comments
B5: =INDEX('Interface List'!$D$7:$D$45,MATCH($C5,'Interface List'!$E$7:$E$45,0)) -> IFMDFIX0016 | C5: Investor per Industry(Bond) | E5: Standard Header | F5: Y | I5: MsgType = M2
B6: =INDEX('Interface List'!$D$7:$D$45,MATCH($C6,'Interface List'!$E$7:$E$45,0)) -> IFMDFIX0016 | C6: Investor per Industry(Bond) | D6: 30001 | E6: =VLOOKUP($D6,'Tag(Glossary)'!$B:$G,2,0) -> MarketID | F6: Y | G6: =VLOOKUP($D6,'Tag(Glossary)'!$B:$G,4,0) -> String | H6: =VLOOKUP($D6,'Tag(Glossary)'!$B:$G,5,0) -> 3 | I6: =VLOOKUP($D6,'Tag(Glossary)'!$B:$H,6,0)&IF(ISBLANK(VLOOKUP($D6,'Tag(Glossary)'!$B:$H,7,0)),"",CHAR(10))&VLOOKUP($D6,'Tag(Glossary)'!$B:$H,7,0) -> ID for identifying the market <Hochiminh Exchange> - STO: HoSE Stock Market - BDO: HoSE Bond Market - RPO: HoSE Repo Market <Hanoi Exchange> - STX: HNX Listed Stock Market - BDX: HNX Government Bond Market - DVX: HNX Derivative Market - UPX: HNX UpCoM Stock Market - HCX: HNX Corporate Bond Market
B7: =INDEX('Interface List'!$D$7:$D$45,MATCH($C7,'Interface List'!$E$7:$E$45,0)) -> IFMDFIX0016 | C7: Investor per Industry(Bond) | D7: 60 | E7: =VLOOKUP($D7,'Tag(Glossary)'!$B:$G,2,0) -> TransactTime | F7: Y | G7: =VLOOKUP($D7,'Tag(Glossary)'!$B:$G,4,0) -> UTCTime | H7: =VLOOKUP($D7,'Tag(Glossary)'!$B:$G,5,0) -> 9 | I7: =VLOOKUP($D7,'Tag(Glossary)'!$B:$H,6,0)&IF(ISBLANK(VLOOKUP($D7,'Tag(Glossary)'!$B:$H,7,0)),"",CHAR(10))&VLOOKUP($D7,'Tag(Glossary)'!$B:$H,7,0) -> Time of execution/order creation HHmmSSsss : Normal Case
B8: =INDEX('Interface List'!$D$7:$D$45,MATCH($C8,'Interface List'!$E$7:$E$45,0)) -> IFMDFIX0016 | C8: Investor per Industry(Bond) | D8: 30597 | E8: =VLOOKUP($D8,'Tag(Glossary)'!$B:$G,2,0) -> BondClassificationCode | F8: Y | G8: =VLOOKUP($D8,'Tag(Glossary)'!$B:$G,4,0) -> String | H8: =VLOOKUP($D8,'Tag(Glossary)'!$B:$G,5,0) -> 10 | I8: =VLOOKUP($D8,'Tag(Glossary)'!$B:$H,6,0)&IF(ISBLANK(VLOOKUP($D8,'Tag(Glossary)'!$B:$H,7,0)),"",CHAR(10))&VLOOKUP($D8,'Tag(Glossary)'!$B:$H,7,0) -> T-bills, T-Bonds, Note of the central bank, State mortgage bonds and so on. ## If CFI has a function to classify above, this item is needless
B9: =INDEX('Interface List'!$D$7:$D$45,MATCH($C9,'Interface List'!$E$7:$E$45,0)) -> IFMDFIX0016 | C9: Investor per Industry(Bond) | D9: 20000 | E9: =VLOOKUP($D9,'Tag(Glossary)'!$B:$G,2,0) -> InvestCode | F9: Y | G9: =VLOOKUP($D9,'Tag(Glossary)'!$B:$G,4,0) -> String | H9: =VLOOKUP($D9,'Tag(Glossary)'!$B:$G,5,0) -> 4 | I9: =VLOOKUP($D9,'Tag(Glossary)'!$B:$H,6,0)&IF(ISBLANK(VLOOKUP($D9,'Tag(Glossary)'!$B:$H,7,0)),"",CHAR(10))&VLOOKUP($D9,'Tag(Glossary)'!$B:$H,7,0) -> This field indicates which category the owner of a given order or quote belongs to. This field is validated against AccountType field as below: - If AccountType is Customer (1), any value is permitted for this field. - If AccountType is House (3), this field must be 1000. 1000 = Securities company 2000 = Insurance company 3000 = Asset management company and Investment company 3200 = Fund 4000 = Bank 5000 = General finance company 6000 = Pension Fund 7000 = Goverment representation 7030 = International organization 7100 = Misc corporation 8000 = Indivisual
B10: =INDEX('Interface List'!$D$7:$D$45,MATCH($C10,'Interface List'!$E$7:$E$45,0)) -> IFMDFIX0016 | C10: Investor per Industry(Bond) | D10: 331 | E10: =VLOOKUP($D10,'Tag(Glossary)'!$B:$G,2,0) -> SellVolume | F10: Y | G10: =VLOOKUP($D10,'Tag(Glossary)'!$B:$G,4,0) -> Int | H10: =VLOOKUP($D10,'Tag(Glossary)'!$B:$G,5,0) -> 12 | I10: =VLOOKUP($D10,'Tag(Glossary)'!$B:$H,6,0)&IF(ISBLANK(VLOOKUP($D10,'Tag(Glossary)'!$B:$H,7,0)),"",CHAR(10))&VLOOKUP($D10,'Tag(Glossary)'!$B:$H,7,0) -> Trading volume in sell side
B11: =INDEX('Interface List'!$D$7:$D$45,MATCH($C11,'Interface List'!$E$7:$E$45,0)) -> IFMDFIX0016 | C11: Investor per Industry(Bond) | D11: 30168 | E11: =VLOOKUP($D11,'Tag(Glossary)'!$B:$G,2,0) -> SellTradeAmount | F11: Y | G11: =VLOOKUP($D11,'Tag(Glossary)'!$B:$G,4,0) -> Float | H11: =VLOOKUP($D11,'Tag(Glossary)'!$B:$G,5,0) -> 23(18.4) | I11: =VLOOKUP($D11,'Tag(Glossary)'!$B:$H,6,0)&IF(ISBLANK(VLOOKUP($D11,'Tag(Glossary)'!$B:$H,7,0)),"",CHAR(10))&VLOOKUP($D11,'Tag(Glossary)'!$B:$H,7,0) -> Trading value in ask side
B12: =INDEX('Interface List'!$D$7:$D$45,MATCH($C12,'Interface List'!$E$7:$E$45,0)) -> IFMDFIX0016 | C12: Investor per Industry(Bond) | D12: 330 | E12: =VLOOKUP($D12,'Tag(Glossary)'!$B:$G,2,0) -> BuyVolume | F12: Y | G12: =VLOOKUP($D12,'Tag(Glossary)'!$B:$G,4,0) -> Int | H12: =VLOOKUP($D12,'Tag(Glossary)'!$B:$G,5,0) -> 12 | I12: =VLOOKUP($D12,'Tag(Glossary)'!$B:$H,6,0)&IF(ISBLANK(VLOOKUP($D12,'Tag(Glossary)'!$B:$H,7,0)),"",CHAR(10))&VLOOKUP($D12,'Tag(Glossary)'!$B:$H,7,0) -> Trading volume in buy side
B13: =INDEX('Interface List'!$D$7:$D$45,MATCH($C13,'Interface List'!$E$7:$E$45,0)) -> IFMDFIX0016 | C13: Investor per Industry(Bond) | D13: 30169 | E13: =VLOOKUP($D13,'Tag(Glossary)'!$B:$G,2,0) -> BuyTradedAmount | F13: Y | G13: =VLOOKUP($D13,'Tag(Glossary)'!$B:$G,4,0) -> Float | H13: =VLOOKUP($D13,'Tag(Glossary)'!$B:$G,5,0) -> 23(18.4) | I13: =VLOOKUP($D13,'Tag(Glossary)'!$B:$H,6,0)&IF(ISBLANK(VLOOKUP($D13,'Tag(Glossary)'!$B:$H,7,0)),"",CHAR(10))&VLOOKUP($D13,'Tag(Glossary)'!$B:$H,7,0) -> Trading value in bid side
B14: =INDEX('Interface List'!$D$7:$D$45,MATCH($C14,'Interface List'!$E$7:$E$45,0)) -> IFMDFIX0016 | C14: Investor per Industry(Bond) | E14: Standard Trailer | F14: Y

Sheet Investor by Industry(Drv)
B2: Investor per Industry(Derivatives)
B4: Interface ID | C4: Interface Name | D4: Tag | E4: Field Name | F4: Req'd | G4: Format | H4: Length | I4: Comments
B5: =INDEX('Interface List'!$D$7:$D$45,MATCH($C5,'Interface List'!$E$7:$E$45,0)) -> IFMDFIX0017 | C5: Investor per Industry(Derivatives) | E5: Standard Header | F5: Y | I5: MsgType = M2
B6: =INDEX('Interface List'!$D$7:$D$45,MATCH($C6,'Interface List'!$E$7:$E$45,0)) -> IFMDFIX0017 | C6: Investor per Industry(Derivatives) | D6: 30001 | E6: =VLOOKUP($D6,'Tag(Glossary)'!$B:$G,2,0) -> MarketID | F6: Y | G6: =VLOOKUP($D6,'Tag(Glossary)'!$B:$G,4,0) -> String | H6: =VLOOKUP($D6,'Tag(Glossary)'!$B:$G,5,0) -> 3 | I6: =VLOOKUP($D6,'Tag(Glossary)'!$B:$H,6,0)&IF(ISBLANK(VLOOKUP($D6,'Tag(Glossary)'!$B:$H,7,0)),"",CHAR(10))&VLOOKUP($D6,'Tag(Glossary)'!$B:$H,7,0) -> ID for identifying the market <Hochiminh Exchange> - STO: HoSE Stock Market - BDO: HoSE Bond Market - RPO: HoSE Repo Market <Hanoi Exchange> - STX: HNX Listed Stock Market - BDX: HNX Government Bond Market - DVX: HNX Derivative Market - UPX: HNX UpCoM Stock Market - HCX: HNX Corporate Bond Market
B7: =INDEX('Interface List'!$D$7:$D$45,MATCH($C7,'Interface List'!$E$7:$E$45,0)) -> IFMDFIX0017 | C7: Investor per Industry(Derivatives) | D7: 60 | E7: =VLOOKUP($D7,'Tag(Glossary)'!$B:$G,2,0) -> TransactTime | F7: Y | G7: =VLOOKUP($D7,'Tag(Glossary)'!$B:$G,4,0) -> UTCTime | H7: =VLOOKUP($D7,'Tag(Glossary)'!$B:$G,5,0) -> 9 | I7: =VLOOKUP($D7,'Tag(Glossary)'!$B:$H,6,0)&IF(ISBLANK(VLOOKUP($D7,'Tag(Glossary)'!$B:$H,7,0)),"",CHAR(10))&VLOOKUP($D7,'Tag(Glossary)'!$B:$H,7,0) -> Time of execution/order creation HHmmSSsss : Normal Case
B8: =INDEX('Interface List'!$D$7:$D$45,MATCH($C8,'Interface List'!$E$7:$E$45,0)) -> IFMDFIX0017 | C8: Investor per Industry(Derivatives) | D8: 30604 | E8: =VLOOKUP($D8,'Tag(Glossary)'!$B:$G,2,0) -> SecurityGroupID | F8: Y | G8: =VLOOKUP($D8,'Tag(Glossary)'!$B:$G,4,0) -> String | H8: =VLOOKUP($D8,'Tag(Glossary)'!$B:$G,5,0) -> 2 | I8: =VLOOKUP($D8,'Tag(Glossary)'!$B:$H,6,0)&IF(ISBLANK(VLOOKUP($D8,'Tag(Glossary)'!$B:$H,7,0)),"",CHAR(10))&VLOOKUP($D8,'Tag(Glossary)'!$B:$H,7,0) -> Security group ID (Stock, Investment Trust, Futures, Option, etc.)
B9: =INDEX('Interface List'!$D$7:$D$45,MATCH($C9,'Interface List'!$E$7:$E$45,0)) -> IFMDFIX0017 | C9: Investor per Industry(Derivatives) | D9: 20000 | E9: =VLOOKUP($D9,'Tag(Glossary)'!$B:$G,2,0) -> InvestCode | F9: Y | G9: =VLOOKUP($D9,'Tag(Glossary)'!$B:$G,4,0) -> String | H9: =VLOOKUP($D9,'Tag(Glossary)'!$B:$G,5,0) -> 4 | I9: =VLOOKUP($D9,'Tag(Glossary)'!$B:$H,6,0)&IF(ISBLANK(VLOOKUP($D9,'Tag(Glossary)'!$B:$H,7,0)),"",CHAR(10))&VLOOKUP($D9,'Tag(Glossary)'!$B:$H,7,0) -> This field indicates which category the owner of a given order or quote belongs to. This field is validated against AccountType field as below: - If AccountType is Customer (1), any value is permitted for this field. - If AccountType is House (3), this field must be 1000. 1000 = Securities company 2000 = Insurance company 3000 = Asset management company and Investment company 3200 = Fund 4000 = Bank 5000 = General finance company 6000 = Pension Fund 7000 = Goverment representation 7030 = International organization 7100 = Misc corporation 8000 = Indivisual
B10: =INDEX('Interface List'!$D$7:$D$45,MATCH($C10,'Interface List'!$E$7:$E$45,0)) -> IFMDFIX0017 | C10: Investor per Industry(Derivatives) | D10: 331 | E10: =VLOOKUP($D10,'Tag(Glossary)'!$B:$G,2,0) -> SellVolume | F10: Y | G10: =VLOOKUP($D10,'Tag(Glossary)'!$B:$G,4,0) -> Int | H10: =VLOOKUP($D10,'Tag(Glossary)'!$B:$G,5,0) -> 12 | I10: =VLOOKUP($D10,'Tag(Glossary)'!$B:$H,6,0)&IF(ISBLANK(VLOOKUP($D10,'Tag(Glossary)'!$B:$H,7,0)),"",CHAR(10))&VLOOKUP($D10,'Tag(Glossary)'!$B:$H,7,0) -> Trading volume in sell side
B11: =INDEX('Interface List'!$D$7:$D$45,MATCH($C11,'Interface List'!$E$7:$E$45,0)) -> IFMDFIX0017 | C11: Investor per Industry(Derivatives) | D11: 30168 | E11: =VLOOKUP($D11,'Tag(Glossary)'!$B:$G,2,0) -> SellTradeAmount | F11: Y | G11: =VLOOKUP($D11,'Tag(Glossary)'!$B:$G,4,0) -> Float | H11: =VLOOKUP($D11,'Tag(Glossary)'!$B:$G,5,0) -> 23(18.4) | I11: =VLOOKUP($D11,'Tag(Glossary)'!$B:$H,6,0)&IF(ISBLANK(VLOOKUP($D11,'Tag(Glossary)'!$B:$H,7,0)),"",CHAR(10))&VLOOKUP($D11,'Tag(Glossary)'!$B:$H,7,0) -> Trading value in ask side
B12: =INDEX('Interface List'!$D$7:$D$45,MATCH($C12,'Interface List'!$E$7:$E$45,0)) -> IFMDFIX0017 | C12: Investor per Industry(Derivatives) | D12: 330 | E12: =VLOOKUP($D12,'Tag(Glossary)'!$B:$G,2,0) -> BuyVolume | F12: Y | G12: =VLOOKUP($D12,'Tag(Glossary)'!$B:$G,4,0) -> Int | H12: =VLOOKUP($D12,'Tag(Glossary)'!$B:$G,5,0) -> 12 | I12: =VLOOKUP($D12,'Tag(Glossary)'!$B:$H,6,0)&IF(ISBLANK(VLOOKUP($D12,'Tag(Glossary)'!$B:$H,7,0)),"",CHAR(10))&VLOOKUP($D12,'Tag(Glossary)'!$B:$H,7,0) -> Trading volume in buy side
B13: =INDEX('Interface List'!$D$7:$D$45,MATCH($C13,'Interface List'!$E$7:$E$45,0)) -> IFMDFIX0017 | C13: Investor per Industry(Derivatives) | D13: 30169 | E13: =VLOOKUP($D13,'Tag(Glossary)'!$B:$G,2,0) -> BuyTradedAmount | F13: Y | G13: =VLOOKUP($D13,'Tag(Glossary)'!$B:$G,4,0) -> Float | H13: =VLOOKUP($D13,'Tag(Glossary)'!$B:$G,5,0) -> 23(18.4) | I13: =VLOOKUP($D13,'Tag(Glossary)'!$B:$H,6,0)&IF(ISBLANK(VLOOKUP($D13,'Tag(Glossary)'!$B:$H,7,0)),"",CHAR(10))&VLOOKUP($D13,'Tag(Glossary)'!$B:$H,7,0) -> Trading value in bid side
B14: =INDEX('Interface List'!$D$7:$D$45,MATCH($C14,'Interface List'!$E$7:$E$45,0)) -> IFMDFIX0017 | C14: Investor per Industry(Derivatives) | E14: Standard Trailer | F14: Y

Sheet Investor per Symbol
B2: Investor per Symbol
B4: Interface ID | C4: Interface Name | D4: Tag | E4: Field Name | F4: Req'd | G4: Format | H4: Length | I4: Comments
B5: =INDEX('Interface List'!$D$7:$D$45,MATCH($C5,'Interface List'!$E$7:$E$45,0)) -> IFMDFIX0018 | C5: Investor per Symbol | E5: Standard Header | F5: Y | I5: MsgType = M3
B6: =INDEX('Interface List'!$D$7:$D$45,MATCH($C6,'Interface List'!$E$7:$E$45,0)) -> IFMDFIX0018 | C6: Investor per Symbol | D6: 30001 | E6: =VLOOKUP($D6,'Tag(Glossary)'!$B:$G,2,0) -> MarketID | F6: Y | G6: =VLOOKUP($D6,'Tag(Glossary)'!$B:$G,4,0) -> String | H6: =VLOOKUP($D6,'Tag(Glossary)'!$B:$G,5,0) -> 3 | I6: =VLOOKUP($D6,'Tag(Glossary)'!$B:$H,6,0)&IF(ISBLANK(VLOOKUP($D6,'Tag(Glossary)'!$B:$H,7,0)),"",CHAR(10))&VLOOKUP($D6,'Tag(Glossary)'!$B:$H,7,0) -> ID for identifying the market <Hochiminh Exchange> - STO: HoSE Stock Market - BDO: HoSE Bond Market - RPO: HoSE Repo Market <Hanoi Exchange> - STX: HNX Listed Stock Market - BDX: HNX Government Bond Market - DVX: HNX Derivative Market - UPX: HNX UpCoM Stock Market - HCX: HNX Corporate Bond Market
B7: =INDEX('Interface List'!$D$7:$D$45,MATCH($C7,'Interface List'!$E$7:$E$45,0)) -> IFMDFIX0018 | C7: Investor per Symbol | D7: 55 | E7: =VLOOKUP($D7,'Tag(Glossary)'!$B:$G,2,0) -> Symbol | F7: Y | G7: =VLOOKUP($D7,'Tag(Glossary)'!$B:$G,4,0) -> String | H7: =VLOOKUP($D7,'Tag(Glossary)'!$B:$G,5,0) -> 12 | I7: =VLOOKUP($D7,'Tag(Glossary)'!$B:$H,6,0)&IF(ISBLANK(VLOOKUP($D7,'Tag(Glossary)'!$B:$H,7,0)),"",CHAR(10))&VLOOKUP($D7,'Tag(Glossary)'!$B:$H,7,0) -> The unique code of an issue (a.k.a. instrument or symbol). Generally it is ISIN code but in case of Repo market it is defined as the exchange staffs want
B8: =INDEX('Interface List'!$D$7:$D$45,MATCH($C8,'Interface List'!$E$7:$E$45,0)) -> IFMDFIX0018 | C8: Investor per Symbol | D8: 20000 | E8: =VLOOKUP($D8,'Tag(Glossary)'!$B:$G,2,0) -> InvestCode | F8: Y | G8: =VLOOKUP($D8,'Tag(Glossary)'!$B:$G,4,0) -> String | H8: =VLOOKUP($D8,'Tag(Glossary)'!$B:$G,5,0) -> 4 | I8: =VLOOKUP($D8,'Tag(Glossary)'!$B:$H,6,0)&IF(ISBLANK(VLOOKUP($D8,'Tag(Glossary)'!$B:$H,7,0)),"",CHAR(10))&VLOOKUP($D8,'Tag(Glossary)'!$B:$H,7,0) -> This field indicates which category the owner of a given order or quote belongs to. This field is validated against AccountType field as below: - If AccountType is Customer (1), any value is permitted for this field. - If AccountType is House (3), this field must be 1000. 1000 = Securities company 2000 = Insurance company 3000 = Asset management company and Investment company 3200 = Fund 4000 = Bank 5000 = General finance company 6000 = Pension Fund 7000 = Goverment representation 7030 = International organization 7100 = Misc corporation 8000 = Indivisual
B9: =INDEX('Interface List'!$D$7:$D$45,MATCH($C9,'Interface List'!$E$7:$E$45,0)) -> IFMDFIX0018 | C9: Investor per Symbol | D9: 331 | E9: =VLOOKUP($D9,'Tag(Glossary)'!$B:$G,2,0) -> SellVolume | F9: Y | G9: =VLOOKUP($D9,'Tag(Glossary)'!$B:$G,4,0) -> Int | H9: =VLOOKUP($D9,'Tag(Glossary)'!$B:$G,5,0) -> 12 | I9: =VLOOKUP($D9,'Tag(Glossary)'!$B:$H,6,0)&IF(ISBLANK(VLOOKUP($D9,'Tag(Glossary)'!$B:$H,7,0)),"",CHAR(10))&VLOOKUP($D9,'Tag(Glossary)'!$B:$H,7,0) -> Trading volume in sell side
B10: =INDEX('Interface List'!$D$7:$D$45,MATCH($C10,'Interface List'!$E$7:$E$45,0)) -> IFMDFIX0018 | C10: Investor per Symbol | D10: 30168 | E10: =VLOOKUP($D10,'Tag(Glossary)'!$B:$G,2,0) -> SellTradeAmount | F10: Y | G10: =VLOOKUP($D10,'Tag(Glossary)'!$B:$G,4,0) -> Float | H10: =VLOOKUP($D10,'Tag(Glossary)'!$B:$G,5,0) -> 23(18.4) | I10: =VLOOKUP($D10,'Tag(Glossary)'!$B:$H,6,0)&IF(ISBLANK(VLOOKUP($D10,'Tag(Glossary)'!$B:$H,7,0)),"",CHAR(10))&VLOOKUP($D10,'Tag(Glossary)'!$B:$H,7,0) -> Trading value in ask side
B11: =INDEX('Interface List'!$D$7:$D$45,MATCH($C11,'Interface List'!$E$7:$E$45,0)) -> IFMDFIX0018 | C11: Investor per Symbol | D11: 330 | E11: =VLOOKUP($D11,'Tag(Glossary)'!$B:$G,2,0) -> BuyVolume | F11: Y | G11: =VLOOKUP($D11,'Tag(Glossary)'!$B:$G,4,0) -> Int | H11: =VLOOKUP($D11,'Tag(Glossary)'!$B:$G,5,0) -> 12 | I11: =VLOOKUP($D11,'Tag(Glossary)'!$B:$H,6,0)&IF(ISBLANK(VLOOKUP($D11,'Tag(Glossary)'!$B:$H,7,0)),"",CHAR(10))&VLOOKUP($D11,'Tag(Glossary)'!$B:$H,7,0) -> Trading volume in buy side
B12: =INDEX('Interface List'!$D$7:$D$45,MATCH($C12,'Interface List'!$E$7:$E$45,0)) -> IFMDFIX0018 | C12: Investor per Symbol | D12: 30169 | E12: =VLOOKUP($D12,'Tag(Glossary)'!$B:$G,2,0) -> BuyTradedAmount | F12: Y | G12: =VLOOKUP($D12,'Tag(Glossary)'!$B:$G,4,0) -> Float | H12: =VLOOKUP($D12,'Tag(Glossary)'!$B:$G,5,0) -> 23(18.4) | I12: =VLOOKUP($D12,'Tag(Glossary)'!$B:$H,6,0)&IF(ISBLANK(VLOOKUP($D12,'Tag(Glossary)'!$B:$H,7,0)),"",CHAR(10))&VLOOKUP($D12,'Tag(Glossary)'!$B:$H,7,0) -> Trading value in bid side
B13: =INDEX('Interface List'!$D$7:$D$45,MATCH($C13,'Interface List'!$E$7:$E$45,0)) -> IFMDFIX0018 | C13: Investor per Symbol | E13: Standard Trailer | F13: Y

Sheet Top N Members per Symbol
B2: Top N Members per Symbol
B4: Interface ID | C4: Interface Name | D4: Tag | E4: Field Name | F4: Req'd | G4: Format | H4: Length | I4: Comments
B5: =INDEX('Interface List'!$D$7:$D$45,MATCH($C5,'Interface List'!$E$7:$E$45,0)) -> IFMDFIX0019 | C5: Top N Members per Symbol | E5: Standard Header | F5: Y | I5: MsgType = M4
B6: =INDEX('Interface List'!$D$7:$D$45,MATCH($C6,'Interface List'!$E$7:$E$45,0)) -> IFMDFIX0019 | C6: Top N Members per Symbol | D6: 30001 | E6: =VLOOKUP($D6,'Tag(Glossary)'!$B:$G,2,0) -> MarketID | F6: Y | G6: =VLOOKUP($D6,'Tag(Glossary)'!$B:$G,4,0) -> String | H6: =VLOOKUP($D6,'Tag(Glossary)'!$B:$G,5,0) -> 3 | I6: =VLOOKUP($D6,'Tag(Glossary)'!$B:$H,6,0)&IF(ISBLANK(VLOOKUP($D6,'Tag(Glossary)'!$B:$H,7,0)),"",CHAR(10))&VLOOKUP($D6,'Tag(Glossary)'!$B:$H,7,0) -> ID for identifying the market <Hochiminh Exchange> - STO: HoSE Stock Market - BDO: HoSE Bond Market - RPO: HoSE Repo Market <Hanoi Exchange> - STX: HNX Listed Stock Market - BDX: HNX Government Bond Market - DVX: HNX Derivative Market - UPX: HNX UpCoM Stock Market - HCX: HNX Corporate Bond Market
B7: =INDEX('Interface List'!$D$7:$D$45,MATCH($C7,'Interface List'!$E$7:$E$45,0)) -> IFMDFIX0019 | C7: Top N Members per Symbol | D7: 55 | E7: =VLOOKUP($D7,'Tag(Glossary)'!$B:$G,2,0) -> Symbol | F7: Y | G7: =VLOOKUP($D7,'Tag(Glossary)'!$B:$G,4,0) -> String | H7: =VLOOKUP($D7,'Tag(Glossary)'!$B:$G,5,0) -> 12 | I7: =VLOOKUP($D7,'Tag(Glossary)'!$B:$H,6,0)&IF(ISBLANK(VLOOKUP($D7,'Tag(Glossary)'!$B:$H,7,0)),"",CHAR(10))&VLOOKUP($D7,'Tag(Glossary)'!$B:$H,7,0) -> The unique code of an issue (a.k.a. instrument or symbol). Generally it is ISIN code but in case of Repo market it is defined as the exchange staffs want
B8: =INDEX('Interface List'!$D$7:$D$45,MATCH($C8,'Interface List'!$E$7:$E$45,0)) -> IFMDFIX0019 | C8: Top N Members per Symbol | D8: 911 | E8: =VLOOKUP($D8,'Tag(Glossary)'!$B:$G,2,0) -> TotNumReports | F8: Y | G8: =VLOOKUP($D8,'Tag(Glossary)'!$B:$G,4,0) -> Int | H8: =VLOOKUP($D8,'Tag(Glossary)'!$B:$G,5,0) -> 16 | I8: =VLOOKUP($D8,'Tag(Glossary)'!$B:$H,6,0)&IF(ISBLANK(VLOOKUP($D8,'Tag(Glossary)'!$B:$H,7,0)),"",CHAR(10))&VLOOKUP($D8,'Tag(Glossary)'!$B:$H,7,0) -> Entire number of messages for issue information transmission or for a set of statistics results
B9: =INDEX('Interface List'!$D$7:$D$45,MATCH($C9,'Interface List'!$E$7:$E$45,0)) -> IFMDFIX0019 | C9: Top N Members per Symbol | D9: 30215 | E9: =VLOOKUP($D9,'Tag(Glossary)'!$B:$G,2,0) -> SellRankSeq | F9: Y | G9: =VLOOKUP($D9,'Tag(Glossary)'!$B:$G,4,0) -> Int | H9: =VLOOKUP($D9,'Tag(Glossary)'!$B:$G,5,0) -> 6 | I9: =VLOOKUP($D9,'Tag(Glossary)'!$B:$H,6,0)&IF(ISBLANK(VLOOKUP($D9,'Tag(Glossary)'!$B:$H,7,0)),"",CHAR(10))&VLOOKUP($D9,'Tag(Glossary)'!$B:$H,7,0) -> Sequence of rank in sell side
B10: =INDEX('Interface List'!$D$7:$D$45,MATCH($C10,'Interface List'!$E$7:$E$45,0)) -> IFMDFIX0019 | C10: Top N Members per Symbol | D10: 30213 | E10: =VLOOKUP($D10,'Tag(Glossary)'!$B:$G,2,0) -> SellMemberNo | F10: Y | G10: =VLOOKUP($D10,'Tag(Glossary)'!$B:$G,4,0) -> String | H10: =VLOOKUP($D10,'Tag(Glossary)'!$B:$G,5,0) -> 5 | I10: =VLOOKUP($D10,'Tag(Glossary)'!$B:$H,6,0)&IF(ISBLANK(VLOOKUP($D10,'Tag(Glossary)'!$B:$H,7,0)),"",CHAR(10))&VLOOKUP($D10,'Tag(Glossary)'!$B:$H,7,0) -> Member ID in sell side
B11: =INDEX('Interface List'!$D$7:$D$45,MATCH($C11,'Interface List'!$E$7:$E$45,0)) -> IFMDFIX0019 | C11: Top N Members per Symbol | D11: 331 | E11: =VLOOKUP($D11,'Tag(Glossary)'!$B:$G,2,0) -> SellVolume | F11: Y | G11: =VLOOKUP($D11,'Tag(Glossary)'!$B:$G,4,0) -> Int | H11: =VLOOKUP($D11,'Tag(Glossary)'!$B:$G,5,0) -> 12 | I11: =VLOOKUP($D11,'Tag(Glossary)'!$B:$H,6,0)&IF(ISBLANK(VLOOKUP($D11,'Tag(Glossary)'!$B:$H,7,0)),"",CHAR(10))&VLOOKUP($D11,'Tag(Glossary)'!$B:$H,7,0) -> Trading volume in sell side
B12: =INDEX('Interface List'!$D$7:$D$45,MATCH($C12,'Interface List'!$E$7:$E$45,0)) -> IFMDFIX0019 | C12: Top N Members per Symbol | D12: 30168 | E12: =VLOOKUP($D12,'Tag(Glossary)'!$B:$G,2,0) -> SellTradeAmount | F12: Y | G12: =VLOOKUP($D12,'Tag(Glossary)'!$B:$G,4,0) -> Float | H12: =VLOOKUP($D12,'Tag(Glossary)'!$B:$G,5,0) -> 23(18.4) | I12: =VLOOKUP($D12,'Tag(Glossary)'!$B:$H,6,0)&IF(ISBLANK(VLOOKUP($D12,'Tag(Glossary)'!$B:$H,7,0)),"",CHAR(10))&VLOOKUP($D12,'Tag(Glossary)'!$B:$H,7,0) -> Trading value in ask side
B13: =INDEX('Interface List'!$D$7:$D$45,MATCH($C13,'Interface List'!$E$7:$E$45,0)) -> IFMDFIX0019 | C13: Top N Members per Symbol | D13: 30216 | E13: =VLOOKUP($D13,'Tag(Glossary)'!$B:$G,2,0) -> BuyRankSeq | F13: Y | G13: =VLOOKUP($D13,'Tag(Glossary)'!$B:$G,4,0) -> Int | H13: =VLOOKUP($D13,'Tag(Glossary)'!$B:$G,5,0) -> 6 | I13: =VLOOKUP($D13,'Tag(Glossary)'!$B:$H,6,0)&IF(ISBLANK(VLOOKUP($D13,'Tag(Glossary)'!$B:$H,7,0)),"",CHAR(10))&VLOOKUP($D13,'Tag(Glossary)'!$B:$H,7,0) -> Sequence of rank in buy side
B14: =INDEX('Interface List'!$D$7:$D$45,MATCH($C14,'Interface List'!$E$7:$E$45,0)) -> IFMDFIX0019 | C14: Top N Members per Symbol | D14: 30214 | E14: =VLOOKUP($D14,'Tag(Glossary)'!$B:$G,2,0) -> BuyMemberNo | F14: Y | G14: =VLOOKUP($D14,'Tag(Glossary)'!$B:$G,4,0) -> String | H14: =VLOOKUP($D14,'Tag(Glossary)'!$B:$G,5,0) -> 5 | I14: =VLOOKUP($D14,'Tag(Glossary)'!$B:$H,6,0)&IF(ISBLANK(VLOOKUP($D14,'Tag(Glossary)'!$B:$H,7,0)),"",CHAR(10))&VLOOKUP($D14,'Tag(Glossary)'!$B:$H,7,0) -> Member ID in buy side
B15: =INDEX('Interface List'!$D$7:$D$45,MATCH($C15,'Interface List'!$E$7:$E$45,0)) -> IFMDFIX0019 | C15: Top N Members per Symbol | D15: 330 | E15: =VLOOKUP($D15,'Tag(Glossary)'!$B:$G,2,0) -> BuyVolume | F15: Y | G15: =VLOOKUP($D15,'Tag(Glossary)'!$B:$G,4,0) -> Int | H15: =VLOOKUP($D15,'Tag(Glossary)'!$B:$G,5,0) -> 12 | I15: =VLOOKUP($D15,'Tag(Glossary)'!$B:$H,6,0)&IF(ISBLANK(VLOOKUP($D15,'Tag(Glossary)'!$B:$H,7,0)),"",CHAR(10))&VLOOKUP($D15,'Tag(Glossary)'!$B:$H,7,0) -> Trading volume in buy side
B16: =INDEX('Interface List'!$D$7:$D$45,MATCH($C16,'Interface List'!$E$7:$E$45,0)) -> IFMDFIX0019 | C16: Top N Members per Symbol | D16: 30169 | E16: =VLOOKUP($D16,'Tag(Glossary)'!$B:$G,2,0) -> BuyTradedAmount | F16: Y | G16: =VLOOKUP($D16,'Tag(Glossary)'!$B:$G,4,0) -> Float | H16: =VLOOKUP($D16,'Tag(Glossary)'!$B:$G,5,0) -> 23(18.4) | I16: =VLOOKUP($D16,'Tag(Glossary)'!$B:$H,6,0)&IF(ISBLANK(VLOOKUP($D16,'Tag(Glossary)'!$B:$H,7,0)),"",CHAR(10))&VLOOKUP($D16,'Tag(Glossary)'!$B:$H,7,0) -> Trading value in bid side
B17: =INDEX('Interface List'!$D$7:$D$45,MATCH($C17,'Interface List'!$E$7:$E$45,0)) -> IFMDFIX0019 | C17: Top N Members per Symbol | E17: Standard Trailer | F17: Y

Sheet Open Interest
B2: Open Interest
B4: Interface ID | C4: Interface Name | D4: Tag | E4: Field Name | F4: Req'd | G4: Format | H4: Length | I4: Comments
B5: =INDEX('Interface List'!$D$7:$D$45,MATCH($C5,'Interface List'!$E$7:$E$45,0)) -> IFMDFIX0020 | C5: Open Interest | E5: Standard Header | F5: Y | I5: MsgType = MA
B6: =INDEX('Interface List'!$D$7:$D$45,MATCH($C6,'Interface List'!$E$7:$E$45,0)) -> IFMDFIX0020 | C6: Open Interest | D6: 30001 | E6: =VLOOKUP($D6,'Tag(Glossary)'!$B:$G,2,0) -> MarketID | F6: Y | G6: =VLOOKUP($D6,'Tag(Glossary)'!$B:$G,4,0) -> String | H6: =VLOOKUP($D6,'Tag(Glossary)'!$B:$G,5,0) -> 3 | I6: =VLOOKUP($D6,'Tag(Glossary)'!$B:$H,6,0)&IF(ISBLANK(VLOOKUP($D6,'Tag(Glossary)'!$B:$H,7,0)),"",CHAR(10))&VLOOKUP($D6,'Tag(Glossary)'!$B:$H,7,0) -> ID for identifying the market <Hochiminh Exchange> - STO: HoSE Stock Market - BDO: HoSE Bond Market - RPO: HoSE Repo Market <Hanoi Exchange> - STX: HNX Listed Stock Market - BDX: HNX Government Bond Market - DVX: HNX Derivative Market - UPX: HNX UpCoM Stock Market - HCX: HNX Corporate Bond Market
B7: =INDEX('Interface List'!$D$7:$D$45,MATCH($C7,'Interface List'!$E$7:$E$45,0)) -> IFMDFIX0020 | C7: Open Interest | D7: 55 | E7: =VLOOKUP($D7,'Tag(Glossary)'!$B:$G,2,0) -> Symbol | F7: Y | G7: =VLOOKUP($D7,'Tag(Glossary)'!$B:$G,4,0) -> String | H7: =VLOOKUP($D7,'Tag(Glossary)'!$B:$G,5,0) -> 12 | I7: =VLOOKUP($D7,'Tag(Glossary)'!$B:$H,6,0)&IF(ISBLANK(VLOOKUP($D7,'Tag(Glossary)'!$B:$H,7,0)),"",CHAR(10))&VLOOKUP($D7,'Tag(Glossary)'!$B:$H,7,0) -> The unique code of an issue (a.k.a. instrument or symbol). Generally it is ISIN code but in case of Repo market it is defined as the exchange staffs want
B8: =INDEX('Interface List'!$D$7:$D$45,MATCH($C8,'Interface List'!$E$7:$E$45,0)) -> IFMDFIX0020 | C8: Open Interest | D8: 75 | E8: =VLOOKUP($D8,'Tag(Glossary)'!$B:$G,2,0) -> TradeDate | F8: Y | G8: =VLOOKUP($D8,'Tag(Glossary)'!$B:$G,4,0) -> LocalMktDate | H8: =VLOOKUP($D8,'Tag(Glossary)'!$B:$G,5,0) -> 8 | I8: =VLOOKUP($D8,'Tag(Glossary)'!$B:$H,6,0)&IF(ISBLANK(VLOOKUP($D8,'Tag(Glossary)'!$B:$H,7,0)),"",CHAR(10))&VLOOKUP($D8,'Tag(Glossary)'!$B:$H,7,0) -> Indicates local date of trade refereneced in this message in YYYYMMDD format. YYYYMMDD
B9: =INDEX('Interface List'!$D$7:$D$45,MATCH($C9,'Interface List'!$E$7:$E$45,0)) -> IFMDFIX0020 | C9: Open Interest | D9: 30540 | E9: =VLOOKUP($D9,'Tag(Glossary)'!$B:$G,2,0) -> OpenInterestQty | F9: Y | G9: =VLOOKUP($D9,'Tag(Glossary)'!$B:$G,4,0) -> Number | H9: =VLOOKUP($D9,'Tag(Glossary)'!$B:$G,5,0) -> 10 | I9: =VLOOKUP($D9,'Tag(Glossary)'!$B:$H,6,0)&IF(ISBLANK(VLOOKUP($D9,'Tag(Glossary)'!$B:$H,7,0)),"",CHAR(10))&VLOOKUP($D9,'Tag(Glossary)'!$B:$H,7,0) -> Open interest quantity
B10: =INDEX('Interface List'!$D$7:$D$45,MATCH($C10,'Interface List'!$E$7:$E$45,0)) -> IFMDFIX0020 | C10: Open Interest | D10: 30573 | E10: =VLOOKUP($D10,'Tag(Glossary)'!$B:$G,2,0) -> SettlementPrice | F10: Y | G10: =VLOOKUP($D10,'Tag(Glossary)'!$B:$G,4,0) -> Price | H10: =VLOOKUP($D10,'Tag(Glossary)'!$B:$G,5,0) -> 18(9.8) | I10: =VLOOKUP($D10,'Tag(Glossary)'!$B:$H,6,0)&IF(ISBLANK(VLOOKUP($D10,'Tag(Glossary)'!$B:$H,7,0)),"",CHAR(10))&VLOOKUP($D10,'Tag(Glossary)'!$B:$H,7,0) -> Settlement price. It will be the reference price of tomorrow of a future instrument when it has any trade since its listing
B11: =INDEX('Interface List'!$D$7:$D$45,MATCH($C11,'Interface List'!$E$7:$E$45,0)) -> IFMDFIX0020 | C11: Open Interest | E11: Standard Trailer | F11: Y

Sheet Deem Trade Price
B2: Deem Trade Price
B4: Interface ID | C4: Interface Name | D4: Tag | E4: Field Name | F4: Req'd | G4: Format | H4: Length | I4: Comments
B5: =INDEX('Interface List'!$D$7:$D$45,MATCH($C5,'Interface List'!$E$7:$E$45,0)) -> IFMDFIX0021 | C5: Deem Trade Price | E5: Standard Header | F5: Y | I5: MsgType = ME
B6: =INDEX('Interface List'!$D$7:$D$45,MATCH($C6,'Interface List'!$E$7:$E$45,0)) -> IFMDFIX0021 | C6: Deem Trade Price | D6: 30001 | E6: =VLOOKUP($D6,'Tag(Glossary)'!$B:$G,2,0) -> MarketID | F6: Y | G6: =VLOOKUP($D6,'Tag(Glossary)'!$B:$G,4,0) -> String | H6: =VLOOKUP($D6,'Tag(Glossary)'!$B:$G,5,0) -> 3 | I6: =VLOOKUP($D6,'Tag(Glossary)'!$B:$H,6,0)&IF(ISBLANK(VLOOKUP($D6,'Tag(Glossary)'!$B:$H,7,0)),"",CHAR(10))&VLOOKUP($D6,'Tag(Glossary)'!$B:$H,7,0) -> ID for identifying the market <Hochiminh Exchange> - STO: HoSE Stock Market - BDO: HoSE Bond Market - RPO: HoSE Repo Market <Hanoi Exchange> - STX: HNX Listed Stock Market - BDX: HNX Government Bond Market - DVX: HNX Derivative Market - UPX: HNX UpCoM Stock Market - HCX: HNX Corporate Bond Market
B7: =INDEX('Interface List'!$D$7:$D$45,MATCH($C7,'Interface List'!$E$7:$E$45,0)) -> IFMDFIX0021 | C7: Deem Trade Price | D7: 20004 | E7: =VLOOKUP($D7,'Tag(Glossary)'!$B:$G,2,0) -> BoardID | F7: Y | G7: =VLOOKUP($D7,'Tag(Glossary)'!$B:$G,4,0) -> String | H7: =VLOOKUP($D7,'Tag(Glossary)'!$B:$G,5,0) -> 2 | I7: =VLOOKUP($D7,'Tag(Glossary)'!$B:$H,6,0)&IF(ISBLANK(VLOOKUP($D7,'Tag(Glossary)'!$B:$H,7,0)),"",CHAR(10))&VLOOKUP($D7,'Tag(Glossary)'!$B:$H,7,0) -> Unique identifier to a Board where a given instrument is traded G1 : Main G2 : Pre open G3 : Post closing G4 : Odd lot G7 : Buy-in G8 : Sell-out T1 : Negotiation (regular) T4 : Negotiation (regular for Odd lot) T2 : Negotiation (pre) T3 : Negotiation (post) T6 : Negotiation (post for Odd lot) R1 : Negotiation (Repo) AL : All Boards
B8: =INDEX('Interface List'!$D$7:$D$45,MATCH($C8,'Interface List'!$E$7:$E$45,0)) -> IFMDFIX0021 | C8: Deem Trade Price | D8: 55 | E8: =VLOOKUP($D8,'Tag(Glossary)'!$B:$G,2,0) -> Symbol | F8: Y | G8: =VLOOKUP($D8,'Tag(Glossary)'!$B:$G,4,0) -> String | H8: =VLOOKUP($D8,'Tag(Glossary)'!$B:$G,5,0) -> 12 | I8: =VLOOKUP($D8,'Tag(Glossary)'!$B:$H,6,0)&IF(ISBLANK(VLOOKUP($D8,'Tag(Glossary)'!$B:$H,7,0)),"",CHAR(10))&VLOOKUP($D8,'Tag(Glossary)'!$B:$H,7,0) -> The unique code of an issue (a.k.a. instrument or symbol). Generally it is ISIN code but in case of Repo market it is defined as the exchange staffs want
B9: =INDEX('Interface List'!$D$7:$D$45,MATCH($C9,'Interface List'!$E$7:$E$45,0)) -> IFMDFIX0021 | C9: Deem Trade Price | D9: 30552 | E9: =VLOOKUP($D9,'Tag(Glossary)'!$B:$G,2,0) -> ExpectedTradePx | F9: Y | G9: =VLOOKUP($D9,'Tag(Glossary)'!$B:$G,4,0) -> Price | H9: =VLOOKUP($D9,'Tag(Glossary)'!$B:$G,5,0) -> 15(9.4) | I9: =VLOOKUP($D9,'Tag(Glossary)'!$B:$H,6,0)&IF(ISBLANK(VLOOKUP($D9,'Tag(Glossary)'!$B:$H,7,0)),"",CHAR(10))&VLOOKUP($D9,'Tag(Glossary)'!$B:$H,7,0) -> Deemed trading price
B10: =INDEX('Interface List'!$D$7:$D$45,MATCH($C10,'Interface List'!$E$7:$E$45,0)) -> IFMDFIX0021 | C10: Deem Trade Price | D10: 30553 | E10: =VLOOKUP($D10,'Tag(Glossary)'!$B:$G,2,0) -> ExpectedTradeQty | F10: Y | G10: =VLOOKUP($D10,'Tag(Glossary)'!$B:$G,4,0) -> Int | H10: =VLOOKUP($D10,'Tag(Glossary)'!$B:$G,5,0) -> 12 | I10: =VLOOKUP($D10,'Tag(Glossary)'!$B:$H,6,0)&IF(ISBLANK(VLOOKUP($D10,'Tag(Glossary)'!$B:$H,7,0)),"",CHAR(10))&VLOOKUP($D10,'Tag(Glossary)'!$B:$H,7,0)
B11: =INDEX('Interface List'!$D$7:$D$45,MATCH($C11,'Interface List'!$E$7:$E$45,0)) -> IFMDFIX0021 | C11: Deem Trade Price | D11: 30554 | E11: =VLOOKUP($D11,'Tag(Glossary)'!$B:$G,2,0) -> ExpectedTradeYield | F11: N | G11: =VLOOKUP($D11,'Tag(Glossary)'!$B:$G,4,0) -> Float | H11: =VLOOKUP($D11,'Tag(Glossary)'!$B:$G,5,0) -> 13(5.6) | I11: =VLOOKUP($D11,'Tag(Glossary)'!$B:$H,6,0)&IF(ISBLANK(VLOOKUP($D11,'Tag(Glossary)'!$B:$H,7,0)),"",CHAR(10))&VLOOKUP($D11,'Tag(Glossary)'!$B:$H,7,0) -> Yield of deemed trading price
B12: =INDEX('Interface List'!$D$7:$D$45,MATCH($C12,'Interface List'!$E$7:$E$45,0)) -> IFMDFIX0021 | C12: Deem Trade Price | E12: Standard Trailer | F12: Y

Sheet Foreigner Order Limit
B2: Foreigner Order Limit
B4: Interface ID | C4: Interface Name | D4: Tag | E4: Field Name | F4: Req'd | G4: Format | H4: Length | I4: Comments
B5: =INDEX('Interface List'!$D$7:$D$45,MATCH($C5,'Interface List'!$E$7:$E$45,0)) -> IFMDFIX0022 | C5: Foreigner Order Limit | E5: Standard Header | F5: Y | I5: MsgType = MF
B6: =INDEX('Interface List'!$D$7:$D$45,MATCH($C6,'Interface List'!$E$7:$E$45,0)) -> IFMDFIX0022 | C6: Foreigner Order Limit | D6: 30001 | E6: =VLOOKUP($D6,'Tag(Glossary)'!$B:$G,2,0) -> MarketID | F6: Y | G6: =VLOOKUP($D6,'Tag(Glossary)'!$B:$G,4,0) -> String | H6: =VLOOKUP($D6,'Tag(Glossary)'!$B:$G,5,0) -> 3 | I6: =VLOOKUP($D6,'Tag(Glossary)'!$B:$H,6,0)&IF(ISBLANK(VLOOKUP($D6,'Tag(Glossary)'!$B:$H,7,0)),"",CHAR(10))&VLOOKUP($D6,'Tag(Glossary)'!$B:$H,7,0) -> ID for identifying the market <Hochiminh Exchange> - STO: HoSE Stock Market - BDO: HoSE Bond Market - RPO: HoSE Repo Market <Hanoi Exchange> - STX: HNX Listed Stock Market - BDX: HNX Government Bond Market - DVX: HNX Derivative Market - UPX: HNX UpCoM Stock Market - HCX: HNX Corporate Bond Market
B7: =INDEX('Interface List'!$D$7:$D$45,MATCH($C7,'Interface List'!$E$7:$E$45,0)) -> IFMDFIX0022 | C7: Foreigner Order Limit | D7: 55 | E7: =VLOOKUP($D7,'Tag(Glossary)'!$B:$G,2,0) -> Symbol | F7: Y | G7: =VLOOKUP($D7,'Tag(Glossary)'!$B:$G,4,0) -> String | H7: =VLOOKUP($D7,'Tag(Glossary)'!$B:$G,5,0) -> 12 | I7: =VLOOKUP($D7,'Tag(Glossary)'!$B:$H,6,0)&IF(ISBLANK(VLOOKUP($D7,'Tag(Glossary)'!$B:$H,7,0)),"",CHAR(10))&VLOOKUP($D7,'Tag(Glossary)'!$B:$H,7,0) -> The unique code of an issue (a.k.a. instrument or symbol). Generally it is ISIN code but in case of Repo market it is defined as the exchange staffs want
B8: =INDEX('Interface List'!$D$7:$D$45,MATCH($C8,'Interface List'!$E$7:$E$45,0)) -> IFMDFIX0022 | C8: Foreigner Order Limit | D8: 30557 | E8: =VLOOKUP($D8,'Tag(Glossary)'!$B:$G,2,0) -> ForeignerBuyPosblQty | F8: Y | G8: =VLOOKUP($D8,'Tag(Glossary)'!$B:$G,4,0) -> Int | H8: =VLOOKUP($D8,'Tag(Glossary)'!$B:$G,5,0) -> 15 | I8: =VLOOKUP($D8,'Tag(Glossary)'!$B:$H,6,0)&IF(ISBLANK(VLOOKUP($D8,'Tag(Glossary)'!$B:$H,7,0)),"",CHAR(10))&VLOOKUP($D8,'Tag(Glossary)'!$B:$H,7,0) -> Maximum number of shares allocated for foreign investors to buy. It is well known as "Total Room"
B9: =INDEX('Interface List'!$D$7:$D$45,MATCH($C9,'Interface List'!$E$7:$E$45,0)) -> IFMDFIX0022 | C9: Foreigner Order Limit | D9: 30558 | E9: =VLOOKUP($D9,'Tag(Glossary)'!$B:$G,2,0) -> ForeignerOrderLimitQty | F9: Y | G9: =VLOOKUP($D9,'Tag(Glossary)'!$B:$G,4,0) -> Int | H9: =VLOOKUP($D9,'Tag(Glossary)'!$B:$G,5,0) -> 16 | I9: =VLOOKUP($D9,'Tag(Glossary)'!$B:$H,6,0)&IF(ISBLANK(VLOOKUP($D9,'Tag(Glossary)'!$B:$H,7,0)),"",CHAR(10))&VLOOKUP($D9,'Tag(Glossary)'!$B:$H,7,0) -> Number of shares available for investors to buy at that time. It is well-known as “Current Room”. Current Room = Total Room – Foreigner Holding Shares
B10: =INDEX('Interface List'!$D$7:$D$45,MATCH($C10,'Interface List'!$E$7:$E$45,0)) -> IFMDFIX0022 | C10: Foreigner Order Limit | E10: Standard Trailer | F10: Y

Sheet Price Limit Expansion
B2: Price Limit Expansion
B4: Interface ID | C4: Interface Name | D4: Tag | E4: Field Name | F4: Req'd | G4: Format | H4: Length | I4: Comments
B5: =INDEX('Interface List'!$D$7:$D$45,MATCH($C5,'Interface List'!$E$7:$E$45,0)) -> IFMDFIX0024 | C5: Price Limit Expansion | E5: Standard Header | F5: Y | I5: MsgType = MX
B6: =INDEX('Interface List'!$D$7:$D$45,MATCH($C6,'Interface List'!$E$7:$E$45,0)) -> IFMDFIX0024 | C6: Price Limit Expansion | D6: 30001 | E6: =VLOOKUP($D6,'Tag(Glossary)'!$B:$G,2,0) -> MarketID | F6: Y | G6: =VLOOKUP($D6,'Tag(Glossary)'!$B:$G,4,0) -> String | H6: =VLOOKUP($D6,'Tag(Glossary)'!$B:$G,5,0) -> 3 | I6: =VLOOKUP($D6,'Tag(Glossary)'!$B:$H,6,0)&IF(ISBLANK(VLOOKUP($D6,'Tag(Glossary)'!$B:$H,7,0)),"",CHAR(10))&VLOOKUP($D6,'Tag(Glossary)'!$B:$H,7,0) -> ID for identifying the market <Hochiminh Exchange> - STO: HoSE Stock Market - BDO: HoSE Bond Market - RPO: HoSE Repo Market <Hanoi Exchange> - STX: HNX Listed Stock Market - BDX: HNX Government Bond Market - DVX: HNX Derivative Market - UPX: HNX UpCoM Stock Market - HCX: HNX Corporate Bond Market
B7: =INDEX('Interface List'!$D$7:$D$45,MATCH($C7,'Interface List'!$E$7:$E$45,0)) -> IFMDFIX0024 | C7: Price Limit Expansion | D7: 20004 | E7: =VLOOKUP($D7,'Tag(Glossary)'!$B:$G,2,0) -> BoardID | F7: Y | G7: =VLOOKUP($D7,'Tag(Glossary)'!$B:$G,4,0) -> String | H7: =VLOOKUP($D7,'Tag(Glossary)'!$B:$G,5,0) -> 2 | I7: =VLOOKUP($D7,'Tag(Glossary)'!$B:$H,6,0)&IF(ISBLANK(VLOOKUP($D7,'Tag(Glossary)'!$B:$H,7,0)),"",CHAR(10))&VLOOKUP($D7,'Tag(Glossary)'!$B:$H,7,0) -> Unique identifier to a Board where a given instrument is traded G1 : Main G2 : Pre open G3 : Post closing G4 : Odd lot G7 : Buy-in G8 : Sell-out T1 : Negotiation (regular) T4 : Negotiation (regular for Odd lot) T2 : Negotiation (pre) T3 : Negotiation (post) T6 : Negotiation (post for Odd lot) R1 : Negotiation (Repo) AL : All Boards
B8: =INDEX('Interface List'!$D$7:$D$45,MATCH($C8,'Interface List'!$E$7:$E$45,0)) -> IFMDFIX0024 | C8: Price Limit Expansion | D8: 55 | E8: =VLOOKUP($D8,'Tag(Glossary)'!$B:$G,2,0) -> Symbol | F8: Y | G8: =VLOOKUP($D8,'Tag(Glossary)'!$B:$G,4,0) -> String | H8: =VLOOKUP($D8,'Tag(Glossary)'!$B:$G,5,0) -> 12 | I8: =VLOOKUP($D8,'Tag(Glossary)'!$B:$H,6,0)&IF(ISBLANK(VLOOKUP($D8,'Tag(Glossary)'!$B:$H,7,0)),"",CHAR(10))&VLOOKUP($D8,'Tag(Glossary)'!$B:$H,7,0) -> The unique code of an issue (a.k.a. instrument or symbol). Generally it is ISIN code but in case of Repo market it is defined as the exchange staffs want
B9: =INDEX('Interface List'!$D$7:$D$45,MATCH($C9,'Interface List'!$E$7:$E$45,0)) -> IFMDFIX0024 | C9: Price Limit Expansion | D9: 60 | E9: =VLOOKUP($D9,'Tag(Glossary)'!$B:$G,2,0) -> TransactTime | F9: Y | G9: =VLOOKUP($D9,'Tag(Glossary)'!$B:$G,4,0) -> UTCTime | H9: =VLOOKUP($D9,'Tag(Glossary)'!$B:$G,5,0) -> 9 | I9: =VLOOKUP($D9,'Tag(Glossary)'!$B:$H,6,0)&IF(ISBLANK(VLOOKUP($D9,'Tag(Glossary)'!$B:$H,7,0)),"",CHAR(10))&VLOOKUP($D9,'Tag(Glossary)'!$B:$H,7,0) -> Time of execution/order creation HHmmSSsss : Normal Case
B10: =INDEX('Interface List'!$D$7:$D$45,MATCH($C10,'Interface List'!$E$7:$E$45,0)) -> IFMDFIX0024 | C10: Price Limit Expansion | D10: 30649 | E10: PleUpLmtStep | F10: N | G10: Int | H10: 2 | I10: =VLOOKUP($D10,'Tag(Glossary)'!$B:$H,6,0)&IF(ISBLANK(VLOOKUP($D10,'Tag(Glossary)'!$B:$H,7,0)),"",CHAR(10))&VLOOKUP($D10,'Tag(Glossary)'!$B:$H,7,0) -> Final step number of PLE in the upper side actually triggered intraday
B11: =INDEX('Interface List'!$D$7:$D$45,MATCH($C11,'Interface List'!$E$7:$E$45,0)) -> IFMDFIX0024 | C11: Price Limit Expansion | D11: 30650 | E11: PleLwLmtStep | F11: N | G11: Int | H11: 2 | I11: =VLOOKUP($D11,'Tag(Glossary)'!$B:$H,6,0)&IF(ISBLANK(VLOOKUP($D11,'Tag(Glossary)'!$B:$H,7,0)),"",CHAR(10))&VLOOKUP($D11,'Tag(Glossary)'!$B:$H,7,0) -> Final step number of PLE in the lower side actually triggered intraday
B12: =INDEX('Interface List'!$D$7:$D$45,MATCH($C12,'Interface List'!$E$7:$E$45,0)) -> IFMDFIX0024 | C12: Price Limit Expansion | D12: 1149 | E12: =VLOOKUP($D12,'Tag(Glossary)'!$B:$G,2,0) -> HighLimitPrice | F12: Y | G12: =VLOOKUP($D12,'Tag(Glossary)'!$B:$G,4,0) -> Price | H12: =VLOOKUP($D12,'Tag(Glossary)'!$B:$G,5,0) -> 15(9.4) | I12: =VLOOKUP($D12,'Tag(Glossary)'!$B:$H,6,0)&IF(ISBLANK(VLOOKUP($D12,'Tag(Glossary)'!$B:$H,7,0)),"",CHAR(10))&VLOOKUP($D12,'Tag(Glossary)'!$B:$H,7,0) -> Available high limit price for the tradig day
B13: =INDEX('Interface List'!$D$7:$D$45,MATCH($C13,'Interface List'!$E$7:$E$45,0)) -> IFMDFIX0024 | C13: Price Limit Expansion | D13: 1148 | E13: =VLOOKUP($D13,'Tag(Glossary)'!$B:$G,2,0) -> LowLimitPrice | F13: Y | G13: =VLOOKUP($D13,'Tag(Glossary)'!$B:$G,4,0) -> Price | H13: =VLOOKUP($D13,'Tag(Glossary)'!$B:$G,5,0) -> 15(9.4) | I13: =VLOOKUP($D13,'Tag(Glossary)'!$B:$H,6,0)&IF(ISBLANK(VLOOKUP($D13,'Tag(Glossary)'!$B:$H,7,0)),"",CHAR(10))&VLOOKUP($D13,'Tag(Glossary)'!$B:$H,7,0) -> Available low limit price for the tradig day
B14: =INDEX('Interface List'!$D$7:$D$45,MATCH($C14,'Interface List'!$E$7:$E$45,0)) -> IFMDFIX0024 | C14: Price Limit Expansion | E14: Standard Trailer | F14: Y

Sheet ETF iNav
B2: ETF iNav
B4: Interface ID | C4: Interface Name | D4: Tag | E4: Field Name | F4: Req'd | G4: Format | H4: Length | I4: Comments
